Workbook

Sheet START HERE
B1: How to work the list
A3: 1 | B3: Open your tab | C3: RAM or SHYAM. Start at row 1.
A4: 2 | B4: Do what column G says | C4: Click Call. Then book, or send the WhatsApp, as column G says.
A5: 3 | B5: Log it | C5: Go to LOG. Add ONE line: time (Ctrl+Shift+;), your name, the phone, the outcome. Request ID only if the answer is about one of their requests.
A6: 4 | B6: Repeat | C6: Go back to your tab. The row you finished goes away and the next one moves up.
B8: Which outcome?
B9: Outcome | C9: When
B10: NO_ANSWER | C10: Called, no answer. You sent the WhatsApp.
B11: CALL_BACK | C11: They picked up but asked you to call later.
B12: BOOKED | C12: You booked the interview for them in the partner's calendar.
B13: SENT_LINK | C13: They said yes; you sent the partner's booking link. NOT a booking: it counts only once they book.
B14: NOT_INTERESTED | C14: They no longer want this interview.
B15: STOP | C15: They asked us to stop contacting them.
B16: WRONG_NUMBER | C16: Wrong number, or not their WhatsApp.
B17: SELF_BOOKED | C17: Their booking is already in the partner's calendar (they did it).
B18: NO_SLOTS | C18: The partner's calendar has no free time. Write that request's ID in E.
B20: Good to know
B21: Two requests, two answers | C21: Yes to one, no to the other? Write two lines: BOOKED and NOT_INTERESTED, each with its request ID (R0..) in column E. Copy the ID from column D of your list. Blank E means all their open requests.
B22: Link sent is not booked | C22: SENT_LINK only means they have the link. The row comes back later so you can check it was booked.
B23: Someone replies later | C23: Type their phone in the yellow box at the top of your tab ("Reply or call-back? Phone"). It shows what to book.
B24: Orange cell in LOG | C24: Something is wrong with that line. Column J says what. Fix it.
B25: Yellow row | C25: Less than 4 hours left. These rows are already at the top.
B26: Never | C26: Contact anyone before 10:00 or after 21:00. Promise anything about the job or the salary. Change other tabs.
B27: Not sure? | C27: Write it in Notes and ask your lead.

Sheet RAM
A1: RAM: your list. Start at the top. Do what column G says.
B2: Ram | C2: Time now | D2: =SETTINGS!$B$4 -> 46309.828 | G2: =C3&" people waiting" -> 0 people waiting | N2: =SETTINGS!$B$14 -> 4
A3: =IF(ROUND(MOD(SETTINGS!$B$4,1)*1440,0)<ROUND(SETTINGS!$B$9*1440,0),"Your shift has not started. Nothing to do yet.",IF(ROUND(MOD(SETTINGS!$B$4,1)*1440,0)>=ROUND(SETTINGS!$B$10*1440,0),"Your shift is over. Thank you!",IF($C$3=0,"Nothing waiting right now. Check LOG column J for lines marked in orange.",""))) -> Your shift is over. Thank you! | C3: =SUMPRODUCT((DESK!$Z$2:$Z$601=$B$2)*(DESK!$AI$2:$AI$601<>"")) -> 0
A4: Reply or call-back? Phone: | E4: =IF($D$4="","",IF(IFERROR(MATCH($D$4&"|1",DESK!$AJ$2:$AJ$601,0),"")="","Not on the open list (already done, or wrong number).",INDEX(DESK!$AW$2:$AW$601,IFERROR(MATCH($D$4&"|1",DESK!$AJ$2:$AJ$601,0),""))&" "&INDEX(DESK!$B$2:$B$601,IFERROR(MATCH($D$4&"|1",DESK!$AJ$2:$AJ$601,0),""))&" "&INDEX(DESK!$G$2:$G$601,IFERROR(MATCH($D$4&"|1",DESK!$AJ$2:$AJ$601,0),""))&IF(IFERROR(MATCH($D$4&"|2",DESK!$AJ$2:$AJ$601,0),"")="","","; "&INDEX(DESK!$AW$2:$AW$601,IFERROR(MATCH($D$4&"|2",DESK!$AJ$2:$AJ$601,0),""))&" "&INDEX(DESK!$B$2:$B$601,IFERROR(MATCH($D$4&"|2",DESK!$AJ$2:$AJ$601,0),""))&" "&INDEX(DESK!$G$2:$G$601,IFERROR(MATCH($D$4&"|2",DESK!$AJ$2:$AJ$601,0),"")))&IF(IFERROR(MATCH($D$4&"|3",DESK!$AJ$2:$AJ$601,0),"")="","","; "&INDEX(DESK!$AW$2:$AW$601,IFERROR(MATCH($D$4&"|3",DESK!$AJ$2:$AJ$601,0),""))&" "&INDEX(DESK!$B$2:$B$601,IFERROR(MATCH($D$4&"|3",DESK!$AJ$2:$AJ$601,0),""))&" "&INDEX(DESK!$G$2:$G$601,IFERROR(MATCH($D$4&"|3",DESK!$AJ$2:$AJ$601,0),"")))&IF(INDEX(DESK!$AC$2:$AC$601,IFERROR(MATCH($D$4&"|1",DESK!$AJ$2:$AJ$601,0),""))="YES"," : they said yes? Book it, log BOOKED."," : send the link, log SENT_LINK."))) | J4: =IF(IFERROR(MATCH($D$4&"|1",DESK!$AJ$2:$AJ$601,0),"")="","",HYPERLINK(INDEX(DESK!$AD$2:$AD$601,IFERROR(MATCH($D$4&"|1",DESK!$AJ$2:$AJ$601,0),"")),"Calendar: "&INDEX(DESK!$B$2:$B$601,IFERROR(MATCH($D$4&"|1",DESK!$AJ$2:$AJ$601,0),"")))) | K4: =IF(IFERROR(MATCH($D$4&"|2",DESK!$AJ$2:$AJ$601,0),"")="","",HYPERLINK(INDEX(DESK!$AD$2:$AD$601,IFERROR(MATCH($D$4&"|2",DESK!$AJ$2:$AJ$601,0),"")),"Calendar: "&INDEX(DESK!$B$2:$B$601,IFERROR(MATCH($D$4&"|2",DESK!$AJ$2:$AJ$601,0),"")))) | L4: =IF(IFERROR(MATCH($D$4&"|3",DESK!$AJ$2:$AJ$601,0),"")="","",HYPERLINK(INDEX(DESK!$AD$2:$AD$601,IFERROR(MATCH($D$4&"|3",DESK!$AJ$2:$AJ$601,0),"")),"Calendar: "&INDEX(DESK!$B$2:$B$601,IFERROR(MATCH($D$4&"|3",DESK!$AJ$2:$AJ$601,0),""))))
A6: # | B6: Candidate | C6: Phone | D6: Interviews to book (request ID first) | E6: Hours left | F6: Try | G6: WHAT TO DO | H6: Call | I6: WhatsApp | J6: Calendar 1 | K6: Calendar 2 | L6: Calendar 3 | M6: Message (copy if WhatsApp opens empty) | N6: key | O6: row | P6: msg
A7: 1 | B7: =IF(O7="","",INDEX(DESK!$D$2:$D$601,O7)) | C7: =IF(O7="","",INDEX(DESK!$F$2:$F$601,O7)) | D7: =IF(O7="","",INDEX(DESK!$AW$2:$AW$601,O7)&" "&INDEX(DESK!$B$2:$B$601,O7)&" "&INDEX(DESK!$G$2:$G$601,O7)&IFERROR("; "&INDEX(DESK!$AW$2:$AW$601,MATCH($C7&"|2",DESK!$AJ$2:$AJ$601,0))&" "&INDEX(DESK!$B$2:$B$601,MATCH($C7&"|2",DESK!$AJ$2:$AJ$601,0))&" "&INDEX(DESK!$G$2:$G$601,MATCH($C7&"|2",DESK!$AJ$2:$AJ$601,0)),"")&IFERROR("; "&INDEX(DESK!$AW$2:$AW$601,MATCH($C7&"|3",DESK!$AJ$2:$AJ$601,0))&" "&INDEX(DESK!$B$2:$B$601,MATCH($C7&"|3",DESK!$AJ$2:$AJ$601,0))&" "&INDEX(DESK!$G$2:$G$601,MATCH($C7&"|3",DESK!$AJ$2:$AJ$601,0)),"")) | E7: =IF(O7="","",ROUND(INDEX(DESK!$W$2:$W$601,O7),1)) | F7: =IF(O7="","",INDEX(DESK!$Q$2:$Q$601,O7)+1) | G7: =IF(O7="","",IF((INDEX(DESK!$AU$2:$AU$601,O7)=1),IF((INDEX(DESK!$AC$2:$AC$601,O7)="YES"),"REPLIED YES on WhatsApp. Open Calendar 1, book the first free slot, WhatsApp them the time, log BOOKED.","REPLIED YES on WhatsApp. Send the WhatsApp (it has the booking link), log SENT_LINK."),IF(F7>=SETTINGS!$B$6,"LAST TRY. ","")&IF((INDEX(DESK!$S$2:$S$601,O7)="SENT_LINK"),"Open Calendar 1. Already booked? Log SELF_BOOKED. Not booked? Call, send the WhatsApp, log what happened.",IF((INDEX(DESK!$AC$2:$AC$601,O7)="YES"),"Call. They say yes? Open Calendar 1, book the first time that suits them, log BOOKED. No answer? Send the WhatsApp, log NO_ANSWER.","Call. They say yes? Send the WhatsApp (it has the booking link), log SENT_LINK. No answer? Send the WhatsApp, log NO_ANSWER.")))&IF(INDEX(DESK!$AS$2:$AS$601,O7)="FAILED"," (Our WhatsApp did not deliver: call only.)","")) | H7: =IF(O7="","",HYPERLINK("tel:+91"&C7,"Call "&C7)) | I7: =IF(O7="","",IF(LEN("https://wa.me/91"&C7&"?text="&_xlfn.ENCODEURL(M7))<=255,HYPERLINK("https://wa.me/91"&C7&"?text="&_xlfn.ENCODEURL(M7),"Open WhatsApp"),HYPERLINK("https://wa.me/91"&C7,"Open WhatsApp, paste column M"))) | J7: =IF(O7="","",HYPERLINK(INDEX(DESK!$AD$2:$AD$601,O7),INDEX(DESK!$B$2:$B$601,O7))) | K7: =IF(O7="","",IFERROR(HYPERLINK(INDEX(DESK!$AD$2:$AD$601,MATCH($C7&"|2",DESK!$AJ$2:$AJ$601,0)),INDEX(DESK!$B$2:$B$601,MATCH($C7&"|2",DESK!$AJ$2:$AJ$601,0))),"")) | L7: =IF(O7="","",IFERROR(HYPERLINK(INDEX(DESK!$AD$2:$AD$601,MATCH($C7&"|3",DESK!$AJ$2:$AJ$601,0)),INDEX(DESK!$B$2:$B$601,MATCH($C7&"|3",DESK!$AJ$2:$AJ$601,0))),"")) | M7: =IF(O7="","",SUBSTITUTE(SUBSTITUTE(SUBSTITUTE(SUBSTITUTE(INDEX(LISTS!$B$14:$B$19,MATCH(P7,LISTS!$A$14:$A$19,0))&IF(IF((INDEX(DESK!$AC$2:$AC$601,O7)="YES"),"",INDEX(DESK!$AD$2:$AD$601,O7))="",INDEX(LISTS!$B$14:$B$19,MATCH("YES",LISTS!$A$14:$A$19,0)),INDEX(LISTS!$B$14:$B$19,MATCH("NO",LISTS!$A$14:$A$19,0))),"{NAME}",INDEX(DESK!$AQ$2:$AQ$601,O7)),"{INTERN}",$B$2),"{COMPANY}",INDEX(DESK!$B$2:$B$601,O7)&IF(INDEX(DESK!$AA$2:$AA$601,O7)>1," and "&(INDEX(DESK!$AA$2:$AA$601,O7)-1)&" more","")),"{LINK}",IF((INDEX(DESK!$AC$2:$AC$601,O7)="YES"),"",INDEX(DESK!$AD$2:$AD$601,O7)))) | N7: =$B$2&"|"&A7 -> Ram|1 | O7: =IFERROR(MATCH(N7,DESK!$AI$2:$AI$601,0),"") | P7: =IF(O7="","",IF((INDEX(DESK!$S$2:$S$601,O7)="SENT_LINK"),"CHK",IF(F7=1,"T1",IF(F7>=SETTINGS!$B$6,"T3","T2"))))
A8: 2 | B8: =IF(O8="","",INDEX(DESK!$D$2:$D$601,O8)) | C8: =IF(O8="","",INDEX(DESK!$F$2:$F$601,O8)) | D8: =IF(O8="","",INDEX(DESK!$AW$2:$AW$601,O8)&" "&INDEX(DESK!$B$2:$B$601,O8)&" "&INDEX(DESK!$G$2:$G$601,O8)&IFERROR("; "&INDEX(DESK!$AW$2:$AW$601,MATCH($C8&"|2",DESK!$AJ$2:$AJ$601,0))&" "&INDEX(DESK!$B$2:$B$601,MATCH($C8&"|2",DESK!$AJ$2:$AJ$601,0))&" "&INDEX(DESK!$G$2:$G$601,MATCH($C8&"|2",DESK!$AJ$2:$AJ$601,0)),"")&IFERROR("; "&INDEX(DESK!$AW$2:$AW$601,MATCH($C8&"|3",DESK!$AJ$2:$AJ$601,0))&" "&INDEX(DESK!$B$2:$B$601,MATCH($C8&"|3",DESK!$AJ$2:$AJ$601,0))&" "&INDEX(DESK!$G$2:$G$601,MATCH($C8&"|3",DESK!$AJ$2:$AJ$601,0)),"")) | E8: =IF(O8="","",ROUND(INDEX(DESK!$W$2:$W$601,O8),1)) | F8: =IF(O8="","",INDEX(DESK!$Q$2:$Q$601,O8)+1) | G8: =IF(O8="","",IF((INDEX(DESK!$AU$2:$AU$601,O8)=1),IF((INDEX(DESK!$AC$2:$AC$601,O8)="YES"),"REPLIED YES on WhatsApp. Open Calendar 1, book the first free slot, WhatsApp them the time, log BOOKED.","REPLIED YES on WhatsApp. Send the WhatsApp (it has the booking link), log SENT_LINK."),IF(F8>=SETTINGS!$B$6,"LAST TRY. ","")&IF((INDEX(DESK!$S$2:$S$601,O8)="SENT_LINK"),"Open Calendar 1. Already booked? Log SELF_BOOKED. Not booked? Call, send the WhatsApp, log what happened.",IF((INDEX(DESK!$AC$2:$AC$601,O8)="YES"),"Call. They say yes? Open Calendar 1, book the first time that suits them, log BOOKED. No answer? Send the WhatsApp, log NO_ANSWER.","Call. They say yes? Send the WhatsApp (it has the booking link), log SENT_LINK. No answer? Send the WhatsApp, log NO_ANSWER.")))&IF(INDEX(DESK!$AS$2:$AS$601,O8)="FAILED"," (Our WhatsApp did not deliver: call only.)","")) | H8: =IF(O8="","",HYPERLINK("tel:+91"&C8,"Call "&C8)) | I8: =IF(O8="","",IF(LEN("https://wa.me/91"&C8&"?text="&_xlfn.ENCODEURL(M8))<=255,HYPERLINK("https://wa.me/91"&C8&"?text="&_xlfn.ENCODEURL(M8),"Open WhatsApp"),HYPERLINK("https://wa.me/91"&C8,"Open WhatsApp, paste column M"))) | J8: =IF(O8="","",HYPERLINK(INDEX(DESK!$AD$2:$AD$601,O8),INDEX(DESK!$B$2:$B$601,O8))) | K8: =IF(O8="","",IFERROR(HYPERLINK(INDEX(DESK!$AD$2:$AD$601,MATCH($C8&"|2",DESK!$AJ$2:$AJ$601,0)),INDEX(DESK!$B$2:$B$601,MATCH($C8&"|2",DESK!$AJ$2:$AJ$601,0))),"")) | L8: =IF(O8="","",IFERROR(HYPERLINK(INDEX(DESK!$AD$2:$AD$601,MATCH($C8&"|3",DESK!$AJ$2:$AJ$601,0)),INDEX(DESK!$B$2:$B$601,MATCH($C8&"|3",DESK!$AJ$2:$AJ$601,0))),"")) | M8: =IF(O8="","",SUBSTITUTE(SUBSTITUTE(SUBSTITUTE(SUBSTITUTE(INDEX(LISTS!$B$14:$B$19,MATCH(P8,LISTS!$A$14:$A$19,0))&IF(IF((INDEX(DESK!$AC$2:$AC$601,O8)="YES"),"",INDEX(DESK!$AD$2:$AD$601,O8))="",INDEX(LISTS!$B$14:$B$19,MATCH("YES",LISTS!$A$14:$A$19,0)),INDEX(LISTS!$B$14:$B$19,MATCH("NO",LISTS!$A$14:$A$19,0))),"{NAME}",INDEX(DESK!$AQ$2:$AQ$601,O8)),"{INTERN}",$B$2),"{COMPANY}",INDEX(DESK!$B$2:$B$601,O8)&IF(INDEX(DESK!$AA$2:$AA$601,O8)>1," and "&(INDEX(DESK!$AA$2:$AA$601,O8)-1)&" more","")),"{LINK}",IF((INDEX(DESK!$AC$2:$AC$601,O8)="YES"),"",INDEX(DESK!$AD$2:$AD$601,O8)))) | N8: =$B$2&"|"&A8 -> Ram|2 | O8: =IFERROR(MATCH(N8,DESK!$AI$2:$AI$601,0),"") | P8: =IF(O8="","",IF((INDEX(DESK!$S$2:$S$601,O8)="SENT_LINK"),"CHK",IF(F8=1,"T1",IF(F8>=SETTINGS!$B$6,"T3","T2"))))
A9: 3 | B9: =IF(O9="","",INDEX(DESK!$D$2:$D$601,O9)) | C9: =IF(O9="","",INDEX(DESK!$F$2:$F$601,O9)) | D9: =IF(O9="","",INDEX(DESK!$AW$2:$AW$601,O9)&" "&INDEX(DESK!$B$2:$B$601,O9)&" "&INDEX(DESK!$G$2:$G$601,O9)&IFERROR("; "&INDEX(DESK!$AW$2:$AW$601,MATCH($C9&"|2",DESK!$AJ$2:$AJ$601,0))&" "&INDEX(DESK!$B$2:$B$601,MATCH($C9&"|2",DESK!$AJ$2:$AJ$601,0))&" "&INDEX(DESK!$G$2:$G$601,MATCH($C9&"|2",DESK!$AJ$2:$AJ$601,0)),"")&IFERROR("; "&INDEX(DESK!$AW$2:$AW$601,MATCH($C9&"|3",DESK!$AJ$2:$AJ$601,0))&" "&INDEX(DESK!$B$2:$B$601,MATCH($C9&"|3",DESK!$AJ$2:$AJ$601,0))&" "&INDEX(DESK!$G$2:$G$601,MATCH($C9&"|3",DESK!$AJ$2:$AJ$601,0)),"")) | E9: =IF(O9="","",ROUND(INDEX(DESK!$W$2:$W$601,O9),1)) | F9: =IF(O9="","",INDEX(DESK!$Q$2:$Q$601,O9)+1) | G9: =IF(O9="","",IF((INDEX(DESK!$AU$2:$AU$601,O9)=1),IF((INDEX(DESK!$AC$2:$AC$601,O9)="YES"),"REPLIED YES on WhatsApp. Open Calendar 1, book the first free slot, WhatsApp them the time, log BOOKED.","REPLIED YES on WhatsApp. Send the WhatsApp (it has the booking link), log SENT_LINK."),IF(F9>=SETTINGS!$B$6,"LAST TRY. ","")&IF((INDEX(DESK!$S$2:$S$601,O9)="SENT_LINK"),"Open Calendar 1. Already booked? Log SELF_BOOKED. Not booked? Call, send the WhatsApp, log what happened.",IF((INDEX(DESK!$AC$2:$AC$601,O9)="YES"),"Call. They say yes? Open Calendar 1, book the first time that suits them, log BOOKED. No answer? Send the WhatsApp, log NO_ANSWER.","Call. They say yes? Send the WhatsApp (it has the booking link), log SENT_LINK. No answer? Send the WhatsApp, log NO_ANSWER.")))&IF(INDEX(DESK!$AS$2:$AS$601,O9)="FAILED"," (Our WhatsApp did not deliver: call only.)","")) | H9: =IF(O9="","",HYPERLINK("tel:+91"&C9,"Call "&C9)) | I9: =IF(O9="","",IF(LEN("https://wa.me/91"&C9&"?text="&_xlfn.ENCODEURL(M9))<=255,HYPERLINK("https://wa.me/91"&C9&"?text="&_xlfn.ENCODEURL(M9),"Open WhatsApp"),HYPERLINK("https://wa.me/91"&C9,"Open WhatsApp, paste column M"))) | J9: =IF(O9="","",HYPERLINK(INDEX(DESK!$AD$2:$AD$601,O9),INDEX(DESK!$B$2:$B$601,O9))) | K9: =IF(O9="","",IFERROR(HYPERLINK(INDEX(DESK!$AD$2:$AD$601,MATCH($C9&"|2",DESK!$AJ$2:$AJ$601,0)),INDEX(DESK!$B$2:$B$601,MATCH($C9&"|2",DESK!$AJ$2:$AJ$601,0))),"")) | L9: =IF(O9="","",IFERROR(HYPERLINK(INDEX(DESK!$AD$2:$AD$601,MATCH($C9&"|3",DESK!$AJ$2:$AJ$601,0)),INDEX(DESK!$B$2:$B$601,MATCH($C9&"|3",DESK!$AJ$2:$AJ$601,0))),"")) | M9: =IF(O9="","",SUBSTITUTE(SUBSTITUTE(SUBSTITUTE(SUBSTITUTE(INDEX(LISTS!$B$14:$B$19,MATCH(P9,LISTS!$A$14:$A$19,0))&IF(IF((INDEX(DESK!$AC$2:$AC$601,O9)="YES"),"",INDEX(DESK!$AD$2:$AD$601,O9))="",INDEX(LISTS!$B$14:$B$19,MATCH("YES",LISTS!$A$14:$A$19,0)),INDEX(LISTS!$B$14:$B$19,MATCH("NO",LISTS!$A$14:$A$19,0))),"{NAME}",INDEX(DESK!$AQ$2:$AQ$601,O9)),"{INTERN}",$B$2),"{COMPANY}",INDEX(DESK!$B$2:$B$601,O9)&IF(INDEX(DESK!$AA$2:$AA$601,O9)>1," and "&(INDEX(DESK!$AA$2:$AA$601,O9)-1)&" more","")),"{LINK}",IF((INDEX(DESK!$AC$2:$AC$601,O9)="YES"),"",INDEX(DESK!$AD$2:$AD$601,O9)))) | N9: =$B$2&"|"&A9 -> Ram|3 | O9: =IFERROR(MATCH(N9,DESK!$AI$2:$AI$601,0),"") | P9: =IF(O9="","",IF((INDEX(DESK!$S$2:$S$601,O9)="SENT_LINK"),"CHK",IF(F9=1,"T1",IF(F9>=SETTINGS!$B$6,"T3","T2"))))
A10: 4 | B10: =IF(O10="","",INDEX(DESK!$D$2:$D$601,O10)) | C10: =IF(O10="","",INDEX(DESK!$F$2:$F$601,O10)) | D10: =IF(O10="","",INDEX(DESK!$AW$2:$AW$601,O10)&" "&INDEX(DESK!$B$2:$B$601,O10)&" "&INDEX(DESK!$G$2:$G$601,O10)&IFERROR("; "&INDEX(DESK!$AW$2:$AW$601,MATCH($C10&"|2",DESK!$AJ$2:$AJ$601,0))&" "&INDEX(DESK!$B$2:$B$601,MATCH($C10&"|2",DESK!$AJ$2:$AJ$601,0))&" "&INDEX(DESK!$G$2:$G$601,MATCH($C10&"|2",DESK!$AJ$2:$AJ$601,0)),"")&IFERROR("; "&INDEX(DESK!$AW$2:$AW$601,MATCH($C10&"|3",DESK!$AJ$2:$AJ$601,0))&" "&INDEX(DESK!$B$2:$B$601,MATCH($C10&"|3",DESK!$AJ$2:$AJ$601,0))&" "&INDEX(DESK!$G$2:$G$601,MATCH($C10&"|3",DESK!$AJ$2:$AJ$601,0)),"")) | E10: =IF(O10="","",ROUND(INDEX(DESK!$W$2:$W$601,O10),1)) | F10: =IF(O10="","",INDEX(DESK!$Q$2:$Q$601,O10)+1) | G10: =IF(O10="","",IF((INDEX(DESK!$AU$2:$AU$601,O10)=1),IF((INDEX(DESK!$AC$2:$AC$601,O10)="YES"),"REPLIED YES on WhatsApp. Open Calendar 1, book the first free slot, WhatsApp them the time, log BOOKED.","REPLIED YES on WhatsApp. Send the WhatsApp (it has the booking link), log SENT_LINK."),IF(F10>=SETTINGS!$B$6,"LAST TRY. ","")&IF((INDEX(DESK!$S$2:$S$601,O10)="SENT_LINK"),"Open Calendar 1. Already booked? Log SELF_BOOKED. Not booked? Call, send the WhatsApp, log what happened.",IF((INDEX(DESK!$AC$2:$AC$601,O10)="YES"),"Call. They say yes? Open Calendar 1, book the first time that suits them, log BOOKED. No answer? Send the WhatsApp, log NO_ANSWER.","Call. They say yes? Send the WhatsApp (it has the booking link), log SENT_LINK. No answer? Send the WhatsApp, log NO_ANSWER.")))&IF(INDEX(DESK!$AS$2:$AS$601,O10)="FAILED"," (Our WhatsApp did not deliver: call only.)","")) | H10: =IF(O10="","",HYPERLINK("tel:+91"&C10,"Call "&C10)) | I10: =IF(O10="","",IF(LEN("https://wa.me/91"&C10&"?text="&_xlfn.ENCODEURL(M10))<=255,HYPERLINK("https://wa.me/91"&C10&"?text="&_xlfn.ENCODEURL(M10),"Open WhatsApp"),HYPERLINK("https://wa.me/91"&C10,"Open WhatsApp, paste column M"))) | J10: =IF(O10="","",HYPERLINK(INDEX(DESK!$AD$2:$AD$601,O10),INDEX(DESK!$B$2:$B$601,O10))) | K10: =IF(O10="","",IFERROR(HYPERLINK(INDEX(DESK!$AD$2:$AD$601,MATCH($C10&"|2",DESK!$AJ$2:$AJ$601,0)),INDEX(DESK!$B$2:$B$601,MATCH($C10&"|2",DESK!$AJ$2:$AJ$601,0))),"")) | L10: =IF(O10="","",IFERROR(HYPERLINK(INDEX(DESK!$AD$2:$AD$601,MATCH($C10&"|3",DESK!$AJ$2:$AJ$601,0)),INDEX(DESK!$B$2:$B$601,MATCH($C10&"|3",DESK!$AJ$2:$AJ$601,0))),"")) | M10: =IF(O10="","",SUBSTITUTE(SUBSTITUTE(SUBSTITUTE(SUBSTITUTE(INDEX(LISTS!$B$14:$B$19,MATCH(P10,LISTS!$A$14:$A$19,0))&IF(IF((INDEX(DESK!$AC$2:$AC$601,O10)="YES"),"",INDEX(DESK!$AD$2:$AD$601,O10))="",INDEX(LISTS!$B$14:$B$19,MATCH("YES",LISTS!$A$14:$A$19,0)),INDEX(LISTS!$B$14:$B$19,MATCH("NO",LISTS!$A$14:$A$19,0))),"{NAME}",INDEX(DESK!$AQ$2:$AQ$601,O10)),"{INTERN}",$B$2),"{COMPANY}",INDEX(DESK!$B$2:$B$601,O10)&IF(INDEX(DESK!$AA$2:$AA$601,O10)>1," and "&(INDEX(DESK!$AA$2:$AA$601,O10)-1)&" more","")),"{LINK}",IF((INDEX(DESK!$AC$2:$AC$601,O10)="YES"),"",INDEX(DESK!$AD$2:$AD$601,O10)))) | N10: =$B$2&"|"&A10 -> Ram|4 | O10: =IFERROR(MATCH(N10,DESK!$AI$2:$AI$601,0),"") | P10: =IF(O10="","",IF((INDEX(DESK!$S$2:$S$601,O10)="SENT_LINK"),"CHK",IF(F10=1,"T1",IF(F10>=SETTINGS!$B$6,"T3","T2"))))
A11: 5 | B11: =IF(O11="","",INDEX(DESK!$D$2:$D$601,O11)) | C11: =IF(O11="","",INDEX(DESK!$F$2:$F$601,O11)) | D11: =IF(O11="","",INDEX(DESK!$AW$2:$AW$601,O11)&" "&INDEX(DESK!$B$2:$B$601,O11)&" "&INDEX(DESK!$G$2:$G$601,O11)&IFERROR("; "&INDEX(DESK!$AW$2:$AW$601,MATCH($C11&"|2",DESK!$AJ$2:$AJ$601,0))&" "&INDEX(DESK!$B$2:$B$601,MATCH($C11&"|2",DESK!$AJ$2:$AJ$601,0))&" "&INDEX(DESK!$G$2:$G$601,MATCH($C11&"|2",DESK!$AJ$2:$AJ$601,0)),"")&IFERROR("; "&INDEX(DESK!$AW$2:$AW$601,MATCH($C11&"|3",DESK!$AJ$2:$AJ$601,0))&" "&INDEX(DESK!$B$2:$B$601,MATCH($C11&"|3",DESK!$AJ$2:$AJ$601,0))&" "&INDEX(DESK!$G$2:$G$601,MATCH($C11&"|3",DESK!$AJ$2:$AJ$601,0)),"")) | E11: =IF(O11="","",ROUND(INDEX(DESK!$W$2:$W$601,O11),1)) | F11: =IF(O11="","",INDEX(DESK!$Q$2:$Q$601,O11)+1) | G11: =IF(O11="","",IF((INDEX(DESK!$AU$2:$AU$601,O11)=1),IF((INDEX(DESK!$AC$2:$AC$601,O11)="YES"),"REPLIED YES on WhatsApp. Open Calendar 1, book the first free slot, WhatsApp them the time, log BOOKED.","REPLIED YES on WhatsApp. Send the WhatsApp (it has the booking link), log SENT_LINK."),IF(F11>=SETTINGS!$B$6,"LAST TRY. ","")&IF((INDEX(DESK!$S$2:$S$601,O11)="SENT_LINK"),"Open Calendar 1. Already booked? Log SELF_BOOKED. Not booked? Call, send the WhatsApp, log what happened.",IF((INDEX(DESK!$AC$2:$AC$601,O11)="YES"),"Call. They say yes? Open Calendar 1, book the first time that suits them, log BOOKED. No answer? Send the WhatsApp, log NO_ANSWER.","Call. They say yes? Send the WhatsApp (it has the booking link), log SENT_LINK. No answer? Send the WhatsApp, log NO_ANSWER.")))&IF(INDEX(DESK!$AS$2:$AS$601,O11)="FAILED"," (Our WhatsApp did not deliver: call only.)","")) | H11: =IF(O11="","",HYPERLINK("tel:+91"&C11,"Call "&C11)) | I11: =IF(O11="","",IF(LEN("https://wa.me/91"&C11&"?text="&_xlfn.ENCODEURL(M11))<=255,HYPERLINK("https://wa.me/91"&C11&"?text="&_xlfn.ENCODEURL(M11),"Open WhatsApp"),HYPERLINK("https://wa.me/91"&C11,"Open WhatsApp, paste column M"))) | J11: =IF(O11="","",HYPERLINK(INDEX(DESK!$AD$2:$AD$601,O11),INDEX(DESK!$B$2:$B$601,O11))) | K11: =IF(O11="","",IFERROR(HYPERLINK(INDEX(DESK!$AD$2:$AD$601,MATCH($C11&"|2",DESK!$AJ$2:$AJ$601,0)),INDEX(DESK!$B$2:$B$601,MATCH($C11&"|2",DESK!$AJ$2:$AJ$601,0))),"")) | L11: =IF(O11="","",IFERROR(HYPERLINK(INDEX(DESK!$AD$2:$AD$601,MATCH($C11&"|3",DESK!$AJ$2:$AJ$601,0)),INDEX(DESK!$B$2:$B$601,MATCH($C11&"|3",DESK!$AJ$2:$AJ$601,0))),"")) | M11: =IF(O11="","",SUBSTITUTE(SUBSTITUTE(SUBSTITUTE(SUBSTITUTE(INDEX(LISTS!$B$14:$B$19,MATCH(P11,LISTS!$A$14:$A$19,0))&IF(IF((INDEX(DESK!$AC$2:$AC$601,O11)="YES"),"",INDEX(DESK!$AD$2:$AD$601,O11))="",INDEX(LISTS!$B$14:$B$19,MATCH("YES",LISTS!$A$14:$A$19,0)),INDEX(LISTS!$B$14:$B$19,MATCH("NO",LISTS!$A$14:$A$19,0))),"{NAME}",INDEX(DESK!$AQ$2:$AQ$601,O11)),"{INTERN}",$B$2),"{COMPANY}",INDEX(DESK!$B$2:$B$601,O11)&IF(INDEX(DESK!$AA$2:$AA$601,O11)>1," and "&(INDEX(DESK!$AA$2:$AA$601,O11)-1)&" more","")),"{LINK}",IF((INDEX(DESK!$AC$2:$AC$601,O11)="YES"),"",INDEX(DESK!$AD$2:$AD$601,O11)))) | N11: =$B$2&"|"&A11 -> Ram|5 | O11: =IFERROR(MATCH(N11,DESK!$AI$2:$AI$601,0),"") | P11: =IF(O11="","",IF((INDEX(DESK!$S$2:$S$601,O11)="SENT_LINK"),"CHK",IF(F11=1,"T1",IF(F11>=SETTINGS!$B$6,"T3","T2"))))
A12: 6 | B12: =IF(O12="","",INDEX(DESK!$D$2:$D$601,O12)) | C12: =IF(O12="","",INDEX(DESK!$F$2:$F$601,O12)) | D12: =IF(O12="","",INDEX(DESK!$AW$2:$AW$601,O12)&" "&INDEX(DESK!$B$2:$B$601,O12)&" "&INDEX(DESK!$G$2:$G$601,O12)&IFERROR("; "&INDEX(DESK!$AW$2:$AW$601,MATCH($C12&"|2",DESK!$AJ$2:$AJ$601,0))&" "&INDEX(DESK!$B$2:$B$601,MATCH($C12&"|2",DESK!$AJ$2:$AJ$601,0))&" "&INDEX(DESK!$G$2:$G$601,MATCH($C12&"|2",DESK!$AJ$2:$AJ$601,0)),"")&IFERROR("; "&INDEX(DESK!$AW$2:$AW$601,MATCH($C12&"|3",DESK!$AJ$2:$AJ$601,0))&" "&INDEX(DESK!$B$2:$B$601,MATCH($C12&"|3",DESK!$AJ$2:$AJ$601,0))&" "&INDEX(DESK!$G$2:$G$601,MATCH($C12&"|3",DESK!$AJ$2:$AJ$601,0)),"")) | E12: =IF(O12="","",ROUND(INDEX(DESK!$W$2:$W$601,O12),1)) | F12: =IF(O12="","",INDEX(DESK!$Q$2:$Q$601,O12)+1) | G12: =IF(O12="","",IF((INDEX(DESK!$AU$2:$AU$601,O12)=1),IF((INDEX(DESK!$AC$2:$AC$601,O12)="YES"),"REPLIED YES on WhatsApp. Open Calendar 1, book the first free slot, WhatsApp them the time, log BOOKED.","REPLIED YES on WhatsApp. Send the WhatsApp (it has the booking link), log SENT_LINK."),IF(F12>=SETTINGS!$B$6,"LAST TRY. ","")&IF((INDEX(DESK!$S$2:$S$601,O12)="SENT_LINK"),"Open Calendar 1. Already booked? Log SELF_BOOKED. Not booked? Call, send the WhatsApp, log what happened.",IF((INDEX(DESK!$AC$2:$AC$601,O12)="YES"),"Call. They say yes? Open Calendar 1, book the first time that suits them, log BOOKED. No answer? Send the WhatsApp, log NO_ANSWER.","Call. They say yes? Send the WhatsApp (it has the booking link), log SENT_LINK. No answer? Send the WhatsApp, log NO_ANSWER.")))&IF(INDEX(DESK!$AS$2:$AS$601,O12)="FAILED"," (Our WhatsApp did not deliver: call only.)","")) | H12: =IF(O12="","",HYPERLINK("tel:+91"&C12,"Call "&C12)) | I12: =IF(O12="","",IF(LEN("https://wa.me/91"&C12&"?text="&_xlfn.ENCODEURL(M12))<=255,HYPERLINK("https://wa.me/91"&C12&"?text="&_xlfn.ENCODEURL(M12),"Open WhatsApp"),HYPERLINK("https://wa.me/91"&C12,"Open WhatsApp, paste column M"))) | J12: =IF(O12="","",HYPERLINK(INDEX(DESK!$AD$2:$AD$601,O12),INDEX(DESK!$B$2:$B$601,O12))) | K12: =IF(O12="","",IFERROR(HYPERLINK(INDEX(DESK!$AD$2:$AD$601,MATCH($C12&"|2",DESK!$AJ$2:$AJ$601,0)),INDEX(DESK!$B$2:$B$601,MATCH($C12&"|2",DESK!$AJ$2:$AJ$601,0))),"")) | L12: =IF(O12="","",IFERROR(HYPERLINK(INDEX(DESK!$AD$2:$AD$601,MATCH($C12&"|3",DESK!$AJ$2:$AJ$601,0)),INDEX(DESK!$B$2:$B$601,MATCH($C12&"|3",DESK!$AJ$2:$AJ$601,0))),"")) | M12: =IF(O12="","",SUBSTITUTE(SUBSTITUTE(SUBSTITUTE(SUBSTITUTE(INDEX(LISTS!$B$14:$B$19,MATCH(P12,LISTS!$A$14:$A$19,0))&IF(IF((INDEX(DESK!$AC$2:$AC$601,O12)="YES"),"",INDEX(DESK!$AD$2:$AD$601,O12))="",INDEX(LISTS!$B$14:$B$19,MATCH("YES",LISTS!$A$14:$A$19,0)),INDEX(LISTS!$B$14:$B$19,MATCH("NO",LISTS!$A$14:$A$19,0))),"{NAME}",INDEX(DESK!$AQ$2:$AQ$601,O12)),"{INTERN}",$B$2),"{COMPANY}",INDEX(DESK!$B$2:$B$601,O12)&IF(INDEX(DESK!$AA$2:$AA$601,O12)>1," and "&(INDEX(DESK!$AA$2:$AA$601,O12)-1)&" more","")),"{LINK}",IF((INDEX(DESK!$AC$2:$AC$601,O12)="YES"),"",INDEX(DESK!$AD$2:$AD$601,O12)))) | N12: =$B$2&"|"&A12 -> Ram|6 | O12: =IFERROR(MATCH(N12,DESK!$AI$2:$AI$601,0),"") | P12: =IF(O12="","",IF((INDEX(DESK!$S$2:$S$601,O12)="SENT_LINK"),"CHK",IF(F12=1,"T1",IF(F12>=SETTINGS!$B$6,"T3","T2"))))
A13: 7 | B13: =IF(O13="","",INDEX(DESK!$D$2:$D$601,O13)) | C13: =IF(O13="","",INDEX(DESK!$F$2:$F$601,O13)) | D13: =IF(O13="","",INDEX(DESK!$AW$2:$AW$601,O13)&" "&INDEX(DESK!$B$2:$B$601,O13)&" "&INDEX(DESK!$G$2:$G$601,O13)&IFERROR("; "&INDEX(DESK!$AW$2:$AW$601,MATCH($C13&"|2",DESK!$AJ$2:$AJ$601,0))&" "&INDEX(DESK!$B$2:$B$601,MATCH($C13&"|2",DESK!$AJ$2:$AJ$601,0))&" "&INDEX(DESK!$G$2:$G$601,MATCH($C13&"|2",DESK!$AJ$2:$AJ$601,0)),"")&IFERROR("; "&INDEX(DESK!$AW$2:$AW$601,MATCH($C13&"|3",DESK!$AJ$2:$AJ$601,0))&" "&INDEX(DESK!$B$2:$B$601,MATCH($C13&"|3",DESK!$AJ$2:$AJ$601,0))&" "&INDEX(DESK!$G$2:$G$601,MATCH($C13&"|3",DESK!$AJ$2:$AJ$601,0)),"")) | E13: =IF(O13="","",ROUND(INDEX(DESK!$W$2:$W$601,O13),1)) | F13: =IF(O13="","",INDEX(DESK!$Q$2:$Q$601,O13)+1) | G13: =IF(O13="","",IF((INDEX(DESK!$AU$2:$AU$601,O13)=1),IF((INDEX(DESK!$AC$2:$AC$601,O13)="YES"),"REPLIED YES on WhatsApp. Open Calendar 1, book the first free slot, WhatsApp them the time, log BOOKED.","REPLIED YES on WhatsApp. Send the WhatsApp (it has the booking link), log SENT_LINK."),IF(F13>=SETTINGS!$B$6,"LAST TRY. ","")&IF((INDEX(DESK!$S$2:$S$601,O13)="SENT_LINK"),"Open Calendar 1. Already booked? Log SELF_BOOKED. Not booked? Call, send the WhatsApp, log what happened.",IF((INDEX(DESK!$AC$2:$AC$601,O13)="YES"),"Call. They say yes? Open Calendar 1, book the first time that suits them, log BOOKED. No answer? Send the WhatsApp, log NO_ANSWER.","Call. They say yes? Send the WhatsApp (it has the booking link), log SENT_LINK. No answer? Send the WhatsApp, log NO_ANSWER.")))&IF(INDEX(DESK!$AS$2:$AS$601,O13)="FAILED"," (Our WhatsApp did not deliver: call only.)","")) | H13: =IF(O13="","",HYPERLINK("tel:+91"&C13,"Call "&C13)) | I13: =IF(O13="","",IF(LEN("https://wa.me/91"&C13&"?text="&_xlfn.ENCODEURL(M13))<=255,HYPERLINK("https://wa.me/91"&C13&"?text="&_xlfn.ENCODEURL(M13),"Open WhatsApp"),HYPERLINK("https://wa.me/91"&C13,"Open WhatsApp, paste column M"))) | J13: =IF(O13="","",HYPERLINK(INDEX(DESK!$AD$2:$AD$601,O13),INDEX(DESK!$B$2:$B$601,O13))) | K13: =IF(O13="","",IFERROR(HYPERLINK(INDEX(DESK!$AD$2:$AD$601,MATCH($C13&"|2",DESK!$AJ$2:$AJ$601,0)),INDEX(DESK!$B$2:$B$601,MATCH($C13&"|2",DESK!$AJ$2:$AJ$601,0))),"")) | L13: =IF(O13="","",IFERROR(HYPERLINK(INDEX(DESK!$AD$2:$AD$601,MATCH($C13&"|3",DESK!$AJ$2:$AJ$601,0)),INDEX(DESK!$B$2:$B$601,MATCH($C13&"|3",DESK!$AJ$2:$AJ$601,0))),"")) | M13: =IF(O13="","",SUBSTITUTE(SUBSTITUTE(SUBSTITUTE(SUBSTITUTE(INDEX(LISTS!$B$14:$B$19,MATCH(P13,LISTS!$A$14:$A$19,0))&IF(IF((INDEX(DESK!$AC$2:$AC$601,O13)="YES"),"",INDEX(DESK!$AD$2:$AD$601,O13))="",INDEX(LISTS!$B$14:$B$19,MATCH("YES",LISTS!$A$14:$A$19,0)),INDEX(LISTS!$B$14:$B$19,MATCH("NO",LISTS!$A$14:$A$19,0))),"{NAME}",INDEX(DESK!$AQ$2:$AQ$601,O13)),"{INTERN}",$B$2),"{COMPANY}",INDEX(DESK!$B$2:$B$601,O13)&IF(INDEX(DESK!$AA$2:$AA$601,O13)>1," and "&(INDEX(DESK!$AA$2:$AA$601,O13)-1)&" more","")),"{LINK}",IF((INDEX(DESK!$AC$2:$AC$601,O13)="YES"),"",INDEX(DESK!$AD$2:$AD$601,O13)))) | N13: =$B$2&"|"&A13 -> Ram|7 | O13: =IFERROR(MATCH(N13,DESK!$AI$2:$AI$601,0),"") | P13: =IF(O13="","",IF((INDEX(DESK!$S$2:$S$601,O13)="SENT_LINK"),"CHK",IF(F13=1,"T1",IF(F13>=SETTINGS!$B$6,"T3","T2"))))
A14: 8 | B14: =IF(O14="","",INDEX(DESK!$D$2:$D$601,O14)) | C14: =IF(O14="","",INDEX(DESK!$F$2:$F$601,O14)) | D14: =IF(O14="","",INDEX(DESK!$AW$2:$AW$601,O14)&" "&INDEX(DESK!$B$2:$B$601,O14)&" "&INDEX(DESK!$G$2:$G$601,O14)&IFERROR("; "&INDEX(DESK!$AW$2:$AW$601,MATCH($C14&"|2",DESK!$AJ$2:$AJ$601,0))&" "&INDEX(DESK!$B$2:$B$601,MATCH($C14&"|2",DESK!$AJ$2:$AJ$601,0))&" "&INDEX(DESK!$G$2:$G$601,MATCH($C14&"|2",DESK!$AJ$2:$AJ$601,0)),"")&IFERROR("; "&INDEX(DESK!$AW$2:$AW$601,MATCH($C14&"|3",DESK!$AJ$2:$AJ$601,0))&" "&INDEX(DESK!$B$2:$B$601,MATCH($C14&"|3",DESK!$AJ$2:$AJ$601,0))&" "&INDEX(DESK!$G$2:$G$601,MATCH($C14&"|3",DESK!$AJ$2:$AJ$601,0)),"")) | E14: =IF(O14="","",ROUND(INDEX(DESK!$W$2:$W$601,O14),1)) | F14: =IF(O14="","",INDEX(DESK!$Q$2:$Q$601,O14)+1) | G14: =IF(O14="","",IF((INDEX(DESK!$AU$2:$AU$601,O14)=1),IF((INDEX(DESK!$AC$2:$AC$601,O14)="YES"),"REPLIED YES on WhatsApp. Open Calendar 1, book the first free slot, WhatsApp them the time, log BOOKED.","REPLIED YES on WhatsApp. Send the WhatsApp (it has the booking link), log SENT_LINK."),IF(F14>=SETTINGS!$B$6,"LAST TRY. ","")&IF((INDEX(DESK!$S$2:$S$601,O14)="SENT_LINK"),"Open Calendar 1. Already booked? Log SELF_BOOKED. Not booked? Call, send the WhatsApp, log what happened.",IF((INDEX(DESK!$AC$2:$AC$601,O14)="YES"),"Call. They say yes? Open Calendar 1, book the first time that suits them, log BOOKED. No answer? Send the WhatsApp, log NO_ANSWER.","Call. They say yes? Send the WhatsApp (it has the booking link), log SENT_LINK. No answer? Send the WhatsApp, log NO_ANSWER.")))&IF(INDEX(DESK!$AS$2:$AS$601,O14)="FAILED"," (Our WhatsApp did not deliver: call only.)","")) | H14: =IF(O14="","",HYPERLINK("tel:+91"&C14,"Call "&C14)) | I14: =IF(O14="","",IF(LEN("https://wa.me/91"&C14&"?text="&_xlfn.ENCODEURL(M14))<=255,HYPERLINK("https://wa.me/91"&C14&"?text="&_xlfn.ENCODEURL(M14),"Open WhatsApp"),HYPERLINK("https://wa.me/91"&C14,"Open WhatsApp, paste column M"))) | J14: =IF(O14="","",HYPERLINK(INDEX(DESK!$AD$2:$AD$601,O14),INDEX(DESK!$B$2:$B$601,O14))) | K14: =IF(O14="","",IFERROR(HYPERLINK(INDEX(DESK!$AD$2:$AD$601,MATCH($C14&"|2",DESK!$AJ$2:$AJ$601,0)),INDEX(DESK!$B$2:$B$601,MATCH($C14&"|2",DESK!$AJ$2:$AJ$601,0))),"")) | L14: =IF(O14="","",IFERROR(HYPERLINK(INDEX(DESK!$AD$2:$AD$601,MATCH($C14&"|3",DESK!$AJ$2:$AJ$601,0)),INDEX(DESK!$B$2:$B$601,MATCH($C14&"|3",DESK!$AJ$2:$AJ$601,0))),"")) | M14: =IF(O14="","",SUBSTITUTE(SUBSTITUTE(SUBSTITUTE(SUBSTITUTE(INDEX(LISTS!$B$14:$B$19,MATCH(P14,LISTS!$A$14:$A$19,0))&IF(IF((INDEX(DESK!$AC$2:$AC$601,O14)="YES"),"",INDEX(DESK!$AD$2:$AD$601,O14))="",INDEX(LISTS!$B$14:$B$19,MATCH("YES",LISTS!$A$14:$A$19,0)),INDEX(LISTS!$B$14:$B$19,MATCH("NO",LISTS!$A$14:$A$19,0))),"{NAME}",INDEX(DESK!$AQ$2:$AQ$601,O14)),"{INTERN}",$B$2),"{COMPANY}",INDEX(DESK!$B$2:$B$601,O14)&IF(INDEX(DESK!$AA$2:$AA$601,O14)>1," and "&(INDEX(DESK!$AA$2:$AA$601,O14)-1)&" more","")),"{LINK}",IF((INDEX(DESK!$AC$2:$AC$601,O14)="YES"),"",INDEX(DESK!$AD$2:$AD$601,O14)))) | N14: =$B$2&"|"&A14 -> Ram|8 | O14: =IFERROR(MATCH(N14,DESK!$AI$2:$AI$601,0),"") | P14: =IF(O14="","",IF((INDEX(DESK!$S$2:$S$601,O14)="SENT_LINK"),"CHK",IF(F14=1,"T1",IF(F14>=SETTINGS!$B$6,"T3","T2"))))
A15: 9 | B15: =IF(O15="","",INDEX(DESK!$D$2:$D$601,O15)) | C15: =IF(O15="","",INDEX(DESK!$F$2:$F$601,O15)) | D15: =IF(O15="","",INDEX(DESK!$AW$2:$AW$601,O15)&" "&INDEX(DESK!$B$2:$B$601,O15)&" "&INDEX(DESK!$G$2:$G$601,O15)&IFERROR("; "&INDEX(DESK!$AW$2:$AW$601,MATCH($C15&"|2",DESK!$AJ$2:$AJ$601,0))&" "&INDEX(DESK!$B$2:$B$601,MATCH($C15&"|2",DESK!$AJ$2:$AJ$601,0))&" "&INDEX(DESK!$G$2:$G$601,MATCH($C15&"|2",DESK!$AJ$2:$AJ$601,0)),"")&IFERROR("; "&INDEX(DESK!$AW$2:$AW$601,MATCH($C15&"|3",DESK!$AJ$2:$AJ$601,0))&" "&INDEX(DESK!$B$2:$B$601,MATCH($C15&"|3",DESK!$AJ$2:$AJ$601,0))&" "&INDEX(DESK!$G$2:$G$601,MATCH($C15&"|3",DESK!$AJ$2:$AJ$601,0)),"")) | E15: =IF(O15="","",ROUND(INDEX(DESK!$W$2:$W$601,O15),1)) | F15: =IF(O15="","",INDEX(DESK!$Q$2:$Q$601,O15)+1) | G15: =IF(O15="","",IF((INDEX(DESK!$AU$2:$AU$601,O15)=1),IF((INDEX(DESK!$AC$2:$AC$601,O15)="YES"),"REPLIED YES on WhatsApp. Open Calendar 1, book the first free slot, WhatsApp them the time, log BOOKED.","REPLIED YES on WhatsApp. Send the WhatsApp (it has the booking link), log SENT_LINK."),IF(F15>=SETTINGS!$B$6,"LAST TRY. ","")&IF((INDEX(DESK!$S$2:$S$601,O15)="SENT_LINK"),"Open Calendar 1. Already booked? Log SELF_BOOKED. Not booked? Call, send the WhatsApp, log what happened.",IF((INDEX(DESK!$AC$2:$AC$601,O15)="YES"),"Call. They say yes? Open Calendar 1, book the first time that suits them, log BOOKED. No answer? Send the WhatsApp, log NO_ANSWER.","Call. They say yes? Send the WhatsApp (it has the booking link), log SENT_LINK. No answer? Send the WhatsApp, log NO_ANSWER.")))&IF(INDEX(DESK!$AS$2:$AS$601,O15)="FAILED"," (Our WhatsApp did not deliver: call only.)","")) | H15: =IF(O15="","",HYPERLINK("tel:+91"&C15,"Call "&C15)) | I15: =IF(O15="","",IF(LEN("https://wa.me/91"&C15&"?text="&_xlfn.ENCODEURL(M15))<=255,HYPERLINK("https://wa.me/91"&C15&"?text="&_xlfn.ENCODEURL(M15),"Open WhatsApp"),HYPERLINK("https://wa.me/91"&C15,"Open WhatsApp, paste column M"))) | J15: =IF(O15="","",HYPERLINK(INDEX(DESK!$AD$2:$AD$601,O15),INDEX(DESK!$B$2:$B$601,O15))) | K15: =IF(O15="","",IFERROR(HYPERLINK(INDEX(DESK!$AD$2:$AD$601,MATCH($C15&"|2",DESK!$AJ$2:$AJ$601,0)),INDEX(DESK!$B$2:$B$601,MATCH($C15&"|2",DESK!$AJ$2:$AJ$601,0))),"")) | L15: =IF(O15="","",IFERROR(HYPERLINK(INDEX(DESK!$AD$2:$AD$601,MATCH($C15&"|3",DESK!$AJ$2:$AJ$601,0)),INDEX(DESK!$B$2:$B$601,MATCH($C15&"|3",DESK!$AJ$2:$AJ$601,0))),"")) | M15: =IF(O15="","",SUBSTITUTE(SUBSTITUTE(SUBSTITUTE(SUBSTITUTE(INDEX(LISTS!$B$14:$B$19,MATCH(P15,LISTS!$A$14:$A$19,0))&IF(IF((INDEX(DESK!$AC$2:$AC$601,O15)="YES"),"",INDEX(DESK!$AD$2:$AD$601,O15))="",INDEX(LISTS!$B$14:$B$19,MATCH("YES",LISTS!$A$14:$A$19,0)),INDEX(LISTS!$B$14:$B$19,MATCH("NO",LISTS!$A$14:$A$19,0))),"{NAME}",INDEX(DESK!$AQ$2:$AQ$601,O15)),"{INTERN}",$B$2),"{COMPANY}",INDEX(DESK!$B$2:$B$601,O15)&IF(INDEX(DESK!$AA$2:$AA$601,O15)>1," and "&(INDEX(DESK!$AA$2:$AA$601,O15)-1)&" more","")),"{LINK}",IF((INDEX(DESK!$AC$2:$AC$601,O15)="YES"),"",INDEX(DESK!$AD$2:$AD$601,O15)))) | N15: =$B$2&"|"&A15 -> Ram|9 | O15: =IFERROR(MATCH(N15,DESK!$AI$2:$AI$601,0),"") | P15: =IF(O15="","",IF((INDEX(DESK!$S$2:$S$601,O15)="SENT_LINK"),"CHK",IF(F15=1,"T1",IF(F15>=SETTINGS!$B$6,"T3","T2"))))
A16: 10 | B16: =IF(O16="","",INDEX(DESK!$D$2:$D$601,O16)) | C16: =IF(O16="","",INDEX(DESK!$F$2:$F$601,O16)) | D16: =IF(O16="","",INDEX(DESK!$AW$2:$AW$601,O16)&" "&INDEX(DESK!$B$2:$B$601,O16)&" "&INDEX(DESK!$G$2:$G$601,O16)&IFERROR("; "&INDEX(DESK!$AW$2:$AW$601,MATCH($C16&"|2",DESK!$AJ$2:$AJ$601,0))&" "&INDEX(DESK!$B$2:$B$601,MATCH($C16&"|2",DESK!$AJ$2:$AJ$601,0))&" "&INDEX(DESK!$G$2:$G$601,MATCH($C16&"|2",DESK!$AJ$2:$AJ$601,0)),"")&IFERROR("; "&INDEX(DESK!$AW$2:$AW$601,MATCH($C16&"|3",DESK!$AJ$2:$AJ$601,0))&" "&INDEX(DESK!$B$2:$B$601,MATCH($C16&"|3",DESK!$AJ$2:$AJ$601,0))&" "&INDEX(DESK!$G$2:$G$601,MATCH($C16&"|3",DESK!$AJ$2:$AJ$601,0)),"")) | E16: =IF(O16="","",ROUND(INDEX(DESK!$W$2:$W$601,O16),1)) | F16: =IF(O16="","",INDEX(DESK!$Q$2:$Q$601,O16)+1) | G16: =IF(O16="","",IF((INDEX(DESK!$AU$2:$AU$601,O16)=1),IF((INDEX(DESK!$AC$2:$AC$601,O16)="YES"),"REPLIED YES on WhatsApp. Open Calendar 1, book the first free slot, WhatsApp them the time, log BOOKED.","REPLIED YES on WhatsApp. Send the WhatsApp (it has the booking link), log SENT_LINK."),IF(F16>=SETTINGS!$B$6,"LAST TRY. ","")&IF((INDEX(DESK!$S$2:$S$601,O16)="SENT_LINK"),"Open Calendar 1. Already booked? Log SELF_BOOKED. Not booked? Call, send the WhatsApp, log what happened.",IF((INDEX(DESK!$AC$2:$AC$601,O16)="YES"),"Call. They say yes? Open Calendar 1, book the first time that suits them, log BOOKED. No answer? Send the WhatsApp, log NO_ANSWER.","Call. They say yes? Send the WhatsApp (it has the booking link), log SENT_LINK. No answer? Send the WhatsApp, log NO_ANSWER.")))&IF(INDEX(DESK!$AS$2:$AS$601,O16)="FAILED"," (Our WhatsApp did not deliver: call only.)","")) | H16: =IF(O16="","",HYPERLINK("tel:+91"&C16,"Call "&C16)) | I16: =IF(O16="","",IF(LEN("https://wa.me/91"&C16&"?text="&_xlfn.ENCODEURL(M16))<=255,HYPERLINK("https://wa.me/91"&C16&"?text="&_xlfn.ENCODEURL(M16),"Open WhatsApp"),HYPERLINK("https://wa.me/91"&C16,"Open WhatsApp, paste column M"))) | J16: =IF(O16="","",HYPERLINK(INDEX(DESK!$AD$2:$AD$601,O16),INDEX(DESK!$B$2:$B$601,O16))) | K16: =IF(O16="","",IFERROR(HYPERLINK(INDEX(DESK!$AD$2:$AD$601,MATCH($C16&"|2",DESK!$AJ$2:$AJ$601,0)),INDEX(DESK!$B$2:$B$601,MATCH($C16&"|2",DESK!$AJ$2:$AJ$601,0))),"")) | L16: =IF(O16="","",IFERROR(HYPERLINK(INDEX(DESK!$AD$2:$AD$601,MATCH($C16&"|3",DESK!$AJ$2:$AJ$601,0)),INDEX(DESK!$B$2:$B$601,MATCH($C16&"|3",DESK!$AJ$2:$AJ$601,0))),"")) | M16: =IF(O16="","",SUBSTITUTE(SUBSTITUTE(SUBSTITUTE(SUBSTITUTE(INDEX(LISTS!$B$14:$B$19,MATCH(P16,LISTS!$A$14:$A$19,0))&IF(IF((INDEX(DESK!$AC$2:$AC$601,O16)="YES"),"",INDEX(DESK!$AD$2:$AD$601,O16))="",INDEX(LISTS!$B$14:$B$19,MATCH("YES",LISTS!$A$14:$A$19,0)),INDEX(LISTS!$B$14:$B$19,MATCH("NO",LISTS!$A$14:$A$19,0))),"{NAME}",INDEX(DESK!$AQ$2:$AQ$601,O16)),"{INTERN}",$B$2),"{COMPANY}",INDEX(DESK!$B$2:$B$601,O16)&IF(INDEX(DESK!$AA$2:$AA$601,O16)>1," and "&(INDEX(DESK!$AA$2:$AA$601,O16)-1)&" more","")),"{LINK}",IF((INDEX(DESK!$AC$2:$AC$601,O16)="YES"),"",INDEX(DESK!$AD$2:$AD$601,O16)))) | N16: =$B$2&"|"&A16 -> Ram|10 | O16: =IFERROR(MATCH(N16,DESK!$AI$2:$AI$601,0),"") | P16: =IF(O16="","",IF((INDEX(DESK!$S$2:$S$601,O16)="SENT_LINK"),"CHK",IF(F16=1,"T1",IF(F16>=SETTINGS!$B$6,"T3","T2"))))
A17: 11 | B17: =IF(O17="","",INDEX(DESK!$D$2:$D$601,O17)) | C17: =IF(O17="","",INDEX(DESK!$F$2:$F$601,O17)) | D17: =IF(O17="","",INDEX(DESK!$AW$2:$AW$601,O17)&" "&INDEX(DESK!$B$2:$B$601,O17)&" "&INDEX(DESK!$G$2:$G$601,O17)&IFERROR("; "&INDEX(DESK!$AW$2:$AW$601,MATCH($C17&"|2",DESK!$AJ$2:$AJ$601,0))&" "&INDEX(DESK!$B$2:$B$601,MATCH($C17&"|2",DESK!$AJ$2:$AJ$601,0))&" "&INDEX(DESK!$G$2:$G$601,MATCH($C17&"|2",DESK!$AJ$2:$AJ$601,0)),"")&IFERROR("; "&INDEX(DESK!$AW$2:$AW$601,MATCH($C17&"|3",DESK!$AJ$2:$AJ$601,0))&" "&INDEX(DESK!$B$2:$B$601,MATCH($C17&"|3",DESK!$AJ$2:$AJ$601,0))&" "&INDEX(DESK!$G$2:$G$601,MATCH($C17&"|3",DESK!$AJ$2:$AJ$601,0)),"")) | E17: =IF(O17="","",ROUND(INDEX(DESK!$W$2:$W$601,O17),1)) | F17: =IF(O17="","",INDEX(DESK!$Q$2:$Q$601,O17)+1) | G17: =IF(O17="","",IF((INDEX(DESK!$AU$2:$AU$601,O17)=1),IF((INDEX(DESK!$AC$2:$AC$601,O17)="YES"),"REPLIED YES on WhatsApp. Open Calendar 1, book the first free slot, WhatsApp them the time, log BOOKED.","REPLIED YES on WhatsApp. Send the WhatsApp (it has the booking link), log SENT_LINK."),IF(F17>=SETTINGS!$B$6,"LAST TRY. ","")&IF((INDEX(DESK!$S$2:$S$601,O17)="SENT_LINK"),"Open Calendar 1. Already booked? Log SELF_BOOKED. Not booked? Call, send the WhatsApp, log what happened.",IF((INDEX(DESK!$AC$2:$AC$601,O17)="YES"),"Call. They say yes? Open Calendar 1, book the first time that suits them, log BOOKED. No answer? Send the WhatsApp, log NO_ANSWER.","Call. They say yes? Send the WhatsApp (it has the booking link), log SENT_LINK. No answer? Send the WhatsApp, log NO_ANSWER.")))&IF(INDEX(DESK!$AS$2:$AS$601,O17)="FAILED"," (Our WhatsApp did not deliver: call only.)","")) | H17: =IF(O17="","",HYPERLINK("tel:+91"&C17,"Call "&C17)) | I17: =IF(O17="","",IF(LEN("https://wa.me/91"&C17&"?text="&_xlfn.ENCODEURL(M17))<=255,HYPERLINK("https://wa.me/91"&C17&"?text="&_xlfn.ENCODEURL(M17),"Open WhatsApp"),HYPERLINK("https://wa.me/91"&C17,"Open WhatsApp, paste column M"))) | J17: =IF(O17="","",HYPERLINK(INDEX(DESK!$AD$2:$AD$601,O17),INDEX(DESK!$B$2:$B$601,O17))) | K17: =IF(O17="","",IFERROR(HYPERLINK(INDEX(DESK!$AD$2:$AD$601,MATCH($C17&"|2",DESK!$AJ$2:$AJ$601,0)),INDEX(DESK!$B$2:$B$601,MATCH($C17&"|2",DESK!$AJ$2:$AJ$601,0))),"")) | L17: =IF(O17="","",IFERROR(HYPERLINK(INDEX(DESK!$AD$2:$AD$601,MATCH($C17&"|3",DESK!$AJ$2:$AJ$601,0)),INDEX(DESK!$B$2:$B$601,MATCH($C17&"|3",DESK!$AJ$2:$AJ$601,0))),"")) | M17: =IF(O17="","",SUBSTITUTE(SUBSTITUTE(SUBSTITUTE(SUBSTITUTE(INDEX(LISTS!$B$14:$B$19,MATCH(P17,LISTS!$A$14:$A$19,0))&IF(IF((INDEX(DESK!$AC$2:$AC$601,O17)="YES"),"",INDEX(DESK!$AD$2:$AD$601,O17))="",INDEX(LISTS!$B$14:$B$19,MATCH("YES",LISTS!$A$14:$A$19,0)),INDEX(LISTS!$B$14:$B$19,MATCH("NO",LISTS!$A$14:$A$19,0))),"{NAME}",INDEX(DESK!$AQ$2:$AQ$601,O17)),"{INTERN}",$B$2),"{COMPANY}",INDEX(DESK!$B$2:$B$601,O17)&IF(INDEX(DESK!$AA$2:$AA$601,O17)>1," and "&(INDEX(DESK!$AA$2:$AA$601,O17)-1)&" more","")),"{LINK}",IF((INDEX(DESK!$AC$2:$AC$601,O17)="YES"),"",INDEX(DESK!$AD$2:$AD$601,O17)))) | N17: =$B$2&"|"&A17 -> Ram|11 | O17: =IFERROR(MATCH(N17,DESK!$AI$2:$AI$601,0),"") | P17: =IF(O17="","",IF((INDEX(DESK!$S$2:$S$601,O17)="SENT_LINK"),"CHK",IF(F17=1,"T1",IF(F17>=SETTINGS!$B$6,"T3","T2"))))
A18: 12 | B18: =IF(O18="","",INDEX(DESK!$D$2:$D$601,O18)) | C18: =IF(O18="","",INDEX(DESK!$F$2:$F$601,O18)) | D18: =IF(O18="","",INDEX(DESK!$AW$2:$AW$601,O18)&" "&INDEX(DESK!$B$2:$B$601,O18)&" "&INDEX(DESK!$G$2:$G$601,O18)&IFERROR("; "&INDEX(DESK!$AW$2:$AW$601,MATCH($C18&"|2",DESK!$AJ$2:$AJ$601,0))&" "&INDEX(DESK!$B$2:$B$601,MATCH($C18&"|2",DESK!$AJ$2:$AJ$601,0))&" "&INDEX(DESK!$G$2:$G$601,MATCH($C18&"|2",DESK!$AJ$2:$AJ$601,0)),"")&IFERROR("; "&INDEX(DESK!$AW$2:$AW$601,MATCH($C18&"|3",DESK!$AJ$2:$AJ$601,0))&" "&INDEX(DESK!$B$2:$B$601,MATCH($C18&"|3",DESK!$AJ$2:$AJ$601,0))&" "&INDEX(DESK!$G$2:$G$601,MATCH($C18&"|3",DESK!$AJ$2:$AJ$601,0)),"")) | E18: =IF(O18="","",ROUND(INDEX(DESK!$W$2:$W$601,O18),1)) | F18: =IF(O18="","",INDEX(DESK!$Q$2:$Q$601,O18)+1) | G18: =IF(O18="","",IF((INDEX(DESK!$AU$2:$AU$601,O18)=1),IF((INDEX(DESK!$AC$2:$AC$601,O18)="YES"),"REPLIED YES on WhatsApp. Open Calendar 1, book the first free slot, WhatsApp them the time, log BOOKED.","REPLIED YES on WhatsApp. Send the WhatsApp (it has the booking link), log SENT_LINK."),IF(F18>=SETTINGS!$B$6,"LAST TRY. ","")&IF((INDEX(DESK!$S$2:$S$601,O18)="SENT_LINK"),"Open Calendar 1. Already booked? Log SELF_BOOKED. Not booked? Call, send the WhatsApp, log what happened.",IF((INDEX(DESK!$AC$2:$AC$601,O18)="YES"),"Call. They say yes? Open Calendar 1, book the first time that suits them, log BOOKED. No answer? Send the WhatsApp, log NO_ANSWER.","Call. They say yes? Send the WhatsApp (it has the booking link), log SENT_LINK. No answer? Send the WhatsApp, log NO_ANSWER.")))&IF(INDEX(DESK!$AS$2:$AS$601,O18)="FAILED"," (Our WhatsApp did not deliver: call only.)","")) | H18: =IF(O18="","",HYPERLINK("tel:+91"&C18,"Call "&C18)) | I18: =IF(O18="","",IF(LEN("https://wa.me/91"&C18&"?text="&_xlfn.ENCODEURL(M18))<=255,HYPERLINK("https://wa.me/91"&C18&"?text="&_xlfn.ENCODEURL(M18),"Open WhatsApp"),HYPERLINK("https://wa.me/91"&C18,"Open WhatsApp, paste column M"))) | J18: =IF(O18="","",HYPERLINK(INDEX(DESK!$AD$2:$AD$601,O18),INDEX(DESK!$B$2:$B$601,O18))) | K18: =IF(O18="","",IFERROR(HYPERLINK(INDEX(DESK!$AD$2:$AD$601,MATCH($C18&"|2",DESK!$AJ$2:$AJ$601,0)),INDEX(DESK!$B$2:$B$601,MATCH($C18&"|2",DESK!$AJ$2:$AJ$601,0))),"")) | L18: =IF(O18="","",IFERROR(HYPERLINK(INDEX(DESK!$AD$2:$AD$601,MATCH($C18&"|3",DESK!$AJ$2:$AJ$601,0)),INDEX(DESK!$B$2:$B$601,MATCH($C18&"|3",DESK!$AJ$2:$AJ$601,0))),"")) | M18: =IF(O18="","",SUBSTITUTE(SUBSTITUTE(SUBSTITUTE(SUBSTITUTE(INDEX(LISTS!$B$14:$B$19,MATCH(P18,LISTS!$A$14:$A$19,0))&IF(IF((INDEX(DESK!$AC$2:$AC$601,O18)="YES"),"",INDEX(DESK!$AD$2:$AD$601,O18))="",INDEX(LISTS!$B$14:$B$19,MATCH("YES",LISTS!$A$14:$A$19,0)),INDEX(LISTS!$B$14:$B$19,MATCH("NO",LISTS!$A$14:$A$19,0))),"{NAME}",INDEX(DESK!$AQ$2:$AQ$601,O18)),"{INTERN}",$B$2),"{COMPANY}",INDEX(DESK!$B$2:$B$601,O18)&IF(INDEX(DESK!$AA$2:$AA$601,O18)>1," and "&(INDEX(DESK!$AA$2:$AA$601,O18)-1)&" more","")),"{LINK}",IF((INDEX(DESK!$AC$2:$AC$601,O18)="YES"),"",INDEX(DESK!$AD$2:$AD$601,O18)))) | N18: =$B$2&"|"&A18 -> Ram|12 | O18: =IFERROR(MATCH(N18,DESK!$AI$2:$AI$601,0),"") | P18: =IF(O18="","",IF((INDEX(DESK!$S$2:$S$601,O18)="SENT_LINK"),"CHK",IF(F18=1,"T1",IF(F18>=SETTINGS!$B$6,"T3","T2"))))
... A31: 25 | B31: =IF(O31="","",INDEX(DESK!$D$2:$D$601,O31)) | C31: =IF(O31="","",INDEX(DESK!$F$2:$F$601,O31)) | D31: =IF(O31="","",INDEX(DESK!$AW$2:$AW$601,O31)&" "&INDEX(DESK!$B$2:$B$601,O31)&" "&INDEX(DESK!$G$2:$G$601,O31)&IFERROR("; "&INDEX(DESK!$AW$2:$AW$601,MATCH($C31&"|2",DESK!$AJ$2:$AJ$601,0))&" "&INDEX(DESK!$B$2:$B$601,MATCH($C31&"|2",DESK!$AJ$2:$AJ$601,0))&" "&INDEX(DESK!$G$2:$G$601,MATCH($C31&"|2",DESK!$AJ$2:$AJ$601,0)),"")&IFERROR("; "&INDEX(DESK!$AW$2:$AW$601,MATCH($C31&"|3",DESK!$AJ$2:$AJ$601,0))&" "&INDEX(DESK!$B$2:$B$601,MATCH($C31&"|3",DESK!$AJ$2:$AJ$601,0))&" "&INDEX(DESK!$G$2:$G$601,MATCH($C31&"|3",DESK!$AJ$2:$AJ$601,0)),"")) | E31: =IF(O31="","",ROUND(INDEX(DESK!$W$2:$W$601,O31),1)) | F31: =IF(O31="","",INDEX(DESK!$Q$2:$Q$601,O31)+1) | G31: =IF(O31="","",IF((INDEX(DESK!$AU$2:$AU$601,O31)=1),IF((INDEX(DESK!$AC$2:$AC$601,O31)="YES"),"REPLIED YES on WhatsApp. Open Calendar 1, book the first free slot, WhatsApp them the time, log BOOKED.","REPLIED YES on WhatsApp. Send the WhatsApp (it has the booking link), log SENT_LINK."),IF(F31>=SETTINGS!$B$6,"LAST TRY. ","")&IF((INDEX(DESK!$S$2:$S$601,O31)="SENT_LINK"),"Open Calendar 1. Already booked? Log SELF_BOOKED. Not booked? Call, send the WhatsApp, log what happened.",IF((INDEX(DESK!$AC$2:$AC$601,O31)="YES"),"Call. They say yes? Open Calendar 1, book the first time that suits them, log BOOKED. No answer? Send the WhatsApp, log NO_ANSWER.","Call. They say yes? Send the WhatsApp (it has the booking link), log SENT_LINK. No answer? Send the WhatsApp, log NO_ANSWER.")))&IF(INDEX(DESK!$AS$2:$AS$601,O31)="FAILED"," (Our WhatsApp did not deliver: call only.)","")) | H31: =IF(O31="","",HYPERLINK("tel:+91"&C31,"Call "&C31)) | I31: =IF(O31="","",IF(LEN("https://wa.me/91"&C31&"?text="&_xlfn.ENCODEURL(M31))<=255,HYPERLINK("https://wa.me/91"&C31&"?text="&_xlfn.ENCODEURL(M31),"Open WhatsApp"),HYPERLINK("https://wa.me/91"&C31,"Open WhatsApp, paste column M"))) | J31: =IF(O31="","",HYPERLINK(INDEX(DESK!$AD$2:$AD$601,O31),INDEX(DESK!$B$2:$B$601,O31))) | K31: =IF(O31="","",IFERROR(HYPERLINK(INDEX(DESK!$AD$2:$AD$601,MATCH($C31&"|2",DESK!$AJ$2:$AJ$601,0)),INDEX(DESK!$B$2:$B$601,MATCH($C31&"|2",DESK!$AJ$2:$AJ$601,0))),"")) | L31: =IF(O31="","",IFERROR(HYPERLINK(INDEX(DESK!$AD$2:$AD$601,MATCH($C31&"|3",DESK!$AJ$2:$AJ$601,0)),INDEX(DESK!$B$2:$B$601,MATCH($C31&"|3",DESK!$AJ$2:$AJ$601,0))),"")) | M31: =IF(O31="","",SUBSTITUTE(SUBSTITUTE(SUBSTITUTE(SUBSTITUTE(INDEX(LISTS!$B$14:$B$19,MATCH(P31,LISTS!$A$14:$A$19,0))&IF(IF((INDEX(DESK!$AC$2:$AC$601,O31)="YES"),"",INDEX(DESK!$AD$2:$AD$601,O31))="",INDEX(LISTS!$B$14:$B$19,MATCH("YES",LISTS!$A$14:$A$19,0)),INDEX(LISTS!$B$14:$B$19,MATCH("NO",LISTS!$A$14:$A$19,0))),"{NAME}",INDEX(DESK!$AQ$2:$AQ$601,O31)),"{INTERN}",$B$2),"{COMPANY}",INDEX(DESK!$B$2:$B$601,O31)&IF(INDEX(DESK!$AA$2:$AA$601,O31)>1," and "&(INDEX(DESK!$AA$2:$AA$601,O31)-1)&" more","")),"{LINK}",IF((INDEX(DESK!$AC$2:$AC$601,O31)="YES"),"",INDEX(DESK!$AD$2:$AD$601,O31)))) | N31: =$B$2&"|"&A31 -> Ram|25 | O31: =IFERROR(MATCH(N31,DESK!$AI$2:$AI$601,0),"") | P31: =IF(O31="","",IF((INDEX(DESK!$S$2:$S$601,O31)="SENT_LINK"),"CHK",IF(F31=1,"T1",IF(F31>=SETTINGS!$B$6,"T3","T2"))))

Sheet SHYAM
A1: SHYAM: your list. Start at the top. Do what column G says.
B2: Shyam | C2: Time now | D2: =SETTINGS!$B$4 -> 46309.828 | G2: =C3&" people waiting" -> 0 people waiting | N2: =SETTINGS!$B$14 -> 4
A3: =IF(ROUND(MOD(SETTINGS!$B$4,1)*1440,0)<ROUND(SETTINGS!$B$11*1440,0),"Your shift has not started. Nothing to do yet.",IF(ROUND(MOD(SETTINGS!$B$4,1)*1440,0)>=ROUND(SETTINGS!$B$12*1440,0),"Your shift is over. Thank you!",IF($C$3=0,"Nothing waiting right now. Check LOG column J for lines marked in orange.",""))) -> Nothing waiting right now. Check LOG column J for lines marked in orange. | C3: =SUMPRODUCT((DESK!$Z$2:$Z$601=$B$2)*(DESK!$AI$2:$AI$601<>"")) -> 0
A4: Reply or call-back? Phone: | E4: =IF($D$4="","",IF(IFERROR(MATCH($D$4&"|1",DESK!$AJ$2:$AJ$601,0),"")="","Not on the open list (already done, or wrong number).",INDEX(DESK!$AW$2:$AW$601,IFERROR(MATCH($D$4&"|1",DESK!$AJ$2:$AJ$601,0),""))&" "&INDEX(DESK!$B$2:$B$601,IFERROR(MATCH($D$4&"|1",DESK!$AJ$2:$AJ$601,0),""))&" "&INDEX(DESK!$G$2:$G$601,IFERROR(MATCH($D$4&"|1",DESK!$AJ$2:$AJ$601,0),""))&IF(IFERROR(MATCH($D$4&"|2",DESK!$AJ$2:$AJ$601,0),"")="","","; "&INDEX(DESK!$AW$2:$AW$601,IFERROR(MATCH($D$4&"|2",DESK!$AJ$2:$AJ$601,0),""))&" "&INDEX(DESK!$B$2:$B$601,IFERROR(MATCH($D$4&"|2",DESK!$AJ$2:$AJ$601,0),""))&" "&INDEX(DESK!$G$2:$G$601,IFERROR(MATCH($D$4&"|2",DESK!$AJ$2:$AJ$601,0),"")))&IF(IFERROR(MATCH($D$4&"|3",DESK!$AJ$2:$AJ$601,0),"")="","","; "&INDEX(DESK!$AW$2:$AW$601,IFERROR(MATCH($D$4&"|3",DESK!$AJ$2:$AJ$601,0),""))&" "&INDEX(DESK!$B$2:$B$601,IFERROR(MATCH($D$4&"|3",DESK!$AJ$2:$AJ$601,0),""))&" "&INDEX(DESK!$G$2:$G$601,IFERROR(MATCH($D$4&"|3",DESK!$AJ$2:$AJ$601,0),"")))&IF(INDEX(DESK!$AC$2:$AC$601,IFERROR(MATCH($D$4&"|1",DESK!$AJ$2:$AJ$601,0),""))="YES"," : they said yes? Book it, log BOOKED."," : send the link, log SENT_LINK."))) | J4: =IF(IFERROR(MATCH($D$4&"|1",DESK!$AJ$2:$AJ$601,0),"")="","",HYPERLINK(INDEX(DESK!$AD$2:$AD$601,IFERROR(MATCH($D$4&"|1",DESK!$AJ$2:$AJ$601,0),"")),"Calendar: "&INDEX(DESK!$B$2:$B$601,IFERROR(MATCH($D$4&"|1",DESK!$AJ$2:$AJ$601,0),"")))) | K4: =IF(IFERROR(MATCH($D$4&"|2",DESK!$AJ$2:$AJ$601,0),"")="","",HYPERLINK(INDEX(DESK!$AD$2:$AD$601,IFERROR(MATCH($D$4&"|2",DESK!$AJ$2:$AJ$601,0),"")),"Calendar: "&INDEX(DESK!$B$2:$B$601,IFERROR(MATCH($D$4&"|2",DESK!$AJ$2:$AJ$601,0),"")))) | L4: =IF(IFERROR(MATCH($D$4&"|3",DESK!$AJ$2:$AJ$601,0),"")="","",HYPERLINK(INDEX(DESK!$AD$2:$AD$601,IFERROR(MATCH($D$4&"|3",DESK!$AJ$2:$AJ$601,0),"")),"Calendar: "&INDEX(DESK!$B$2:$B$601,IFERROR(MATCH($D$4&"|3",DESK!$AJ$2:$AJ$601,0),""))))
A6: # | B6: Candidate | C6: Phone | D6: Interviews to book (request ID first) | E6: Hours left | F6: Try | G6: WHAT TO DO | H6: Call | I6: WhatsApp | J6: Calendar 1 | K6: Calendar 2 | L6: Calendar 3 | M6: Message (copy if WhatsApp opens empty) | N6: key | O6: row | P6: msg
A7: 1 | B7: =IF(O7="","",INDEX(DESK!$D$2:$D$601,O7)) | C7: =IF(O7="","",INDEX(DESK!$F$2:$F$601,O7)) | D7: =IF(O7="","",INDEX(DESK!$AW$2:$AW$601,O7)&" "&INDEX(DESK!$B$2:$B$601,O7)&" "&INDEX(DESK!$G$2:$G$601,O7)&IFERROR("; "&INDEX(DESK!$AW$2:$AW$601,MATCH($C7&"|2",DESK!$AJ$2:$AJ$601,0))&" "&INDEX(DESK!$B$2:$B$601,MATCH($C7&"|2",DESK!$AJ$2:$AJ$601,0))&" "&INDEX(DESK!$G$2:$G$601,MATCH($C7&"|2",DESK!$AJ$2:$AJ$601,0)),"")&IFERROR("; "&INDEX(DESK!$AW$2:$AW$601,MATCH($C7&"|3",DESK!$AJ$2:$AJ$601,0))&" "&INDEX(DESK!$B$2:$B$601,MATCH($C7&"|3",DESK!$AJ$2:$AJ$601,0))&" "&INDEX(DESK!$G$2:$G$601,MATCH($C7&"|3",DESK!$AJ$2:$AJ$601,0)),"")) | E7: =IF(O7="","",ROUND(INDEX(DESK!$W$2:$W$601,O7),1)) | F7: =IF(O7="","",INDEX(DESK!$Q$2:$Q$601,O7)+1) | G7: =IF(O7="","",IF((INDEX(DESK!$AU$2:$AU$601,O7)=1),IF((INDEX(DESK!$AC$2:$AC$601,O7)="YES"),"REPLIED YES on WhatsApp. Open Calendar 1, book the first free slot, WhatsApp them the time, log BOOKED.","REPLIED YES on WhatsApp. Send the WhatsApp (it has the booking link), log SENT_LINK."),IF(F7>=SETTINGS!$B$6,"LAST TRY. ","")&IF((INDEX(DESK!$S$2:$S$601,O7)="SENT_LINK"),"Open Calendar 1. Already booked? Log SELF_BOOKED. Not booked? Call, send the WhatsApp, log what happened.",IF((INDEX(DESK!$AC$2:$AC$601,O7)="YES"),"Call. They say yes? Open Calendar 1, book the first time that suits them, log BOOKED. No answer? Send the WhatsApp, log NO_ANSWER.","Call. They say yes? Send the WhatsApp (it has the booking link), log SENT_LINK. No answer? Send the WhatsApp, log NO_ANSWER.")))&IF(INDEX(DESK!$AS$2:$AS$601,O7)="FAILED"," (Our WhatsApp did not deliver: call only.)","")) | H7: =IF(O7="","",HYPERLINK("tel:+91"&C7,"Call "&C7)) | I7: =IF(O7="","",IF(LEN("https://wa.me/91"&C7&"?text="&_xlfn.ENCODEURL(M7))<=255,HYPERLINK("https://wa.me/91"&C7&"?text="&_xlfn.ENCODEURL(M7),"Open WhatsApp"),HYPERLINK("https://wa.me/91"&C7,"Open WhatsApp, paste column M"))) | J7: =IF(O7="","",HYPERLINK(INDEX(DESK!$AD$2:$AD$601,O7),INDEX(DESK!$B$2:$B$601,O7))) | K7: =IF(O7="","",IFERROR(HYPERLINK(INDEX(DESK!$AD$2:$AD$601,MATCH($C7&"|2",DESK!$AJ$2:$AJ$601,0)),INDEX(DESK!$B$2:$B$601,MATCH($C7&"|2",DESK!$AJ$2:$AJ$601,0))),"")) | L7: =IF(O7="","",IFERROR(HYPERLINK(INDEX(DESK!$AD$2:$AD$601,MATCH($C7&"|3",DESK!$AJ$2:$AJ$601,0)),INDEX(DESK!$B$2:$B$601,MATCH($C7&"|3",DESK!$AJ$2:$AJ$601,0))),"")) | M7: =IF(O7="","",SUBSTITUTE(SUBSTITUTE(SUBSTITUTE(SUBSTITUTE(INDEX(LISTS!$B$14:$B$19,MATCH(P7,LISTS!$A$14:$A$19,0))&IF(IF((INDEX(DESK!$AC$2:$AC$601,O7)="YES"),"",INDEX(DESK!$AD$2:$AD$601,O7))="",INDEX(LISTS!$B$14:$B$19,MATCH("YES",LISTS!$A$14:$A$19,0)),INDEX(LISTS!$B$14:$B$19,MATCH("NO",LISTS!$A$14:$A$19,0))),"{NAME}",INDEX(DESK!$AQ$2:$AQ$601,O7)),"{INTERN}",$B$2),"{COMPANY}",INDEX(DESK!$B$2:$B$601,O7)&IF(INDEX(DESK!$AA$2:$AA$601,O7)>1," and "&(INDEX(DESK!$AA$2:$AA$601,O7)-1)&" more","")),"{LINK}",IF((INDEX(DESK!$AC$2:$AC$601,O7)="YES"),"",INDEX(DESK!$AD$2:$AD$601,O7)))) | N7: =$B$2&"|"&A7 -> Shyam|1 | O7: =IFERROR(MATCH(N7,DESK!$AI$2:$AI$601,0),"") | P7: =IF(O7="","",IF((INDEX(DESK!$S$2:$S$601,O7)="SENT_LINK"),"CHK",IF(F7=1,"T1",IF(F7>=SETTINGS!$B$6,"T3","T2"))))
A8: 2 | B8: =IF(O8="","",INDEX(DESK!$D$2:$D$601,O8)) | C8: =IF(O8="","",INDEX(DESK!$F$2:$F$601,O8)) | D8: =IF(O8="","",INDEX(DESK!$AW$2:$AW$601,O8)&" "&INDEX(DESK!$B$2:$B$601,O8)&" "&INDEX(DESK!$G$2:$G$601,O8)&IFERROR("; "&INDEX(DESK!$AW$2:$AW$601,MATCH($C8&"|2",DESK!$AJ$2:$AJ$601,0))&" "&INDEX(DESK!$B$2:$B$601,MATCH($C8&"|2",DESK!$AJ$2:$AJ$601,0))&" "&INDEX(DESK!$G$2:$G$601,MATCH($C8&"|2",DESK!$AJ$2:$AJ$601,0)),"")&IFERROR("; "&INDEX(DESK!$AW$2:$AW$601,MATCH($C8&"|3",DESK!$AJ$2:$AJ$601,0))&" "&INDEX(DESK!$B$2:$B$601,MATCH($C8&"|3",DESK!$AJ$2:$AJ$601,0))&" "&INDEX(DESK!$G$2:$G$601,MATCH($C8&"|3",DESK!$AJ$2:$AJ$601,0)),"")) | E8: =IF(O8="","",ROUND(INDEX(DESK!$W$2:$W$601,O8),1)) | F8: =IF(O8="","",INDEX(DESK!$Q$2:$Q$601,O8)+1) | G8: =IF(O8="","",IF((INDEX(DESK!$AU$2:$AU$601,O8)=1),IF((INDEX(DESK!$AC$2:$AC$601,O8)="YES"),"REPLIED YES on WhatsApp. Open Calendar 1, book the first free slot, WhatsApp them the time, log BOOKED.","REPLIED YES on WhatsApp. Send the WhatsApp (it has the booking link), log SENT_LINK."),IF(F8>=SETTINGS!$B$6,"LAST TRY. ","")&IF((INDEX(DESK!$S$2:$S$601,O8)="SENT_LINK"),"Open Calendar 1. Already booked? Log SELF_BOOKED. Not booked? Call, send the WhatsApp, log what happened.",IF((INDEX(DESK!$AC$2:$AC$601,O8)="YES"),"Call. They say yes? Open Calendar 1, book the first time that suits them, log BOOKED. No answer? Send the WhatsApp, log NO_ANSWER.","Call. They say yes? Send the WhatsApp (it has the booking link), log SENT_LINK. No answer? Send the WhatsApp, log NO_ANSWER.")))&IF(INDEX(DESK!$AS$2:$AS$601,O8)="FAILED"," (Our WhatsApp did not deliver: call only.)","")) | H8: =IF(O8="","",HYPERLINK("tel:+91"&C8,"Call "&C8)) | I8: =IF(O8="","",IF(LEN("https://wa.me/91"&C8&"?text="&_xlfn.ENCODEURL(M8))<=255,HYPERLINK("https://wa.me/91"&C8&"?text="&_xlfn.ENCODEURL(M8),"Open WhatsApp"),HYPERLINK("https://wa.me/91"&C8,"Open WhatsApp, paste column M"))) | J8: =IF(O8="","",HYPERLINK(INDEX(DESK!$AD$2:$AD$601,O8),INDEX(DESK!$B$2:$B$601,O8))) | K8: =IF(O8="","",IFERROR(HYPERLINK(INDEX(DESK!$AD$2:$AD$601,MATCH($C8&"|2",DESK!$AJ$2:$AJ$601,0)),INDEX(DESK!$B$2:$B$601,MATCH($C8&"|2",DESK!$AJ$2:$AJ$601,0))),"")) | L8: =IF(O8="","",IFERROR(HYPERLINK(INDEX(DESK!$AD$2:$AD$601,MATCH($C8&"|3",DESK!$AJ$2:$AJ$601,0)),INDEX(DESK!$B$2:$B$601,MATCH($C8&"|3",DESK!$AJ$2:$AJ$601,0))),"")) | M8: =IF(O8="","",SUBSTITUTE(SUBSTITUTE(SUBSTITUTE(SUBSTITUTE(INDEX(LISTS!$B$14:$B$19,MATCH(P8,LISTS!$A$14:$A$19,0))&IF(IF((INDEX(DESK!$AC$2:$AC$601,O8)="YES"),"",INDEX(DESK!$AD$2:$AD$601,O8))="",INDEX(LISTS!$B$14:$B$19,MATCH("YES",LISTS!$A$14:$A$19,0)),INDEX(LISTS!$B$14:$B$19,MATCH("NO",LISTS!$A$14:$A$19,0))),"{NAME}",INDEX(DESK!$AQ$2:$AQ$601,O8)),"{INTERN}",$B$2),"{COMPANY}",INDEX(DESK!$B$2:$B$601,O8)&IF(INDEX(DESK!$AA$2:$AA$601,O8)>1," and "&(INDEX(DESK!$AA$2:$AA$601,O8)-1)&" more","")),"{LINK}",IF((INDEX(DESK!$AC$2:$AC$601,O8)="YES"),"",INDEX(DESK!$AD$2:$AD$601,O8)))) | N8: =$B$2&"|"&A8 -> Shyam|2 | O8: =IFERROR(MATCH(N8,DESK!$AI$2:$AI$601,0),"") | P8: =IF(O8="","",IF((INDEX(DESK!$S$2:$S$601,O8)="SENT_LINK"),"CHK",IF(F8=1,"T1",IF(F8>=SETTINGS!$B$6,"T3","T2"))))
A9: 3 | B9: =IF(O9="","",INDEX(DESK!$D$2:$D$601,O9)) | C9: =IF(O9="","",INDEX(DESK!$F$2:$F$601,O9)) | D9: =IF(O9="","",INDEX(DESK!$AW$2:$AW$601,O9)&" "&INDEX(DESK!$B$2:$B$601,O9)&" "&INDEX(DESK!$G$2:$G$601,O9)&IFERROR("; "&INDEX(DESK!$AW$2:$AW$601,MATCH($C9&"|2",DESK!$AJ$2:$AJ$601,0))&" "&INDEX(DESK!$B$2:$B$601,MATCH($C9&"|2",DESK!$AJ$2:$AJ$601,0))&" "&INDEX(DESK!$G$2:$G$601,MATCH($C9&"|2",DESK!$AJ$2:$AJ$601,0)),"")&IFERROR("; "&INDEX(DESK!$AW$2:$AW$601,MATCH($C9&"|3",DESK!$AJ$2:$AJ$601,0))&" "&INDEX(DESK!$B$2:$B$601,MATCH($C9&"|3",DESK!$AJ$2:$AJ$601,0))&" "&INDEX(DESK!$G$2:$G$601,MATCH($C9&"|3",DESK!$AJ$2:$AJ$601,0)),"")) | E9: =IF(O9="","",ROUND(INDEX(DESK!$W$2:$W$601,O9),1)) | F9: =IF(O9="","",INDEX(DESK!$Q$2:$Q$601,O9)+1) | G9: =IF(O9="","",IF((INDEX(DESK!$AU$2:$AU$601,O9)=1),IF((INDEX(DESK!$AC$2:$AC$601,O9)="YES"),"REPLIED YES on WhatsApp. Open Calendar 1, book the first free slot, WhatsApp them the time, log BOOKED.","REPLIED YES on WhatsApp. Send the WhatsApp (it has the booking link), log SENT_LINK."),IF(F9>=SETTINGS!$B$6,"LAST TRY. ","")&IF((INDEX(DESK!$S$2:$S$601,O9)="SENT_LINK"),"Open Calendar 1. Already booked? Log SELF_BOOKED. Not booked? Call, send the WhatsApp, log what happened.",IF((INDEX(DESK!$AC$2:$AC$601,O9)="YES"),"Call. They say yes? Open Calendar 1, book the first time that suits them, log BOOKED. No answer? Send the WhatsApp, log NO_ANSWER.","Call. They say yes? Send the WhatsApp (it has the booking link), log SENT_LINK. No answer? Send the WhatsApp, log NO_ANSWER.")))&IF(INDEX(DESK!$AS$2:$AS$601,O9)="FAILED"," (Our WhatsApp did not deliver: call only.)","")) | H9: =IF(O9="","",HYPERLINK("tel:+91"&C9,"Call "&C9)) | I9: =IF(O9="","",IF(LEN("https://wa.me/91"&C9&"?text="&_xlfn.ENCODEURL(M9))<=255,HYPERLINK("https://wa.me/91"&C9&"?text="&_xlfn.ENCODEURL(M9),"Open WhatsApp"),HYPERLINK("https://wa.me/91"&C9,"Open WhatsApp, paste column M"))) | J9: =IF(O9="","",HYPERLINK(INDEX(DESK!$AD$2:$AD$601,O9),INDEX(DESK!$B$2:$B$601,O9))) | K9: =IF(O9="","",IFERROR(HYPERLINK(INDEX(DESK!$AD$2:$AD$601,MATCH($C9&"|2",DESK!$AJ$2:$AJ$601,0)),INDEX(DESK!$B$2:$B$601,MATCH($C9&"|2",DESK!$AJ$2:$AJ$601,0))),"")) | L9: =IF(O9="","",IFERROR(HYPERLINK(INDEX(DESK!$AD$2:$AD$601,MATCH($C9&"|3",DESK!$AJ$2:$AJ$601,0)),INDEX(DESK!$B$2:$B$601,MATCH($C9&"|3",DESK!$AJ$2:$AJ$601,0))),"")) | M9: =IF(O9="","",SUBSTITUTE(SUBSTITUTE(SUBSTITUTE(SUBSTITUTE(INDEX(LISTS!$B$14:$B$19,MATCH(P9,LISTS!$A$14:$A$19,0))&IF(IF((INDEX(DESK!$AC$2:$AC$601,O9)="YES"),"",INDEX(DESK!$AD$2:$AD$601,O9))="",INDEX(LISTS!$B$14:$B$19,MATCH("YES",LISTS!$A$14:$A$19,0)),INDEX(LISTS!$B$14:$B$19,MATCH("NO",LISTS!$A$14:$A$19,0))),"{NAME}",INDEX(DESK!$AQ$2:$AQ$601,O9)),"{INTERN}",$B$2),"{COMPANY}",INDEX(DESK!$B$2:$B$601,O9)&IF(INDEX(DESK!$AA$2:$AA$601,O9)>1," and "&(INDEX(DESK!$AA$2:$AA$601,O9)-1)&" more","")),"{LINK}",IF((INDEX(DESK!$AC$2:$AC$601,O9)="YES"),"",INDEX(DESK!$AD$2:$AD$601,O9)))) | N9: =$B$2&"|"&A9 -> Shyam|3 | O9: =IFERROR(MATCH(N9,DESK!$AI$2:$AI$601,0),"") | P9: =IF(O9="","",IF((INDEX(DESK!$S$2:$S$601,O9)="SENT_LINK"),"CHK",IF(F9=1,"T1",IF(F9>=SETTINGS!$B$6,"T3","T2"))))
A10: 4 | B10: =IF(O10="","",INDEX(DESK!$D$2:$D$601,O10)) | C10: =IF(O10="","",INDEX(DESK!$F$2:$F$601,O10)) | D10: =IF(O10="","",INDEX(DESK!$AW$2:$AW$601,O10)&" "&INDEX(DESK!$B$2:$B$601,O10)&" "&INDEX(DESK!$G$2:$G$601,O10)&IFERROR("; "&INDEX(DESK!$AW$2:$AW$601,MATCH($C10&"|2",DESK!$AJ$2:$AJ$601,0))&" "&INDEX(DESK!$B$2:$B$601,MATCH($C10&"|2",DESK!$AJ$2:$AJ$601,0))&" "&INDEX(DESK!$G$2:$G$601,MATCH($C10&"|2",DESK!$AJ$2:$AJ$601,0)),"")&IFERROR("; "&INDEX(DESK!$AW$2:$AW$601,MATCH($C10&"|3",DESK!$AJ$2:$AJ$601,0))&" "&INDEX(DESK!$B$2:$B$601,MATCH($C10&"|3",DESK!$AJ$2:$AJ$601,0))&" "&INDEX(DESK!$G$2:$G$601,MATCH($C10&"|3",DESK!$AJ$2:$AJ$601,0)),"")) | E10: =IF(O10="","",ROUND(INDEX(DESK!$W$2:$W$601,O10),1)) | F10: =IF(O10="","",INDEX(DESK!$Q$2:$Q$601,O10)+1) | G10: =IF(O10="","",IF((INDEX(DESK!$AU$2:$AU$601,O10)=1),IF((INDEX(DESK!$AC$2:$AC$601,O10)="YES"),"REPLIED YES on WhatsApp. Open Calendar 1, book the first free slot, WhatsApp them the time, log BOOKED.","REPLIED YES on WhatsApp. Send the WhatsApp (it has the booking link), log SENT_LINK."),IF(F10>=SETTINGS!$B$6,"LAST TRY. ","")&IF((INDEX(DESK!$S$2:$S$601,O10)="SENT_LINK"),"Open Calendar 1. Already booked? Log SELF_BOOKED. Not booked? Call, send the WhatsApp, log what happened.",IF((INDEX(DESK!$AC$2:$AC$601,O10)="YES"),"Call. They say yes? Open Calendar 1, book the first time that suits them, log BOOKED. No answer? Send the WhatsApp, log NO_ANSWER.","Call. They say yes? Send the WhatsApp (it has the booking link), log SENT_LINK. No answer? Send the WhatsApp, log NO_ANSWER.")))&IF(INDEX(DESK!$AS$2:$AS$601,O10)="FAILED"," (Our WhatsApp did not deliver: call only.)","")) | H10: =IF(O10="","",HYPERLINK("tel:+91"&C10,"Call "&C10)) | I10: =IF(O10="","",IF(LEN("https://wa.me/91"&C10&"?text="&_xlfn.ENCODEURL(M10))<=255,HYPERLINK("https://wa.me/91"&C10&"?text="&_xlfn.ENCODEURL(M10),"Open WhatsApp"),HYPERLINK("https://wa.me/91"&C10,"Open WhatsApp, paste column M"))) | J10: =IF(O10="","",HYPERLINK(INDEX(DESK!$AD$2:$AD$601,O10),INDEX(DESK!$B$2:$B$601,O10))) | K10: =IF(O10="","",IFERROR(HYPERLINK(INDEX(DESK!$AD$2:$AD$601,MATCH($C10&"|2",DESK!$AJ$2:$AJ$601,0)),INDEX(DESK!$B$2:$B$601,MATCH($C10&"|2",DESK!$AJ$2:$AJ$601,0))),"")) | L10: =IF(O10="","",IFERROR(HYPERLINK(INDEX(DESK!$AD$2:$AD$601,MATCH($C10&"|3",DESK!$AJ$2:$AJ$601,0)),INDEX(DESK!$B$2:$B$601,MATCH($C10&"|3",DESK!$AJ$2:$AJ$601,0))),"")) | M10: =IF(O10="","",SUBSTITUTE(SUBSTITUTE(SUBSTITUTE(SUBSTITUTE(INDEX(LISTS!$B$14:$B$19,MATCH(P10,LISTS!$A$14:$A$19,0))&IF(IF((INDEX(DESK!$AC$2:$AC$601,O10)="YES"),"",INDEX(DESK!$AD$2:$AD$601,O10))="",INDEX(LISTS!$B$14:$B$19,MATCH("YES",LISTS!$A$14:$A$19,0)),INDEX(LISTS!$B$14:$B$19,MATCH("NO",LISTS!$A$14:$A$19,0))),"{NAME}",INDEX(DESK!$AQ$2:$AQ$601,O10)),"{INTERN}",$B$2),"{COMPANY}",INDEX(DESK!$B$2:$B$601,O10)&IF(INDEX(DESK!$AA$2:$AA$601,O10)>1," and "&(INDEX(DESK!$AA$2:$AA$601,O10)-1)&" more","")),"{LINK}",IF((INDEX(DESK!$AC$2:$AC$601,O10)="YES"),"",INDEX(DESK!$AD$2:$AD$601,O10)))) | N10: =$B$2&"|"&A10 -> Shyam|4 | O10: =IFERROR(MATCH(N10,DESK!$AI$2:$AI$601,0),"") | P10: =IF(O10="","",IF((INDEX(DESK!$S$2:$S$601,O10)="SENT_LINK"),"CHK",IF(F10=1,"T1",IF(F10>=SETTINGS!$B$6,"T3","T2"))))
A11: 5 | B11: =IF(O11="","",INDEX(DESK!$D$2:$D$601,O11)) | C11: =IF(O11="","",INDEX(DESK!$F$2:$F$601,O11)) | D11: =IF(O11="","",INDEX(DESK!$AW$2:$AW$601,O11)&" "&INDEX(DESK!$B$2:$B$601,O11)&" "&INDEX(DESK!$G$2:$G$601,O11)&IFERROR("; "&INDEX(DESK!$AW$2:$AW$601,MATCH($C11&"|2",DESK!$AJ$2:$AJ$601,0))&" "&INDEX(DESK!$B$2:$B$601,MATCH($C11&"|2",DESK!$AJ$2:$AJ$601,0))&" "&INDEX(DESK!$G$2:$G$601,MATCH($C11&"|2",DESK!$AJ$2:$AJ$601,0)),"")&IFERROR("; "&INDEX(DESK!$AW$2:$AW$601,MATCH($C11&"|3",DESK!$AJ$2:$AJ$601,0))&" "&INDEX(DESK!$B$2:$B$601,MATCH($C11&"|3",DESK!$AJ$2:$AJ$601,0))&" "&INDEX(DESK!$G$2:$G$601,MATCH($C11&"|3",DESK!$AJ$2:$AJ$601,0)),"")) | E11: =IF(O11="","",ROUND(INDEX(DESK!$W$2:$W$601,O11),1)) | F11: =IF(O11="","",INDEX(DESK!$Q$2:$Q$601,O11)+1) | G11: =IF(O11="","",IF((INDEX(DESK!$AU$2:$AU$601,O11)=1),IF((INDEX(DESK!$AC$2:$AC$601,O11)="YES"),"REPLIED YES on WhatsApp. Open Calendar 1, book the first free slot, WhatsApp them the time, log BOOKED.","REPLIED YES on WhatsApp. Send the WhatsApp (it has the booking link), log SENT_LINK."),IF(F11>=SETTINGS!$B$6,"LAST TRY. ","")&IF((INDEX(DESK!$S$2:$S$601,O11)="SENT_LINK"),"Open Calendar 1. Already booked? Log SELF_BOOKED. Not booked? Call, send the WhatsApp, log what happened.",IF((INDEX(DESK!$AC$2:$AC$601,O11)="YES"),"Call. They say yes? Open Calendar 1, book the first time that suits them, log BOOKED. No answer? Send the WhatsApp, log NO_ANSWER.","Call. They say yes? Send the WhatsApp (it has the booking link), log SENT_LINK. No answer? Send the WhatsApp, log NO_ANSWER.")))&IF(INDEX(DESK!$AS$2:$AS$601,O11)="FAILED"," (Our WhatsApp did not deliver: call only.)","")) | H11: =IF(O11="","",HYPERLINK("tel:+91"&C11,"Call "&C11)) | I11: =IF(O11="","",IF(LEN("https://wa.me/91"&C11&"?text="&_xlfn.ENCODEURL(M11))<=255,HYPERLINK("https://wa.me/91"&C11&"?text="&_xlfn.ENCODEURL(M11),"Open WhatsApp"),HYPERLINK("https://wa.me/91"&C11,"Open WhatsApp, paste column M"))) | J11: =IF(O11="","",HYPERLINK(INDEX(DESK!$AD$2:$AD$601,O11),INDEX(DESK!$B$2:$B$601,O11))) | K11: =IF(O11="","",IFERROR(HYPERLINK(INDEX(DESK!$AD$2:$AD$601,MATCH($C11&"|2",DESK!$AJ$2:$AJ$601,0)),INDEX(DESK!$B$2:$B$601,MATCH($C11&"|2",DESK!$AJ$2:$AJ$601,0))),"")) | L11: =IF(O11="","",IFERROR(HYPERLINK(INDEX(DESK!$AD$2:$AD$601,MATCH($C11&"|3",DESK!$AJ$2:$AJ$601,0)),INDEX(DESK!$B$2:$B$601,MATCH($C11&"|3",DESK!$AJ$2:$AJ$601,0))),"")) | M11: =IF(O11="","",SUBSTITUTE(SUBSTITUTE(SUBSTITUTE(SUBSTITUTE(INDEX(LISTS!$B$14:$B$19,MATCH(P11,LISTS!$A$14:$A$19,0))&IF(IF((INDEX(DESK!$AC$2:$AC$601,O11)="YES"),"",INDEX(DESK!$AD$2:$AD$601,O11))="",INDEX(LISTS!$B$14:$B$19,MATCH("YES",LISTS!$A$14:$A$19,0)),INDEX(LISTS!$B$14:$B$19,MATCH("NO",LISTS!$A$14:$A$19,0))),"{NAME}",INDEX(DESK!$AQ$2:$AQ$601,O11)),"{INTERN}",$B$2),"{COMPANY}",INDEX(DESK!$B$2:$B$601,O11)&IF(INDEX(DESK!$AA$2:$AA$601,O11)>1," and "&(INDEX(DESK!$AA$2:$AA$601,O11)-1)&" more","")),"{LINK}",IF((INDEX(DESK!$AC$2:$AC$601,O11)="YES"),"",INDEX(DESK!$AD$2:$AD$601,O11)))) | N11: =$B$2&"|"&A11 -> Shyam|5 | O11: =IFERROR(MATCH(N11,DESK!$AI$2:$AI$601,0),"") | P11: =IF(O11="","",IF((INDEX(DESK!$S$2:$S$601,O11)="SENT_LINK"),"CHK",IF(F11=1,"T1",IF(F11>=SETTINGS!$B$6,"T3","T2"))))
A12: 6 | B12: =IF(O12="","",INDEX(DESK!$D$2:$D$601,O12)) | C12: =IF(O12="","",INDEX(DESK!$F$2:$F$601,O12)) | D12: =IF(O12="","",INDEX(DESK!$AW$2:$AW$601,O12)&" "&INDEX(DESK!$B$2:$B$601,O12)&" "&INDEX(DESK!$G$2:$G$601,O12)&IFERROR("; "&INDEX(DESK!$AW$2:$AW$601,MATCH($C12&"|2",DESK!$AJ$2:$AJ$601,0))&" "&INDEX(DESK!$B$2:$B$601,MATCH($C12&"|2",DESK!$AJ$2:$AJ$601,0))&" "&INDEX(DESK!$G$2:$G$601,MATCH($C12&"|2",DESK!$AJ$2:$AJ$601,0)),"")&IFERROR("; "&INDEX(DESK!$AW$2:$AW$601,MATCH($C12&"|3",DESK!$AJ$2:$AJ$601,0))&" "&INDEX(DESK!$B$2:$B$601,MATCH($C12&"|3",DESK!$AJ$2:$AJ$601,0))&" "&INDEX(DESK!$G$2:$G$601,MATCH($C12&"|3",DESK!$AJ$2:$AJ$601,0)),"")) | E12: =IF(O12="","",ROUND(INDEX(DESK!$W$2:$W$601,O12),1)) | F12: =IF(O12="","",INDEX(DESK!$Q$2:$Q$601,O12)+1) | G12: =IF(O12="","",IF((INDEX(DESK!$AU$2:$AU$601,O12)=1),IF((INDEX(DESK!$AC$2:$AC$601,O12)="YES"),"REPLIED YES on WhatsApp. Open Calendar 1, book the first free slot, WhatsApp them the time, log BOOKED.","REPLIED YES on WhatsApp. Send the WhatsApp (it has the booking link), log SENT_LINK."),IF(F12>=SETTINGS!$B$6,"LAST TRY. ","")&IF((INDEX(DESK!$S$2:$S$601,O12)="SENT_LINK"),"Open Calendar 1. Already booked? Log SELF_BOOKED. Not booked? Call, send the WhatsApp, log what happened.",IF((INDEX(DESK!$AC$2:$AC$601,O12)="YES"),"Call. They say yes? Open Calendar 1, book the first time that suits them, log BOOKED. No answer? Send the WhatsApp, log NO_ANSWER.","Call. They say yes? Send the WhatsApp (it has the booking link), log SENT_LINK. No answer? Send the WhatsApp, log NO_ANSWER.")))&IF(INDEX(DESK!$AS$2:$AS$601,O12)="FAILED"," (Our WhatsApp did not deliver: call only.)","")) | H12: =IF(O12="","",HYPERLINK("tel:+91"&C12,"Call "&C12)) | I12: =IF(O12="","",IF(LEN("https://wa.me/91"&C12&"?text="&_xlfn.ENCODEURL(M12))<=255,HYPERLINK("https://wa.me/91"&C12&"?text="&_xlfn.ENCODEURL(M12),"Open WhatsApp"),HYPERLINK("https://wa.me/91"&C12,"Open WhatsApp, paste column M"))) | J12: =IF(O12="","",HYPERLINK(INDEX(DESK!$AD$2:$AD$601,O12),INDEX(DESK!$B$2:$B$601,O12))) | K12: =IF(O12="","",IFERROR(HYPERLINK(INDEX(DESK!$AD$2:$AD$601,MATCH($C12&"|2",DESK!$AJ$2:$AJ$601,0)),INDEX(DESK!$B$2:$B$601,MATCH($C12&"|2",DESK!$AJ$2:$AJ$601,0))),"")) | L12: =IF(O12="","",IFERROR(HYPERLINK(INDEX(DESK!$AD$2:$AD$601,MATCH($C12&"|3",DESK!$AJ$2:$AJ$601,0)),INDEX(DESK!$B$2:$B$601,MATCH($C12&"|3",DESK!$AJ$2:$AJ$601,0))),"")) | M12: =IF(O12="","",SUBSTITUTE(SUBSTITUTE(SUBSTITUTE(SUBSTITUTE(INDEX(LISTS!$B$14:$B$19,MATCH(P12,LISTS!$A$14:$A$19,0))&IF(IF((INDEX(DESK!$AC$2:$AC$601,O12)="YES"),"",INDEX(DESK!$AD$2:$AD$601,O12))="",INDEX(LISTS!$B$14:$B$19,MATCH("YES",LISTS!$A$14:$A$19,0)),INDEX(LISTS!$B$14:$B$19,MATCH("NO",LISTS!$A$14:$A$19,0))),"{NAME}",INDEX(DESK!$AQ$2:$AQ$601,O12)),"{INTERN}",$B$2),"{COMPANY}",INDEX(DESK!$B$2:$B$601,O12)&IF(INDEX(DESK!$AA$2:$AA$601,O12)>1," and "&(INDEX(DESK!$AA$2:$AA$601,O12)-1)&" more","")),"{LINK}",IF((INDEX(DESK!$AC$2:$AC$601,O12)="YES"),"",INDEX(DESK!$AD$2:$AD$601,O12)))) | N12: =$B$2&"|"&A12 -> Shyam|6 | O12: =IFERROR(MATCH(N12,DESK!$AI$2:$AI$601,0),"") | P12: =IF(O12="","",IF((INDEX(DESK!$S$2:$S$601,O12)="SENT_LINK"),"CHK",IF(F12=1,"T1",IF(F12>=SETTINGS!$B$6,"T3","T2"))))
A13: 7 | B13: =IF(O13="","",INDEX(DESK!$D$2:$D$601,O13)) | C13: =IF(O13="","",INDEX(DESK!$F$2:$F$601,O13)) | D13: =IF(O13="","",INDEX(DESK!$AW$2:$AW$601,O13)&" "&INDEX(DESK!$B$2:$B$601,O13)&" "&INDEX(DESK!$G$2:$G$601,O13)&IFERROR("; "&INDEX(DESK!$AW$2:$AW$601,MATCH($C13&"|2",DESK!$AJ$2:$AJ$601,0))&" "&INDEX(DESK!$B$2:$B$601,MATCH($C13&"|2",DESK!$AJ$2:$AJ$601,0))&" "&INDEX(DESK!$G$2:$G$601,MATCH($C13&"|2",DESK!$AJ$2:$AJ$601,0)),"")&IFERROR("; "&INDEX(DESK!$AW$2:$AW$601,MATCH($C13&"|3",DESK!$AJ$2:$AJ$601,0))&" "&INDEX(DESK!$B$2:$B$601,MATCH($C13&"|3",DESK!$AJ$2:$AJ$601,0))&" "&INDEX(DESK!$G$2:$G$601,MATCH($C13&"|3",DESK!$AJ$2:$AJ$601,0)),"")) | E13: =IF(O13="","",ROUND(INDEX(DESK!$W$2:$W$601,O13),1)) | F13: =IF(O13="","",INDEX(DESK!$Q$2:$Q$601,O13)+1) | G13: =IF(O13="","",IF((INDEX(DESK!$AU$2:$AU$601,O13)=1),IF((INDEX(DESK!$AC$2:$AC$601,O13)="YES"),"REPLIED YES on WhatsApp. Open Calendar 1, book the first free slot, WhatsApp them the time, log BOOKED.","REPLIED YES on WhatsApp. Send the WhatsApp (it has the booking link), log SENT_LINK."),IF(F13>=SETTINGS!$B$6,"LAST TRY. ","")&IF((INDEX(DESK!$S$2:$S$601,O13)="SENT_LINK"),"Open Calendar 1. Already booked? Log SELF_BOOKED. Not booked? Call, send the WhatsApp, log what happened.",IF((INDEX(DESK!$AC$2:$AC$601,O13)="YES"),"Call. They say yes? Open Calendar 1, book the first time that suits them, log BOOKED. No answer? Send the WhatsApp, log NO_ANSWER.","Call. They say yes? Send the WhatsApp (it has the booking link), log SENT_LINK. No answer? Send the WhatsApp, log NO_ANSWER.")))&IF(INDEX(DESK!$AS$2:$AS$601,O13)="FAILED"," (Our WhatsApp did not deliver: call only.)","")) | H13: =IF(O13="","",HYPERLINK("tel:+91"&C13,"Call "&C13)) | I13: =IF(O13="","",IF(LEN("https://wa.me/91"&C13&"?text="&_xlfn.ENCODEURL(M13))<=255,HYPERLINK("https://wa.me/91"&C13&"?text="&_xlfn.ENCODEURL(M13),"Open WhatsApp"),HYPERLINK("https://wa.me/91"&C13,"Open WhatsApp, paste column M"))) | J13: =IF(O13="","",HYPERLINK(INDEX(DESK!$AD$2:$AD$601,O13),INDEX(DESK!$B$2:$B$601,O13))) | K13: =IF(O13="","",IFERROR(HYPERLINK(INDEX(DESK!$AD$2:$AD$601,MATCH($C13&"|2",DESK!$AJ$2:$AJ$601,0)),INDEX(DESK!$B$2:$B$601,MATCH($C13&"|2",DESK!$AJ$2:$AJ$601,0))),"")) | L13: =IF(O13="","",IFERROR(HYPERLINK(INDEX(DESK!$AD$2:$AD$601,MATCH($C13&"|3",DESK!$AJ$2:$AJ$601,0)),INDEX(DESK!$B$2:$B$601,MATCH($C13&"|3",DESK!$AJ$2:$AJ$601,0))),"")) | M13: =IF(O13="","",SUBSTITUTE(SUBSTITUTE(SUBSTITUTE(SUBSTITUTE(INDEX(LISTS!$B$14:$B$19,MATCH(P13,LISTS!$A$14:$A$19,0))&IF(IF((INDEX(DESK!$AC$2:$AC$601,O13)="YES"),"",INDEX(DESK!$AD$2:$AD$601,O13))="",INDEX(LISTS!$B$14:$B$19,MATCH("YES",LISTS!$A$14:$A$19,0)),INDEX(LISTS!$B$14:$B$19,MATCH("NO",LISTS!$A$14:$A$19,0))),"{NAME}",INDEX(DESK!$AQ$2:$AQ$601,O13)),"{INTERN}",$B$2),"{COMPANY}",INDEX(DESK!$B$2:$B$601,O13)&IF(INDEX(DESK!$AA$2:$AA$601,O13)>1," and "&(INDEX(DESK!$AA$2:$AA$601,O13)-1)&" more","")),"{LINK}",IF((INDEX(DESK!$AC$2:$AC$601,O13)="YES"),"",INDEX(DESK!$AD$2:$AD$601,O13)))) | N13: =$B$2&"|"&A13 -> Shyam|7 | O13: =IFERROR(MATCH(N13,DESK!$AI$2:$AI$601,0),"") | P13: =IF(O13="","",IF((INDEX(DESK!$S$2:$S$601,O13)="SENT_LINK"),"CHK",IF(F13=1,"T1",IF(F13>=SETTINGS!$B$6,"T3","T2"))))
A14: 8 | B14: =IF(O14="","",INDEX(DESK!$D$2:$D$601,O14)) | C14: =IF(O14="","",INDEX(DESK!$F$2:$F$601,O14)) | D14: =IF(O14="","",INDEX(DESK!$AW$2:$AW$601,O14)&" "&INDEX(DESK!$B$2:$B$601,O14)&" "&INDEX(DESK!$G$2:$G$601,O14)&IFERROR("; "&INDEX(DESK!$AW$2:$AW$601,MATCH($C14&"|2",DESK!$AJ$2:$AJ$601,0))&" "&INDEX(DESK!$B$2:$B$601,MATCH($C14&"|2",DESK!$AJ$2:$AJ$601,0))&" "&INDEX(DESK!$G$2:$G$601,MATCH($C14&"|2",DESK!$AJ$2:$AJ$601,0)),"")&IFERROR("; "&INDEX(DESK!$AW$2:$AW$601,MATCH($C14&"|3",DESK!$AJ$2:$AJ$601,0))&" "&INDEX(DESK!$B$2:$B$601,MATCH($C14&"|3",DESK!$AJ$2:$AJ$601,0))&" "&INDEX(DESK!$G$2:$G$601,MATCH($C14&"|3",DESK!$AJ$2:$AJ$601,0)),"")) | E14: =IF(O14="","",ROUND(INDEX(DESK!$W$2:$W$601,O14),1)) | F14: =IF(O14="","",INDEX(DESK!$Q$2:$Q$601,O14)+1) | G14: =IF(O14="","",IF((INDEX(DESK!$AU$2:$AU$601,O14)=1),IF((INDEX(DESK!$AC$2:$AC$601,O14)="YES"),"REPLIED YES on WhatsApp. Open Calendar 1, book the first free slot, WhatsApp them the time, log BOOKED.","REPLIED YES on WhatsApp. Send the WhatsApp (it has the booking link), log SENT_LINK."),IF(F14>=SETTINGS!$B$6,"LAST TRY. ","")&IF((INDEX(DESK!$S$2:$S$601,O14)="SENT_LINK"),"Open Calendar 1. Already booked? Log SELF_BOOKED. Not booked? Call, send the WhatsApp, log what happened.",IF((INDEX(DESK!$AC$2:$AC$601,O14)="YES"),"Call. They say yes? Open Calendar 1, book the first time that suits them, log BOOKED. No answer? Send the WhatsApp, log NO_ANSWER.","Call. They say yes? Send the WhatsApp (it has the booking link), log SENT_LINK. No answer? Send the WhatsApp, log NO_ANSWER.")))&IF(INDEX(DESK!$AS$2:$AS$601,O14)="FAILED"," (Our WhatsApp did not deliver: call only.)","")) | H14: =IF(O14="","",HYPERLINK("tel:+91"&C14,"Call "&C14)) | I14: =IF(O14="","",IF(LEN("https://wa.me/91"&C14&"?text="&_xlfn.ENCODEURL(M14))<=255,HYPERLINK("https://wa.me/91"&C14&"?text="&_xlfn.ENCODEURL(M14),"Open WhatsApp"),HYPERLINK("https://wa.me/91"&C14,"Open WhatsApp, paste column M"))) | J14: =IF(O14="","",HYPERLINK(INDEX(DESK!$AD$2:$AD$601,O14),INDEX(DESK!$B$2:$B$601,O14))) | K14: =IF(O14="","",IFERROR(HYPERLINK(INDEX(DESK!$AD$2:$AD$601,MATCH($C14&"|2",DESK!$AJ$2:$AJ$601,0)),INDEX(DESK!$B$2:$B$601,MATCH($C14&"|2",DESK!$AJ$2:$AJ$601,0))),"")) | L14: =IF(O14="","",IFERROR(HYPERLINK(INDEX(DESK!$AD$2:$AD$601,MATCH($C14&"|3",DESK!$AJ$2:$AJ$601,0)),INDEX(DESK!$B$2:$B$601,MATCH($C14&"|3",DESK!$AJ$2:$AJ$601,0))),"")) | M14: =IF(O14="","",SUBSTITUTE(SUBSTITUTE(SUBSTITUTE(SUBSTITUTE(INDEX(LISTS!$B$14:$B$19,MATCH(P14,LISTS!$A$14:$A$19,0))&IF(IF((INDEX(DESK!$AC$2:$AC$601,O14)="YES"),"",INDEX(DESK!$AD$2:$AD$601,O14))="",INDEX(LISTS!$B$14:$B$19,MATCH("YES",LISTS!$A$14:$A$19,0)),INDEX(LISTS!$B$14:$B$19,MATCH("NO",LISTS!$A$14:$A$19,0))),"{NAME}",INDEX(DESK!$AQ$2:$AQ$601,O14)),"{INTERN}",$B$2),"{COMPANY}",INDEX(DESK!$B$2:$B$601,O14)&IF(INDEX(DESK!$AA$2:$AA$601,O14)>1," and "&(INDEX(DESK!$AA$2:$AA$601,O14)-1)&" more","")),"{LINK}",IF((INDEX(DESK!$AC$2:$AC$601,O14)="YES"),"",INDEX(DESK!$AD$2:$AD$601,O14)))) | N14: =$B$2&"|"&A14 -> Shyam|8 | O14: =IFERROR(MATCH(N14,DESK!$AI$2:$AI$601,0),"") | P14: =IF(O14="","",IF((INDEX(DESK!$S$2:$S$601,O14)="SENT_LINK"),"CHK",IF(F14=1,"T1",IF(F14>=SETTINGS!$B$6,"T3","T2"))))
A15: 9 | B15: =IF(O15="","",INDEX(DESK!$D$2:$D$601,O15)) | C15: =IF(O15="","",INDEX(DESK!$F$2:$F$601,O15)) | D15: =IF(O15="","",INDEX(DESK!$AW$2:$AW$601,O15)&" "&INDEX(DESK!$B$2:$B$601,O15)&" "&INDEX(DESK!$G$2:$G$601,O15)&IFERROR("; "&INDEX(DESK!$AW$2:$AW$601,MATCH($C15&"|2",DESK!$AJ$2:$AJ$601,0))&" "&INDEX(DESK!$B$2:$B$601,MATCH($C15&"|2",DESK!$AJ$2:$AJ$601,0))&" "&INDEX(DESK!$G$2:$G$601,MATCH($C15&"|2",DESK!$AJ$2:$AJ$601,0)),"")&IFERROR("; "&INDEX(DESK!$AW$2:$AW$601,MATCH($C15&"|3",DESK!$AJ$2:$AJ$601,0))&" "&INDEX(DESK!$B$2:$B$601,MATCH($C15&"|3",DESK!$AJ$2:$AJ$601,0))&" "&INDEX(DESK!$G$2:$G$601,MATCH($C15&"|3",DESK!$AJ$2:$AJ$601,0)),"")) | E15: =IF(O15="","",ROUND(INDEX(DESK!$W$2:$W$601,O15),1)) | F15: =IF(O15="","",INDEX(DESK!$Q$2:$Q$601,O15)+1) | G15: =IF(O15="","",IF((INDEX(DESK!$AU$2:$AU$601,O15)=1),IF((INDEX(DESK!$AC$2:$AC$601,O15)="YES"),"REPLIED YES on WhatsApp. Open Calendar 1, book the first free slot, WhatsApp them the time, log BOOKED.","REPLIED YES on WhatsApp. Send the WhatsApp (it has the booking link), log SENT_LINK."),IF(F15>=SETTINGS!$B$6,"LAST TRY. ","")&IF((INDEX(DESK!$S$2:$S$601,O15)="SENT_LINK"),"Open Calendar 1. Already booked? Log SELF_BOOKED. Not booked? Call, send the WhatsApp, log what happened.",IF((INDEX(DESK!$AC$2:$AC$601,O15)="YES"),"Call. They say yes? Open Calendar 1, book the first time that suits them, log BOOKED. No answer? Send the WhatsApp, log NO_ANSWER.","Call. They say yes? Send the WhatsApp (it has the booking link), log SENT_LINK. No answer? Send the WhatsApp, log NO_ANSWER.")))&IF(INDEX(DESK!$AS$2:$AS$601,O15)="FAILED"," (Our WhatsApp did not deliver: call only.)","")) | H15: =IF(O15="","",HYPERLINK("tel:+91"&C15,"Call "&C15)) | I15: =IF(O15="","",IF(LEN("https://wa.me/91"&C15&"?text="&_xlfn.ENCODEURL(M15))<=255,HYPERLINK("https://wa.me/91"&C15&"?text="&_xlfn.ENCODEURL(M15),"Open WhatsApp"),HYPERLINK("https://wa.me/91"&C15,"Open WhatsApp, paste column M"))) | J15: =IF(O15="","",HYPERLINK(INDEX(DESK!$AD$2:$AD$601,O15),INDEX(DESK!$B$2:$B$601,O15))) | K15: =IF(O15="","",IFERROR(HYPERLINK(INDEX(DESK!$AD$2:$AD$601,MATCH($C15&"|2",DESK!$AJ$2:$AJ$601,0)),INDEX(DESK!$B$2:$B$601,MATCH($C15&"|2",DESK!$AJ$2:$AJ$601,0))),"")) | L15: =IF(O15="","",IFERROR(HYPERLINK(INDEX(DESK!$AD$2:$AD$601,MATCH($C15&"|3",DESK!$AJ$2:$AJ$601,0)),INDEX(DESK!$B$2:$B$601,MATCH($C15&"|3",DESK!$AJ$2:$AJ$601,0))),"")) | M15: =IF(O15="","",SUBSTITUTE(SUBSTITUTE(SUBSTITUTE(SUBSTITUTE(INDEX(LISTS!$B$14:$B$19,MATCH(P15,LISTS!$A$14:$A$19,0))&IF(IF((INDEX(DESK!$AC$2:$AC$601,O15)="YES"),"",INDEX(DESK!$AD$2:$AD$601,O15))="",INDEX(LISTS!$B$14:$B$19,MATCH("YES",LISTS!$A$14:$A$19,0)),INDEX(LISTS!$B$14:$B$19,MATCH("NO",LISTS!$A$14:$A$19,0))),"{NAME}",INDEX(DESK!$AQ$2:$AQ$601,O15)),"{INTERN}",$B$2),"{COMPANY}",INDEX(DESK!$B$2:$B$601,O15)&IF(INDEX(DESK!$AA$2:$AA$601,O15)>1," and "&(INDEX(DESK!$AA$2:$AA$601,O15)-1)&" more","")),"{LINK}",IF((INDEX(DESK!$AC$2:$AC$601,O15)="YES"),"",INDEX(DESK!$AD$2:$AD$601,O15)))) | N15: =$B$2&"|"&A15 -> Shyam|9 | O15: =IFERROR(MATCH(N15,DESK!$AI$2:$AI$601,0),"") | P15: =IF(O15="","",IF((INDEX(DESK!$S$2:$S$601,O15)="SENT_LINK"),"CHK",IF(F15=1,"T1",IF(F15>=SETTINGS!$B$6,"T3","T2"))))
A16: 10 | B16: =IF(O16="","",INDEX(DESK!$D$2:$D$601,O16)) | C16: =IF(O16="","",INDEX(DESK!$F$2:$F$601,O16)) | D16: =IF(O16="","",INDEX(DESK!$AW$2:$AW$601,O16)&" "&INDEX(DESK!$B$2:$B$601,O16)&" "&INDEX(DESK!$G$2:$G$601,O16)&IFERROR("; "&INDEX(DESK!$AW$2:$AW$601,MATCH($C16&"|2",DESK!$AJ$2:$AJ$601,0))&" "&INDEX(DESK!$B$2:$B$601,MATCH($C16&"|2",DESK!$AJ$2:$AJ$601,0))&" "&INDEX(DESK!$G$2:$G$601,MATCH($C16&"|2",DESK!$AJ$2:$AJ$601,0)),"")&IFERROR("; "&INDEX(DESK!$AW$2:$AW$601,MATCH($C16&"|3",DESK!$AJ$2:$AJ$601,0))&" "&INDEX(DESK!$B$2:$B$601,MATCH($C16&"|3",DESK!$AJ$2:$AJ$601,0))&" "&INDEX(DESK!$G$2:$G$601,MATCH($C16&"|3",DESK!$AJ$2:$AJ$601,0)),"")) | E16: =IF(O16="","",ROUND(INDEX(DESK!$W$2:$W$601,O16),1)) | F16: =IF(O16="","",INDEX(DESK!$Q$2:$Q$601,O16)+1) | G16: =IF(O16="","",IF((INDEX(DESK!$AU$2:$AU$601,O16)=1),IF((INDEX(DESK!$AC$2:$AC$601,O16)="YES"),"REPLIED YES on WhatsApp. Open Calendar 1, book the first free slot, WhatsApp them the time, log BOOKED.","REPLIED YES on WhatsApp. Send the WhatsApp (it has the booking link), log SENT_LINK."),IF(F16>=SETTINGS!$B$6,"LAST TRY. ","")&IF((INDEX(DESK!$S$2:$S$601,O16)="SENT_LINK"),"Open Calendar 1. Already booked? Log SELF_BOOKED. Not booked? Call, send the WhatsApp, log what happened.",IF((INDEX(DESK!$AC$2:$AC$601,O16)="YES"),"Call. They say yes? Open Calendar 1, book the first time that suits them, log BOOKED. No answer? Send the WhatsApp, log NO_ANSWER.","Call. They say yes? Send the WhatsApp (it has the booking link), log SENT_LINK. No answer? Send the WhatsApp, log NO_ANSWER.")))&IF(INDEX(DESK!$AS$2:$AS$601,O16)="FAILED"," (Our WhatsApp did not deliver: call only.)","")) | H16: =IF(O16="","",HYPERLINK("tel:+91"&C16,"Call "&C16)) | I16: =IF(O16="","",IF(LEN("https://wa.me/91"&C16&"?text="&_xlfn.ENCODEURL(M16))<=255,HYPERLINK("https://wa.me/91"&C16&"?text="&_xlfn.ENCODEURL(M16),"Open WhatsApp"),HYPERLINK("https://wa.me/91"&C16,"Open WhatsApp, paste column M"))) | J16: =IF(O16="","",HYPERLINK(INDEX(DESK!$AD$2:$AD$601,O16),INDEX(DESK!$B$2:$B$601,O16))) | K16: =IF(O16="","",IFERROR(HYPERLINK(INDEX(DESK!$AD$2:$AD$601,MATCH($C16&"|2",DESK!$AJ$2:$AJ$601,0)),INDEX(DESK!$B$2:$B$601,MATCH($C16&"|2",DESK!$AJ$2:$AJ$601,0))),"")) | L16: =IF(O16="","",IFERROR(HYPERLINK(INDEX(DESK!$AD$2:$AD$601,MATCH($C16&"|3",DESK!$AJ$2:$AJ$601,0)),INDEX(DESK!$B$2:$B$601,MATCH($C16&"|3",DESK!$AJ$2:$AJ$601,0))),"")) | M16: =IF(O16="","",SUBSTITUTE(SUBSTITUTE(SUBSTITUTE(SUBSTITUTE(INDEX(LISTS!$B$14:$B$19,MATCH(P16,LISTS!$A$14:$A$19,0))&IF(IF((INDEX(DESK!$AC$2:$AC$601,O16)="YES"),"",INDEX(DESK!$AD$2:$AD$601,O16))="",INDEX(LISTS!$B$14:$B$19,MATCH("YES",LISTS!$A$14:$A$19,0)),INDEX(LISTS!$B$14:$B$19,MATCH("NO",LISTS!$A$14:$A$19,0))),"{NAME}",INDEX(DESK!$AQ$2:$AQ$601,O16)),"{INTERN}",$B$2),"{COMPANY}",INDEX(DESK!$B$2:$B$601,O16)&IF(INDEX(DESK!$AA$2:$AA$601,O16)>1," and "&(INDEX(DESK!$AA$2:$AA$601,O16)-1)&" more","")),"{LINK}",IF((INDEX(DESK!$AC$2:$AC$601,O16)="YES"),"",INDEX(DESK!$AD$2:$AD$601,O16)))) | N16: =$B$2&"|"&A16 -> Shyam|10 | O16: =IFERROR(MATCH(N16,DESK!$AI$2:$AI$601,0),"") | P16: =IF(O16="","",IF((INDEX(DESK!$S$2:$S$601,O16)="SENT_LINK"),"CHK",IF(F16=1,"T1",IF(F16>=SETTINGS!$B$6,"T3","T2"))))
A17: 11 | B17: =IF(O17="","",INDEX(DESK!$D$2:$D$601,O17)) | C17: =IF(O17="","",INDEX(DESK!$F$2:$F$601,O17)) | D17: =IF(O17="","",INDEX(DESK!$AW$2:$AW$601,O17)&" "&INDEX(DESK!$B$2:$B$601,O17)&" "&INDEX(DESK!$G$2:$G$601,O17)&IFERROR("; "&INDEX(DESK!$AW$2:$AW$601,MATCH($C17&"|2",DESK!$AJ$2:$AJ$601,0))&" "&INDEX(DESK!$B$2:$B$601,MATCH($C17&"|2",DESK!$AJ$2:$AJ$601,0))&" "&INDEX(DESK!$G$2:$G$601,MATCH($C17&"|2",DESK!$AJ$2:$AJ$601,0)),"")&IFERROR("; "&INDEX(DESK!$AW$2:$AW$601,MATCH($C17&"|3",DESK!$AJ$2:$AJ$601,0))&" "&INDEX(DESK!$B$2:$B$601,MATCH($C17&"|3",DESK!$AJ$2:$AJ$601,0))&" "&INDEX(DESK!$G$2:$G$601,MATCH($C17&"|3",DESK!$AJ$2:$AJ$601,0)),"")) | E17: =IF(O17="","",ROUND(INDEX(DESK!$W$2:$W$601,O17),1)) | F17: =IF(O17="","",INDEX(DESK!$Q$2:$Q$601,O17)+1) | G17: =IF(O17="","",IF((INDEX(DESK!$AU$2:$AU$601,O17)=1),IF((INDEX(DESK!$AC$2:$AC$601,O17)="YES"),"REPLIED YES on WhatsApp. Open Calendar 1, book the first free slot, WhatsApp them the time, log BOOKED.","REPLIED YES on WhatsApp. Send the WhatsApp (it has the booking link), log SENT_LINK."),IF(F17>=SETTINGS!$B$6,"LAST TRY. ","")&IF((INDEX(DESK!$S$2:$S$601,O17)="SENT_LINK"),"Open Calendar 1. Already booked? Log SELF_BOOKED. Not booked? Call, send the WhatsApp, log what happened.",IF((INDEX(DESK!$AC$2:$AC$601,O17)="YES"),"Call. They say yes? Open Calendar 1, book the first time that suits them, log BOOKED. No answer? Send the WhatsApp, log NO_ANSWER.","Call. They say yes? Send the WhatsApp (it has the booking link), log SENT_LINK. No answer? Send the WhatsApp, log NO_ANSWER.")))&IF(INDEX(DESK!$AS$2:$AS$601,O17)="FAILED"," (Our WhatsApp did not deliver: call only.)","")) | H17: =IF(O17="","",HYPERLINK("tel:+91"&C17,"Call "&C17)) | I17: =IF(O17="","",IF(LEN("https://wa.me/91"&C17&"?text="&_xlfn.ENCODEURL(M17))<=255,HYPERLINK("https://wa.me/91"&C17&"?text="&_xlfn.ENCODEURL(M17),"Open WhatsApp"),HYPERLINK("https://wa.me/91"&C17,"Open WhatsApp, paste column M"))) | J17: =IF(O17="","",HYPERLINK(INDEX(DESK!$AD$2:$AD$601,O17),INDEX(DESK!$B$2:$B$601,O17))) | K17: =IF(O17="","",IFERROR(HYPERLINK(INDEX(DESK!$AD$2:$AD$601,MATCH($C17&"|2",DESK!$AJ$2:$AJ$601,0)),INDEX(DESK!$B$2:$B$601,MATCH($C17&"|2",DESK!$AJ$2:$AJ$601,0))),"")) | L17: =IF(O17="","",IFERROR(HYPERLINK(INDEX(DESK!$AD$2:$AD$601,MATCH($C17&"|3",DESK!$AJ$2:$AJ$601,0)),INDEX(DESK!$B$2:$B$601,MATCH($C17&"|3",DESK!$AJ$2:$AJ$601,0))),"")) | M17: =IF(O17="","",SUBSTITUTE(SUBSTITUTE(SUBSTITUTE(SUBSTITUTE(INDEX(LISTS!$B$14:$B$19,MATCH(P17,LISTS!$A$14:$A$19,0))&IF(IF((INDEX(DESK!$AC$2:$AC$601,O17)="YES"),"",INDEX(DESK!$AD$2:$AD$601,O17))="",INDEX(LISTS!$B$14:$B$19,MATCH("YES",LISTS!$A$14:$A$19,0)),INDEX(LISTS!$B$14:$B$19,MATCH("NO",LISTS!$A$14:$A$19,0))),"{NAME}",INDEX(DESK!$AQ$2:$AQ$601,O17)),"{INTERN}",$B$2),"{COMPANY}",INDEX(DESK!$B$2:$B$601,O17)&IF(INDEX(DESK!$AA$2:$AA$601,O17)>1," and "&(INDEX(DESK!$AA$2:$AA$601,O17)-1)&" more","")),"{LINK}",IF((INDEX(DESK!$AC$2:$AC$601,O17)="YES"),"",INDEX(DESK!$AD$2:$AD$601,O17)))) | N17: =$B$2&"|"&A17 -> Shyam|11 | O17: =IFERROR(MATCH(N17,DESK!$AI$2:$AI$601,0),"") | P17: =IF(O17="","",IF((INDEX(DESK!$S$2:$S$601,O17)="SENT_LINK"),"CHK",IF(F17=1,"T1",IF(F17>=SETTINGS!$B$6,"T3","T2"))))
A18: 12 | B18: =IF(O18="","",INDEX(DESK!$D$2:$D$601,O18)) | C18: =IF(O18="","",INDEX(DESK!$F$2:$F$601,O18)) | D18: =IF(O18="","",INDEX(DESK!$AW$2:$AW$601,O18)&" "&INDEX(DESK!$B$2:$B$601,O18)&" "&INDEX(DESK!$G$2:$G$601,O18)&IFERROR("; "&INDEX(DESK!$AW$2:$AW$601,MATCH($C18&"|2",DESK!$AJ$2:$AJ$601,0))&" "&INDEX(DESK!$B$2:$B$601,MATCH($C18&"|2",DESK!$AJ$2:$AJ$601,0))&" "&INDEX(DESK!$G$2:$G$601,MATCH($C18&"|2",DESK!$AJ$2:$AJ$601,0)),"")&IFERROR("; "&INDEX(DESK!$AW$2:$AW$601,MATCH($C18&"|3",DESK!$AJ$2:$AJ$601,0))&" "&INDEX(DESK!$B$2:$B$601,MATCH($C18&"|3",DESK!$AJ$2:$AJ$601,0))&" "&INDEX(DESK!$G$2:$G$601,MATCH($C18&"|3",DESK!$AJ$2:$AJ$601,0)),"")) | E18: =IF(O18="","",ROUND(INDEX(DESK!$W$2:$W$601,O18),1)) | F18: =IF(O18="","",INDEX(DESK!$Q$2:$Q$601,O18)+1) | G18: =IF(O18="","",IF((INDEX(DESK!$AU$2:$AU$601,O18)=1),IF((INDEX(DESK!$AC$2:$AC$601,O18)="YES"),"REPLIED YES on WhatsApp. Open Calendar 1, book the first free slot, WhatsApp them the time, log BOOKED.","REPLIED YES on WhatsApp. Send the WhatsApp (it has the booking link), log SENT_LINK."),IF(F18>=SETTINGS!$B$6,"LAST TRY. ","")&IF((INDEX(DESK!$S$2:$S$601,O18)="SENT_LINK"),"Open Calendar 1. Already booked? Log SELF_BOOKED. Not booked? Call, send the WhatsApp, log what happened.",IF((INDEX(DESK!$AC$2:$AC$601,O18)="YES"),"Call. They say yes? Open Calendar 1, book the first time that suits them, log BOOKED. No answer? Send the WhatsApp, log NO_ANSWER.","Call. They say yes? Send the WhatsApp (it has the booking link), log SENT_LINK. No answer? Send the WhatsApp, log NO_ANSWER.")))&IF(INDEX(DESK!$AS$2:$AS$601,O18)="FAILED"," (Our WhatsApp did not deliver: call only.)","")) | H18: =IF(O18="","",HYPERLINK("tel:+91"&C18,"Call "&C18)) | I18: =IF(O18="","",IF(LEN("https://wa.me/91"&C18&"?text="&_xlfn.ENCODEURL(M18))<=255,HYPERLINK("https://wa.me/91"&C18&"?text="&_xlfn.ENCODEURL(M18),"Open WhatsApp"),HYPERLINK("https://wa.me/91"&C18,"Open WhatsApp, paste column M"))) | J18: =IF(O18="","",HYPERLINK(INDEX(DESK!$AD$2:$AD$601,O18),INDEX(DESK!$B$2:$B$601,O18))) | K18: =IF(O18="","",IFERROR(HYPERLINK(INDEX(DESK!$AD$2:$AD$601,MATCH($C18&"|2",DESK!$AJ$2:$AJ$601,0)),INDEX(DESK!$B$2:$B$601,MATCH($C18&"|2",DESK!$AJ$2:$AJ$601,0))),"")) | L18: =IF(O18="","",IFERROR(HYPERLINK(INDEX(DESK!$AD$2:$AD$601,MATCH($C18&"|3",DESK!$AJ$2:$AJ$601,0)),INDEX(DESK!$B$2:$B$601,MATCH($C18&"|3",DESK!$AJ$2:$AJ$601,0))),"")) | M18: =IF(O18="","",SUBSTITUTE(SUBSTITUTE(SUBSTITUTE(SUBSTITUTE(INDEX(LISTS!$B$14:$B$19,MATCH(P18,LISTS!$A$14:$A$19,0))&IF(IF((INDEX(DESK!$AC$2:$AC$601,O18)="YES"),"",INDEX(DESK!$AD$2:$AD$601,O18))="",INDEX(LISTS!$B$14:$B$19,MATCH("YES",LISTS!$A$14:$A$19,0)),INDEX(LISTS!$B$14:$B$19,MATCH("NO",LISTS!$A$14:$A$19,0))),"{NAME}",INDEX(DESK!$AQ$2:$AQ$601,O18)),"{INTERN}",$B$2),"{COMPANY}",INDEX(DESK!$B$2:$B$601,O18)&IF(INDEX(DESK!$AA$2:$AA$601,O18)>1," and "&(INDEX(DESK!$AA$2:$AA$601,O18)-1)&" more","")),"{LINK}",IF((INDEX(DESK!$AC$2:$AC$601,O18)="YES"),"",INDEX(DESK!$AD$2:$AD$601,O18)))) | N18: =$B$2&"|"&A18 -> Shyam|12 | O18: =IFERROR(MATCH(N18,DESK!$AI$2:$AI$601,0),"") | P18: =IF(O18="","",IF((INDEX(DESK!$S$2:$S$601,O18)="SENT_LINK"),"CHK",IF(F18=1,"T1",IF(F18>=SETTINGS!$B$6,"T3","T2"))))
... A31: 25 | B31: =IF(O31="","",INDEX(DESK!$D$2:$D$601,O31)) | C31: =IF(O31="","",INDEX(DESK!$F$2:$F$601,O31)) | D31: =IF(O31="","",INDEX(DESK!$AW$2:$AW$601,O31)&" "&INDEX(DESK!$B$2:$B$601,O31)&" "&INDEX(DESK!$G$2:$G$601,O31)&IFERROR("; "&INDEX(DESK!$AW$2:$AW$601,MATCH($C31&"|2",DESK!$AJ$2:$AJ$601,0))&" "&INDEX(DESK!$B$2:$B$601,MATCH($C31&"|2",DESK!$AJ$2:$AJ$601,0))&" "&INDEX(DESK!$G$2:$G$601,MATCH($C31&"|2",DESK!$AJ$2:$AJ$601,0)),"")&IFERROR("; "&INDEX(DESK!$AW$2:$AW$601,MATCH($C31&"|3",DESK!$AJ$2:$AJ$601,0))&" "&INDEX(DESK!$B$2:$B$601,MATCH($C31&"|3",DESK!$AJ$2:$AJ$601,0))&" "&INDEX(DESK!$G$2:$G$601,MATCH($C31&"|3",DESK!$AJ$2:$AJ$601,0)),"")) | E31: =IF(O31="","",ROUND(INDEX(DESK!$W$2:$W$601,O31),1)) | F31: =IF(O31="","",INDEX(DESK!$Q$2:$Q$601,O31)+1) | G31: =IF(O31="","",IF((INDEX(DESK!$AU$2:$AU$601,O31)=1),IF((INDEX(DESK!$AC$2:$AC$601,O31)="YES"),"REPLIED YES on WhatsApp. Open Calendar 1, book the first free slot, WhatsApp them the time, log BOOKED.","REPLIED YES on WhatsApp. Send the WhatsApp (it has the booking link), log SENT_LINK."),IF(F31>=SETTINGS!$B$6,"LAST TRY. ","")&IF((INDEX(DESK!$S$2:$S$601,O31)="SENT_LINK"),"Open Calendar 1. Already booked? Log SELF_BOOKED. Not booked? Call, send the WhatsApp, log what happened.",IF((INDEX(DESK!$AC$2:$AC$601,O31)="YES"),"Call. They say yes? Open Calendar 1, book the first time that suits them, log BOOKED. No answer? Send the WhatsApp, log NO_ANSWER.","Call. They say yes? Send the WhatsApp (it has the booking link), log SENT_LINK. No answer? Send the WhatsApp, log NO_ANSWER.")))&IF(INDEX(DESK!$AS$2:$AS$601,O31)="FAILED"," (Our WhatsApp did not deliver: call only.)","")) | H31: =IF(O31="","",HYPERLINK("tel:+91"&C31,"Call "&C31)) | I31: =IF(O31="","",IF(LEN("https://wa.me/91"&C31&"?text="&_xlfn.ENCODEURL(M31))<=255,HYPERLINK("https://wa.me/91"&C31&"?text="&_xlfn.ENCODEURL(M31),"Open WhatsApp"),HYPERLINK("https://wa.me/91"&C31,"Open WhatsApp, paste column M"))) | J31: =IF(O31="","",HYPERLINK(INDEX(DESK!$AD$2:$AD$601,O31),INDEX(DESK!$B$2:$B$601,O31))) | K31: =IF(O31="","",IFERROR(HYPERLINK(INDEX(DESK!$AD$2:$AD$601,MATCH($C31&"|2",DESK!$AJ$2:$AJ$601,0)),INDEX(DESK!$B$2:$B$601,MATCH($C31&"|2",DESK!$AJ$2:$AJ$601,0))),"")) | L31: =IF(O31="","",IFERROR(HYPERLINK(INDEX(DESK!$AD$2:$AD$601,MATCH($C31&"|3",DESK!$AJ$2:$AJ$601,0)),INDEX(DESK!$B$2:$B$601,MATCH($C31&"|3",DESK!$AJ$2:$AJ$601,0))),"")) | M31: =IF(O31="","",SUBSTITUTE(SUBSTITUTE(SUBSTITUTE(SUBSTITUTE(INDEX(LISTS!$B$14:$B$19,MATCH(P31,LISTS!$A$14:$A$19,0))&IF(IF((INDEX(DESK!$AC$2:$AC$601,O31)="YES"),"",INDEX(DESK!$AD$2:$AD$601,O31))="",INDEX(LISTS!$B$14:$B$19,MATCH("YES",LISTS!$A$14:$A$19,0)),INDEX(LISTS!$B$14:$B$19,MATCH("NO",LISTS!$A$14:$A$19,0))),"{NAME}",INDEX(DESK!$AQ$2:$AQ$601,O31)),"{INTERN}",$B$2),"{COMPANY}",INDEX(DESK!$B$2:$B$601,O31)&IF(INDEX(DESK!$AA$2:$AA$601,O31)>1," and "&(INDEX(DESK!$AA$2:$AA$601,O31)-1)&" more","")),"{LINK}",IF((INDEX(DESK!$AC$2:$AC$601,O31)="YES"),"",INDEX(DESK!$AD$2:$AD$601,O31)))) | N31: =$B$2&"|"&A31 -> Shyam|25 | O31: =IFERROR(MATCH(N31,DESK!$AI$2:$AI$601,0),"") | P31: =IF(O31="","",IF((INDEX(DESK!$S$2:$S$601,O31)="SENT_LINK"),"CHK",IF(F31=1,"T1",IF(F31>=SETTINGS!$B$6,"T3","T2"))))

Sheet LOG
A1: Time (Ctrl+Shift+;) | B1: Who | C1: Phone (copy from your list) | D1: Outcome | E1: Request ID (blank = all their open requests) | F1: Notes | G1: time used (auto) | H1: try? (auto) | I1: try key (auto) | J1: Check (auto) | K1: company (auto) | L1: conversation no. (auto) | M1: try ended in a confirmed booking? (auto)
A2: 46308.844 | B2: Lead | C2: 9000002230 | D2: SELF_BOOKED | E2: R361 | F2: calendly confirmation | G2: =IF(A2="","",IF(A2>=1,A2,INT(SETTINGS!$B$4)+A2)) -> 46308.844 | H2: =IF(D2="","",IFERROR(VLOOKUP(D2,LISTS!$A$2:$E$10,3,FALSE),0)) -> 0 | I2: =IF(H2=1,C2&"|"&COUNTIFS($C$2:C2,C2,$H$2:H2,1),"") | J2: =IF(D2="","",IF(A2="","Missing time",IF(AND(D2="NO_SLOTS",E2=""),"Write the request ID in column E",IF(C2="","Missing phone",IF(COUNTIF(DESK!$F$2:$F$601,C2)=0,"Phone not found: copy it from your list",IF(E2="","OK",IF(COUNTIFS(DESK!$F$2:$F$601,C2,DESK!$AW$2:$AW$601,E2)=0,"Request ID is not one of theirs: copy it from column D",IF(COUNTIFS(DESK!$F$2:$F$601,C2,DESK!$AW$2:$AW$601,E2,DESK!$L$2:$L$601,1)=0,"That ID is a removed duplicate: use the ID on your list","OK")))))))) -> OK | K2: =IF(E2="","",IFERROR(INDEX(DESK!$B$2:$B$601,MATCH(E2,DESK!$AW$2:$AW$601,0)),"")) -> Partner 029 | L2: =IF(OR(D2="",C2=""),"",COUNTIFS($C$2:C2,C2,$H$2:H2,1)) -> 0 | M2: =IF(H2<>1,"",IF(COUNTIFS(LOG!$C$2:$C$2001,C2,LOG!$L$2:$L$2001,L2,LOG!$D$2:$D$2001,"BOOKED")>0,1,IF(AND(COUNTIFS(LOG!$C$2:$C$2001,C2,LOG!$L$2:$L$2001,L2,LOG!$D$2:$D$2001,"SENT_LINK")>0,COUNTIFS(LOG!$C$2:$C$2001,C2,LOG!$D$2:$D$2001,"SELF_BOOKED",LOG!$G$2:$G$2001,">"&G2)>0),1,0)))
A3: 46308.865 | B3: Lead | C3: 9000003855 | D3: SELF_BOOKED | E3: R395 | F3: calendly confirmation | G3: =IF(A3="","",IF(A3>=1,A3,IF(MAX($G$2:G2)=0,INT(SETTINGS!$B$4)+A3,INT(MAX($G$2:G2))+A3+IF(A3<MOD(MAX($G$2:G2),1),1,0)))) -> 46308.865 | H3: =IF(D3="","",IF(IFERROR(VLOOKUP(D3,LISTS!$A$2:$E$10,3,FALSE),0)=0,0,IF(IFERROR(COUNTIFS($C$2:C2,C3,$H$2:H2,1,$G$2:G2,">="&(G3-15/1440)),0)>0,0,1))) -> 0 | I3: =IF(H3=1,C3&"|"&COUNTIFS($C$2:C3,C3,$H$2:H3,1),"") | J3: =IF(D3="","",IF(A3="","Missing time",IF(AND(D3="NO_SLOTS",E3=""),"Write the request ID in column E",IF(C3="","Missing phone",IF(COUNTIF(DESK!$F$2:$F$601,C3)=0,"Phone not found: copy it from your list",IF(E3="","OK",IF(COUNTIFS(DESK!$F$2:$F$601,C3,DESK!$AW$2:$AW$601,E3)=0,"Request ID is not one of theirs: copy it from column D",IF(COUNTIFS(DESK!$F$2:$F$601,C3,DESK!$AW$2:$AW$601,E3,DESK!$L$2:$L$601,1)=0,"That ID is a removed duplicate: use the ID on your list","OK")))))))) -> OK | K3: =IF(E3="","",IFERROR(INDEX(DESK!$B$2:$B$601,MATCH(E3,DESK!$AW$2:$AW$601,0)),"")) -> Partner 015 | L3: =IF(OR(D3="",C3=""),"",COUNTIFS($C$2:C3,C3,$H$2:H3,1)) -> 0 | M3: =IF(H3<>1,"",IF(COUNTIFS(LOG!$C$2:$C$2001,C3,LOG!$L$2:$L$2001,L3,LOG!$D$2:$D$2001,"BOOKED")>0,1,IF(AND(COUNTIFS(LOG!$C$2:$C$2001,C3,LOG!$L$2:$L$2001,L3,LOG!$D$2:$D$2001,"SENT_LINK")>0,COUNTIFS(LOG!$C$2:$C$2001,C3,LOG!$D$2:$D$2001,"SELF_BOOKED",LOG!$G$2:$G$2001,">"&G3)>0),1,0)))
A4: 46308.865 | B4: Lead | C4: 9000003608 | D4: SELF_BOOKED | E4: R197 | F4: calendly confirmation | G4: =IF(A4="","",IF(A4>=1,A4,IF(MAX($G$2:G3)=0,INT(SETTINGS!$B$4)+A4,INT(MAX($G$2:G3))+A4+IF(A4<MOD(MAX($G$2:G3),1),1,0)))) -> 46308.865 | H4: =IF(D4="","",IF(IFERROR(VLOOKUP(D4,LISTS!$A$2:$E$10,3,FALSE),0)=0,0,IF(IFERROR(COUNTIFS($C$2:C3,C4,$H$2:H3,1,$G$2:G3,">="&(G4-15/1440)),0)>0,0,1))) -> 0 | I4: =IF(H4=1,C4&"|"&COUNTIFS($C$2:C4,C4,$H$2:H4,1),"") | J4: =IF(D4="","",IF(A4="","Missing time",IF(AND(D4="NO_SLOTS",E4=""),"Write the request ID in column E",IF(C4="","Missing phone",IF(COUNTIF(DESK!$F$2:$F$601,C4)=0,"Phone not found: copy it from your list",IF(E4="","OK",IF(COUNTIFS(DESK!$F$2:$F$601,C4,DESK!$AW$2:$AW$601,E4)=0,"Request ID is not one of theirs: copy it from column D",IF(COUNTIFS(DESK!$F$2:$F$601,C4,DESK!$AW$2:$AW$601,E4,DESK!$L$2:$L$601,1)=0,"That ID is a removed duplicate: use the ID on your list","OK")))))))) -> OK | K4: =IF(E4="","",IFERROR(INDEX(DESK!$B$2:$B$601,MATCH(E4,DESK!$AW$2:$AW$601,0)),"")) -> Partner 035 | L4: =IF(OR(D4="",C4=""),"",COUNTIFS($C$2:C4,C4,$H$2:H4,1)) -> 0 | M4: =IF(H4<>1,"",IF(COUNTIFS(LOG!$C$2:$C$2001,C4,LOG!$L$2:$L$2001,L4,LOG!$D$2:$D$2001,"BOOKED")>0,1,IF(AND(COUNTIFS(LOG!$C$2:$C$2001,C4,LOG!$L$2:$L$2001,L4,LOG!$D$2:$D$2001,"SENT_LINK")>0,COUNTIFS(LOG!$C$2:$C$2001,C4,LOG!$D$2:$D$2001,"SELF_BOOKED",LOG!$G$2:$G$2001,">"&G4)>0),1,0)))
A5: 46308.872 | B5: Lead | C5: 9000002607 | D5: SELF_BOOKED | E5: R431 | F5: calendly confirmation | G5: =IF(A5="","",IF(A5>=1,A5,IF(MAX($G$2:G4)=0,INT(SETTINGS!$B$4)+A5,INT(MAX($G$2:G4))+A5+IF(A5<MOD(MAX($G$2:G4),1),1,0)))) -> 46308.872 | H5: =IF(D5="","",IF(IFERROR(VLOOKUP(D5,LISTS!$A$2:$E$10,3,FALSE),0)=0,0,IF(IFERROR(COUNTIFS($C$2:C4,C5,$H$2:H4,1,$G$2:G4,">="&(G5-15/1440)),0)>0,0,1))) -> 0 | I5: =IF(H5=1,C5&"|"&COUNTIFS($C$2:C5,C5,$H$2:H5,1),"") | J5: =IF(D5="","",IF(A5="","Missing time",IF(AND(D5="NO_SLOTS",E5=""),"Write the request ID in column E",IF(C5="","Missing phone",IF(COUNTIF(DESK!$F$2:$F$601,C5)=0,"Phone not found: copy it from your list",IF(E5="","OK",IF(COUNTIFS(DESK!$F$2:$F$601,C5,DESK!$AW$2:$AW$601,E5)=0,"Request ID is not one of theirs: copy it from column D",IF(COUNTIFS(DESK!$F$2:$F$601,C5,DESK!$AW$2:$AW$601,E5,DESK!$L$2:$L$601,1)=0,"That ID is a removed duplicate: use the ID on your list","OK")))))))) -> OK | K5: =IF(E5="","",IFERROR(INDEX(DESK!$B$2:$B$601,MATCH(E5,DESK!$AW$2:$AW$601,0)),"")) -> Partner 057 | L5: =IF(OR(D5="",C5=""),"",COUNTIFS($C$2:C5,C5,$H$2:H5,1)) -> 0 | M5: =IF(H5<>1,"",IF(COUNTIFS(LOG!$C$2:$C$2001,C5,LOG!$L$2:$L$2001,L5,LOG!$D$2:$D$2001,"BOOKED")>0,1,IF(AND(COUNTIFS(LOG!$C$2:$C$2001,C5,LOG!$L$2:$L$2001,L5,LOG!$D$2:$D$2001,"SENT_LINK")>0,COUNTIFS(LOG!$C$2:$C$2001,C5,LOG!$D$2:$D$2001,"SELF_BOOKED",LOG!$G$2:$G$2001,">"&G5)>0),1,0)))
A6: 46308.876 | B6: Lead | C6: 9000003426 | D6: SELF_BOOKED | E6: R416 | F6: calendly confirmation | G6: =IF(A6="","",IF(A6>=1,A6,IF(MAX($G$2:G5)=0,INT(SETTINGS!$B$4)+A6,INT(MAX($G$2:G5))+A6+IF(A6<MOD(MAX($G$2:G5),1),1,0)))) -> 46308.876 | H6: =IF(D6="","",IF(IFERROR(VLOOKUP(D6,LISTS!$A$2:$E$10,3,FALSE),0)=0,0,IF(IFERROR(COUNTIFS($C$2:C5,C6,$H$2:H5,1,$G$2:G5,">="&(G6-15/1440)),0)>0,0,1))) -> 0 | I6: =IF(H6=1,C6&"|"&COUNTIFS($C$2:C6,C6,$H$2:H6,1),"") | J6: =IF(D6="","",IF(A6="","Missing time",IF(AND(D6="NO_SLOTS",E6=""),"Write the request ID in column E",IF(C6="","Missing phone",IF(COUNTIF(DESK!$F$2:$F$601,C6)=0,"Phone not found: copy it from your list",IF(E6="","OK",IF(COUNTIFS(DESK!$F$2:$F$601,C6,DESK!$AW$2:$AW$601,E6)=0,"Request ID is not one of theirs: copy it from column D",IF(COUNTIFS(DESK!$F$2:$F$601,C6,DESK!$AW$2:$AW$601,E6,DESK!$L$2:$L$601,1)=0,"That ID is a removed duplicate: use the ID on your list","OK")))))))) -> OK | K6: =IF(E6="","",IFERROR(INDEX(DESK!$B$2:$B$601,MATCH(E6,DESK!$AW$2:$AW$601,0)),"")) -> Partner 001 | L6: =IF(OR(D6="",C6=""),"",COUNTIFS($C$2:C6,C6,$H$2:H6,1)) -> 0 | M6: =IF(H6<>1,"",IF(COUNTIFS(LOG!$C$2:$C$2001,C6,LOG!$L$2:$L$2001,L6,LOG!$D$2:$D$2001,"BOOKED")>0,1,IF(AND(COUNTIFS(LOG!$C$2:$C$2001,C6,LOG!$L$2:$L$2001,L6,LOG!$D$2:$D$2001,"SENT_LINK")>0,COUNTIFS(LOG!$C$2:$C$2001,C6,LOG!$D$2:$D$2001,"SELF_BOOKED",LOG!$G$2:$G$2001,">"&G6)>0),1,0)))
A7: 46308.884 | B7: Lead | C7: 9000003309 | D7: SELF_BOOKED | E7: R256 | F7: calendly confirmation | G7: =IF(A7="","",IF(A7>=1,A7,IF(MAX($G$2:G6)=0,INT(SETTINGS!$B$4)+A7,INT(MAX($G$2:G6))+A7+IF(A7<MOD(MAX($G$2:G6),1),1,0)))) -> 46308.884 | H7: =IF(D7="","",IF(IFERROR(VLOOKUP(D7,LISTS!$A$2:$E$10,3,FALSE),0)=0,0,IF(IFERROR(COUNTIFS($C$2:C6,C7,$H$2:H6,1,$G$2:G6,">="&(G7-15/1440)),0)>0,0,1))) -> 0 | I7: =IF(H7=1,C7&"|"&COUNTIFS($C$2:C7,C7,$H$2:H7,1),"") | J7: =IF(D7="","",IF(A7="","Missing time",IF(AND(D7="NO_SLOTS",E7=""),"Write the request ID in column E",IF(C7="","Missing phone",IF(COUNTIF(DESK!$F$2:$F$601,C7)=0,"Phone not found: copy it from your list",IF(E7="","OK",IF(COUNTIFS(DESK!$F$2:$F$601,C7,DESK!$AW$2:$AW$601,E7)=0,"Request ID is not one of theirs: copy it from column D",IF(COUNTIFS(DESK!$F$2:$F$601,C7,DESK!$AW$2:$AW$601,E7,DESK!$L$2:$L$601,1)=0,"That ID is a removed duplicate: use the ID on your list","OK")))))))) -> OK | K7: =IF(E7="","",IFERROR(INDEX(DESK!$B$2:$B$601,MATCH(E7,DESK!$AW$2:$AW$601,0)),"")) -> Partner 028 | L7: =IF(OR(D7="",C7=""),"",COUNTIFS($C$2:C7,C7,$H$2:H7,1)) -> 0 | M7: =IF(H7<>1,"",IF(COUNTIFS(LOG!$C$2:$C$2001,C7,LOG!$L$2:$L$2001,L7,LOG!$D$2:$D$2001,"BOOKED")>0,1,IF(AND(COUNTIFS(LOG!$C$2:$C$2001,C7,LOG!$L$2:$L$2001,L7,LOG!$D$2:$D$2001,"SENT_LINK")>0,COUNTIFS(LOG!$C$2:$C$2001,C7,LOG!$D$2:$D$2001,"SELF_BOOKED",LOG!$G$2:$G$2001,">"&G7)>0),1,0)))
A8: 46308.889 | B8: Lead | C8: 9000004323 | D8: SELF_BOOKED | E8: R172 | F8: calendly confirmation | G8: =IF(A8="","",IF(A8>=1,A8,IF(MAX($G$2:G7)=0,INT(SETTINGS!$B$4)+A8,INT(MAX($G$2:G7))+A8+IF(A8<MOD(MAX($G$2:G7),1),1,0)))) -> 46308.889 | H8: =IF(D8="","",IF(IFERROR(VLOOKUP(D8,LISTS!$A$2:$E$10,3,FALSE),0)=0,0,IF(IFERROR(COUNTIFS($C$2:C7,C8,$H$2:H7,1,$G$2:G7,">="&(G8-15/1440)),0)>0,0,1))) -> 0 | I8: =IF(H8=1,C8&"|"&COUNTIFS($C$2:C8,C8,$H$2:H8,1),"") | J8: =IF(D8="","",IF(A8="","Missing time",IF(AND(D8="NO_SLOTS",E8=""),"Write the request ID in column E",IF(C8="","Missing phone",IF(COUNTIF(DESK!$F$2:$F$601,C8)=0,"Phone not found: copy it from your list",IF(E8="","OK",IF(COUNTIFS(DESK!$F$2:$F$601,C8,DESK!$AW$2:$AW$601,E8)=0,"Request ID is not one of theirs: copy it from column D",IF(COUNTIFS(DESK!$F$2:$F$601,C8,DESK!$AW$2:$AW$601,E8,DESK!$L$2:$L$601,1)=0,"That ID is a removed duplicate: use the ID on your list","OK")))))))) -> OK | K8: =IF(E8="","",IFERROR(INDEX(DESK!$B$2:$B$601,MATCH(E8,DESK!$AW$2:$AW$601,0)),"")) -> Partner 000 | L8: =IF(OR(D8="",C8=""),"",COUNTIFS($C$2:C8,C8,$H$2:H8,1)) -> 0 | M8: =IF(H8<>1,"",IF(COUNTIFS(LOG!$C$2:$C$2001,C8,LOG!$L$2:$L$2001,L8,LOG!$D$2:$D$2001,"BOOKED")>0,1,IF(AND(COUNTIFS(LOG!$C$2:$C$2001,C8,LOG!$L$2:$L$2001,L8,LOG!$D$2:$D$2001,"SENT_LINK")>0,COUNTIFS(LOG!$C$2:$C$2001,C8,LOG!$D$2:$D$2001,"SELF_BOOKED",LOG!$G$2:$G$2001,">"&G8)>0),1,0)))
A9: 46308.889 | B9: Lead | C9: 9000000527 | D9: SELF_BOOKED | E9: R235 | F9: calendly confirmation | G9: =IF(A9="","",IF(A9>=1,A9,IF(MAX($G$2:G8)=0,INT(SETTINGS!$B$4)+A9,INT(MAX($G$2:G8))+A9+IF(A9<MOD(MAX($G$2:G8),1),1,0)))) -> 46308.889 | H9: =IF(D9="","",IF(IFERROR(VLOOKUP(D9,LISTS!$A$2:$E$10,3,FALSE),0)=0,0,IF(IFERROR(COUNTIFS($C$2:C8,C9,$H$2:H8,1,$G$2:G8,">="&(G9-15/1440)),0)>0,0,1))) -> 0 | I9: =IF(H9=1,C9&"|"&COUNTIFS($C$2:C9,C9,$H$2:H9,1),"") | J9: =IF(D9="","",IF(A9="","Missing time",IF(AND(D9="NO_SLOTS",E9=""),"Write the request ID in column E",IF(C9="","Missing phone",IF(COUNTIF(DESK!$F$2:$F$601,C9)=0,"Phone not found: copy it from your list",IF(E9="","OK",IF(COUNTIFS(DESK!$F$2:$F$601,C9,DESK!$AW$2:$AW$601,E9)=0,"Request ID is not one of theirs: copy it from column D",IF(COUNTIFS(DESK!$F$2:$F$601,C9,DESK!$AW$2:$AW$601,E9,DESK!$L$2:$L$601,1)=0,"That ID is a removed duplicate: use the ID on your list","OK")))))))) -> OK | K9: =IF(E9="","",IFERROR(INDEX(DESK!$B$2:$B$601,MATCH(E9,DESK!$AW$2:$AW$601,0)),"")) -> Partner 044 | L9: =IF(OR(D9="",C9=""),"",COUNTIFS($C$2:C9,C9,$H$2:H9,1)) -> 0 | M9: =IF(H9<>1,"",IF(COUNTIFS(LOG!$C$2:$C$2001,C9,LOG!$L$2:$L$2001,L9,LOG!$D$2:$D$2001,"BOOKED")>0,1,IF(AND(COUNTIFS(LOG!$C$2:$C$2001,C9,LOG!$L$2:$L$2001,L9,LOG!$D$2:$D$2001,"SENT_LINK")>0,COUNTIFS(LOG!$C$2:$C$2001,C9,LOG!$D$2:$D$2001,"SELF_BOOKED",LOG!$G$2:$G$2001,">"&G9)>0),1,0)))
A10: 46308.897 | B10: Lead | C10: 9000003881 | D10: SELF_BOOKED | E10: R083 | F10: calendly confirmation | G10: =IF(A10="","",IF(A10>=1,A10,IF(MAX($G$2:G9)=0,INT(SETTINGS!$B$4)+A10,INT(MAX($G$2:G9))+A10+IF(A10<MOD(MAX($G$2:G9),1),1,0)))) -> 46308.897 | H10: =IF(D10="","",IF(IFERROR(VLOOKUP(D10,LISTS!$A$2:$E$10,3,FALSE),0)=0,0,IF(IFERROR(COUNTIFS($C$2:C9,C10,$H$2:H9,1,$G$2:G9,">="&(G10-15/1440)),0)>0,0,1))) -> 0 | I10: =IF(H10=1,C10&"|"&COUNTIFS($C$2:C10,C10,$H$2:H10,1),"") | J10: =IF(D10="","",IF(A10="","Missing time",IF(AND(D10="NO_SLOTS",E10=""),"Write the request ID in column E",IF(C10="","Missing phone",IF(COUNTIF(DESK!$F$2:$F$601,C10)=0,"Phone not found: copy it from your list",IF(E10="","OK",IF(COUNTIFS(DESK!$F$2:$F$601,C10,DESK!$AW$2:$AW$601,E10)=0,"Request ID is not one of theirs: copy it from column D",IF(COUNTIFS(DESK!$F$2:$F$601,C10,DESK!$AW$2:$AW$601,E10,DESK!$L$2:$L$601,1)=0,"That ID is a removed duplicate: use the ID on your list","OK")))))))) -> OK | K10: =IF(E10="","",IFERROR(INDEX(DESK!$B$2:$B$601,MATCH(E10,DESK!$AW$2:$AW$601,0)),"")) -> Partner 006 | L10: =IF(OR(D10="",C10=""),"",COUNTIFS($C$2:C10,C10,$H$2:H10,1)) -> 0 | M10: =IF(H10<>1,"",IF(COUNTIFS(LOG!$C$2:$C$2001,C10,LOG!$L$2:$L$2001,L10,LOG!$D$2:$D$2001,"BOOKED")>0,1,IF(AND(COUNTIFS(LOG!$C$2:$C$2001,C10,LOG!$L$2:$L$2001,L10,LOG!$D$2:$D$2001,"SENT_LINK")>0,COUNTIFS(LOG!$C$2:$C$2001,C10,LOG!$D$2:$D$2001,"SELF_BOOKED",LOG!$G$2:$G$2001,">"&G10)>0),1,0)))
A11: 46308.897 | B11: Lead | C11: 9000003283 | D11: SELF_BOOKED | E11: R344 | F11: calendly confirmation | G11: =IF(A11="","",IF(A11>=1,A11,IF(MAX($G$2:G10)=0,INT(SETTINGS!$B$4)+A11,INT(MAX($G$2:G10))+A11+IF(A11<MOD(MAX($G$2:G10),1),1,0)))) -> 46308.897 | H11: =IF(D11="","",IF(IFERROR(VLOOKUP(D11,LISTS!$A$2:$E$10,3,FALSE),0)=0,0,IF(IFERROR(COUNTIFS($C$2:C10,C11,$H$2:H10,1,$G$2:G10,">="&(G11-15/1440)),0)>0,0,1))) -> 0 | I11: =IF(H11=1,C11&"|"&COUNTIFS($C$2:C11,C11,$H$2:H11,1),"") | J11: =IF(D11="","",IF(A11="","Missing time",IF(AND(D11="NO_SLOTS",E11=""),"Write the request ID in column E",IF(C11="","Missing phone",IF(COUNTIF(DESK!$F$2:$F$601,C11)=0,"Phone not found: copy it from your list",IF(E11="","OK",IF(COUNTIFS(DESK!$F$2:$F$601,C11,DESK!$AW$2:$AW$601,E11)=0,"Request ID is not one of theirs: copy it from column D",IF(COUNTIFS(DESK!$F$2:$F$601,C11,DESK!$AW$2:$AW$601,E11,DESK!$L$2:$L$601,1)=0,"That ID is a removed duplicate: use the ID on your list","OK")))))))) -> OK | K11: =IF(E11="","",IFERROR(INDEX(DESK!$B$2:$B$601,MATCH(E11,DESK!$AW$2:$AW$601,0)),"")) -> Partner 067 | L11: =IF(OR(D11="",C11=""),"",COUNTIFS($C$2:C11,C11,$H$2:H11,1)) -> 0 | M11: =IF(H11<>1,"",IF(COUNTIFS(LOG!$C$2:$C$2001,C11,LOG!$L$2:$L$2001,L11,LOG!$D$2:$D$2001,"BOOKED")>0,1,IF(AND(COUNTIFS(LOG!$C$2:$C$2001,C11,LOG!$L$2:$L$2001,L11,LOG!$D$2:$D$2001,"SENT_LINK")>0,COUNTIFS(LOG!$C$2:$C$2001,C11,LOG!$D$2:$D$2001,"SELF_BOOKED",LOG!$G$2:$G$2001,">"&G11)>0),1,0)))
A12: 46308.9 | B12: Lead | C12: 9000003829 | D12: SELF_BOOKED | E12: R485 | F12: calendly confirmation | G12: =IF(A12="","",IF(A12>=1,A12,IF(MAX($G$2:G11)=0,INT(SETTINGS!$B$4)+A12,INT(MAX($G$2:G11))+A12+IF(A12<MOD(MAX($G$2:G11),1),1,0)))) -> 46308.9 | H12: =IF(D12="","",IF(IFERROR(VLOOKUP(D12,LISTS!$A$2:$E$10,3,FALSE),0)=0,0,IF(IFERROR(COUNTIFS($C$2:C11,C12,$H$2:H11,1,$G$2:G11,">="&(G12-15/1440)),0)>0,0,1))) -> 0 | I12: =IF(H12=1,C12&"|"&COUNTIFS($C$2:C12,C12,$H$2:H12,1),"") | J12: =IF(D12="","",IF(A12="","Missing time",IF(AND(D12="NO_SLOTS",E12=""),"Write the request ID in column E",IF(C12="","Missing phone",IF(COUNTIF(DESK!$F$2:$F$601,C12)=0,"Phone not found: copy it from your list",IF(E12="","OK",IF(COUNTIFS(DESK!$F$2:$F$601,C12,DESK!$AW$2:$AW$601,E12)=0,"Request ID is not one of theirs: copy it from column D",IF(COUNTIFS(DESK!$F$2:$F$601,C12,DESK!$AW$2:$AW$601,E12,DESK!$L$2:$L$601,1)=0,"That ID is a removed duplicate: use the ID on your list","OK")))))))) -> OK | K12: =IF(E12="","",IFERROR(INDEX(DESK!$B$2:$B$601,MATCH(E12,DESK!$AW$2:$AW$601,0)),"")) -> Partner 080 | L12: =IF(OR(D12="",C12=""),"",COUNTIFS($C$2:C12,C12,$H$2:H12,1)) -> 0 | M12: =IF(H12<>1,"",IF(COUNTIFS(LOG!$C$2:$C$2001,C12,LOG!$L$2:$L$2001,L12,LOG!$D$2:$D$2001,"BOOKED")>0,1,IF(AND(COUNTIFS(LOG!$C$2:$C$2001,C12,LOG!$L$2:$L$2001,L12,LOG!$D$2:$D$2001,"SENT_LINK")>0,COUNTIFS(LOG!$C$2:$C$2001,C12,LOG!$D$2:$D$2001,"SELF_BOOKED",LOG!$G$2:$G$2001,">"&G12)>0),1,0)))
A13: 46308.905 | B13: Lead | C13: 9000004700 | D13: SELF_BOOKED | E13: R325 | F13: calendly confirmation | G13: =IF(A13="","",IF(A13>=1,A13,IF(MAX($G$2:G12)=0,INT(SETTINGS!$B$4)+A13,INT(MAX($G$2:G12))+A13+IF(A13<MOD(MAX($G$2:G12),1),1,0)))) -> 46308.905 | H13: =IF(D13="","",IF(IFERROR(VLOOKUP(D13,LISTS!$A$2:$E$10,3,FALSE),0)=0,0,IF(IFERROR(COUNTIFS($C$2:C12,C13,$H$2:H12,1,$G$2:G12,">="&(G13-15/1440)),0)>0,0,1))) -> 0 | I13: =IF(H13=1,C13&"|"&COUNTIFS($C$2:C13,C13,$H$2:H13,1),"") | J13: =IF(D13="","",IF(A13="","Missing time",IF(AND(D13="NO_SLOTS",E13=""),"Write the request ID in column E",IF(C13="","Missing phone",IF(COUNTIF(DESK!$F$2:$F$601,C13)=0,"Phone not found: copy it from your list",IF(E13="","OK",IF(COUNTIFS(DESK!$F$2:$F$601,C13,DESK!$AW$2:$AW$601,E13)=0,"Request ID is not one of theirs: copy it from column D",IF(COUNTIFS(DESK!$F$2:$F$601,C13,DESK!$AW$2:$AW$601,E13,DESK!$L$2:$L$601,1)=0,"That ID is a removed duplicate: use the ID on your list","OK")))))))) -> OK | K13: =IF(E13="","",IFERROR(INDEX(DESK!$B$2:$B$601,MATCH(E13,DESK!$AW$2:$AW$601,0)),"")) -> Partner 045 | L13: =IF(OR(D13="",C13=""),"",COUNTIFS($C$2:C13,C13,$H$2:H13,1)) -> 0 | M13: =IF(H13<>1,"",IF(COUNTIFS(LOG!$C$2:$C$2001,C13,LOG!$L$2:$L$2001,L13,LOG!$D$2:$D$2001,"BOOKED")>0,1,IF(AND(COUNTIFS(LOG!$C$2:$C$2001,C13,LOG!$L$2:$L$2001,L13,LOG!$D$2:$D$2001,"SENT_LINK")>0,COUNTIFS(LOG!$C$2:$C$2001,C13,LOG!$D$2:$D$2001,"SELF_BOOKED",LOG!$G$2:$G$2001,">"&G13)>0),1,0)))
A14: 46308.909 | B14: Lead | C14: 9000005012 | D14: SELF_BOOKED | E14: R180 | F14: calendly confirmation | G14: =IF(A14="","",IF(A14>=1,A14,IF(MAX($G$2:G13)=0,INT(SETTINGS!$B$4)+A14,INT(MAX($G$2:G13))+A14+IF(A14<MOD(MAX($G$2:G13),1),1,0)))) -> 46308.909 | H14: =IF(D14="","",IF(IFERROR(VLOOKUP(D14,LISTS!$A$2:$E$10,3,FALSE),0)=0,0,IF(IFERROR(COUNTIFS($C$2:C13,C14,$H$2:H13,1,$G$2:G13,">="&(G14-15/1440)),0)>0,0,1))) -> 0 | I14: =IF(H14=1,C14&"|"&COUNTIFS($C$2:C14,C14,$H$2:H14,1),"") | J14: =IF(D14="","",IF(A14="","Missing time",IF(AND(D14="NO_SLOTS",E14=""),"Write the request ID in column E",IF(C14="","Missing phone",IF(COUNTIF(DESK!$F$2:$F$601,C14)=0,"Phone not found: copy it from your list",IF(E14="","OK",IF(COUNTIFS(DESK!$F$2:$F$601,C14,DESK!$AW$2:$AW$601,E14)=0,"Request ID is not one of theirs: copy it from column D",IF(COUNTIFS(DESK!$F$2:$F$601,C14,DESK!$AW$2:$AW$601,E14,DESK!$L$2:$L$601,1)=0,"That ID is a removed duplicate: use the ID on your list","OK")))))))) -> OK | K14: =IF(E14="","",IFERROR(INDEX(DESK!$B$2:$B$601,MATCH(E14,DESK!$AW$2:$AW$601,0)),"")) -> Partner 002 | L14: =IF(OR(D14="",C14=""),"",COUNTIFS($C$2:C14,C14,$H$2:H14,1)) -> 0 | M14: =IF(H14<>1,"",IF(COUNTIFS(LOG!$C$2:$C$2001,C14,LOG!$L$2:$L$2001,L14,LOG!$D$2:$D$2001,"BOOKED")>0,1,IF(AND(COUNTIFS(LOG!$C$2:$C$2001,C14,LOG!$L$2:$L$2001,L14,LOG!$D$2:$D$2001,"SENT_LINK")>0,COUNTIFS(LOG!$C$2:$C$2001,C14,LOG!$D$2:$D$2001,"SELF_BOOKED",LOG!$G$2:$G$2001,">"&G14)>0),1,0)))
... A91: 46309.412 | B91: Lead | C91: 9000003673 | D91: SELF_BOOKED | E91: R116 | F91: calendly confirmation | G91: =IF(A91="","",IF(A91>=1,A91,IF(MAX($G$2:G90)=0,INT(SETTINGS!$B$4)+A91,INT(MAX($G$2:G90))+A91+IF(A91<MOD(MAX($G$2:G90),1),1,0)))) -> 46309.412 | H91: =IF(D91="","",IF(IFERROR(VLOOKUP(D91,LISTS!$A$2:$E$10,3,FALSE),0)=0,0,IF(IFERROR(COUNTIFS($C$2:C90,C91,$H$2:H90,1,$G$2:G90,">="&(G91-15/1440)),0)>0,0,1))) -> 0 | I91: =IF(H91=1,C91&"|"&COUNTIFS($C$2:C91,C91,$H$2:H91,1),"") | J91: =IF(D91="","",IF(A91="","Missing time",IF(AND(D91="NO_SLOTS",E91=""),"Write the request ID in column E",IF(C91="","Missing phone",IF(COUNTIF(DESK!$F$2:$F$601,C91)=0,"Phone not found: copy it from your list",IF(E91="","OK",IF(COUNTIFS(DESK!$F$2:$F$601,C91,DESK!$AW$2:$AW$601,E91)=0,"Request ID is not one of theirs: copy it from column D",IF(COUNTIFS(DESK!$F$2:$F$601,C91,DESK!$AW$2:$AW$601,E91,DESK!$L$2:$L$601,1)=0,"That ID is a removed duplicate: use the ID on your list","OK")))))))) -> OK | K91: =IF(E91="","",IFERROR(INDEX(DESK!$B$2:$B$601,MATCH(E91,DESK!$AW$2:$AW$601,0)),"")) -> Partner 006 | L91: =IF(OR(D91="",C91=""),"",COUNTIFS($C$2:C91,C91,$H$2:H91,1)) -> 0 | M91: =IF(H91<>1,"",IF(COUNTIFS(LOG!$C$2:$C$2001,C91,LOG!$L$2:$L$2001,L91,LOG!$D$2:$D$2001,"BOOKED")>0,1,IF(AND(COUNTIFS(LOG!$C$2:$C$2001,C91,LOG!$L$2:$L$2001,L91,LOG!$D$2:$D$2001,"SENT_LINK")>0,COUNTIFS(LOG!$C$2:$C$2001,C91,LOG!$D$2:$D$2001,"SELF_BOOKED",LOG!$G$2:$G$2001,">"&G91)>0),1,0)))
A92: 46309.421 | B92: Ram | C92: 9000004869 | D92: SENT_LINK | F92: sent booking link | G92: =IF(A92="","",IF(A92>=1,A92,IF(MAX($G$2:G91)=0,INT(SETTINGS!$B$4)+A92,INT(MAX($G$2:G91))+A92+IF(A92<MOD(MAX($G$2:G91),1),1,0)))) -> 46309.421 | H92: =IF(D92="","",IF(IFERROR(VLOOKUP(D92,LISTS!$A$2:$E$10,3,FALSE),0)=0,0,IF(IFERROR(COUNTIFS($C$2:C91,C92,$H$2:H91,1,$G$2:G91,">="&(G92-15/1440)),0)>0,0,1))) -> 1 | I92: =IF(H92=1,C92&"|"&COUNTIFS($C$2:C92,C92,$H$2:H92,1),"") -> 9000004869|1 | J92: =IF(D92="","",IF(A92="","Missing time",IF(AND(D92="NO_SLOTS",E92=""),"Write the request ID in column E",IF(C92="","Missing phone",IF(COUNTIF(DESK!$F$2:$F$601,C92)=0,"Phone not found: copy it from your list",IF(E92="","OK",IF(COUNTIFS(DESK!$F$2:$F$601,C92,DESK!$AW$2:$AW$601,E92)=0,"Request ID is not one of theirs: copy it from column D",IF(COUNTIFS(DESK!$F$2:$F$601,C92,DESK!$AW$2:$AW$601,E92,DESK!$L$2:$L$601,1)=0,"That ID is a removed duplicate: use the ID on your list","OK")))))))) -> OK | K92: =IF(E92="","",IFERROR(INDEX(DESK!$B$2:$B$601,MATCH(E92,DESK!$AW$2:$AW$601,0)),"")) | L92: =IF(OR(D92="",C92=""),"",COUNTIFS($C$2:C92,C92,$H$2:H92,1)) -> 1 | M92: =IF(H92<>1,"",IF(COUNTIFS(LOG!$C$2:$C$2001,C92,LOG!$L$2:$L$2001,L92,LOG!$D$2:$D$2001,"BOOKED")>0,1,IF(AND(COUNTIFS(LOG!$C$2:$C$2001,C92,LOG!$L$2:$L$2001,L92,LOG!$D$2:$D$2001,"SENT_LINK")>0,COUNTIFS(LOG!$C$2:$C$2001,C92,LOG!$D$2:$D$2001,"SELF_BOOKED",LOG!$G$2:$G$2001,">"&G92)>0),1,0))) -> 1
A93: 46309.421 | B93: Ram | C93: 9000004869 | D93: BOOKED | E93: R415 | G93: =IF(A93="","",IF(A93>=1,A93,IF(MAX($G$2:G92)=0,INT(SETTINGS!$B$4)+A93,INT(MAX($G$2:G92))+A93+IF(A93<MOD(MAX($G$2:G92),1),1,0)))) -> 46309.421 | H93: =IF(D93="","",IF(IFERROR(VLOOKUP(D93,LISTS!$A$2:$E$10,3,FALSE),0)=0,0,IF(IFERROR(COUNTIFS($C$2:C92,C93,$H$2:H92,1,$G$2:G92,">="&(G93-15/1440)),0)>0,0,1))) -> 0 | I93: =IF(H93=1,C93&"|"&COUNTIFS($C$2:C93,C93,$H$2:H93,1),"") | J93: =IF(D93="","",IF(A93="","Missing time",IF(AND(D93="NO_SLOTS",E93=""),"Write the request ID in column E",IF(C93="","Missing phone",IF(COUNTIF(DESK!$F$2:$F$601,C93)=0,"Phone not found: copy it from your list",IF(E93="","OK",IF(COUNTIFS(DESK!$F$2:$F$601,C93,DESK!$AW$2:$AW$601,E93)=0,"Request ID is not one of theirs: copy it from column D",IF(COUNTIFS(DESK!$F$2:$F$601,C93,DESK!$AW$2:$AW$601,E93,DESK!$L$2:$L$601,1)=0,"That ID is a removed duplicate: use the ID on your list","OK")))))))) -> OK | K93: =IF(E93="","",IFERROR(INDEX(DESK!$B$2:$B$601,MATCH(E93,DESK!$AW$2:$AW$601,0)),"")) -> Partner 005 | L93: =IF(OR(D93="",C93=""),"",COUNTIFS($C$2:C93,C93,$H$2:H93,1)) -> 1 | M93: =IF(H93<>1,"",IF(COUNTIFS(LOG!$C$2:$C$2001,C93,LOG!$L$2:$L$2001,L93,LOG!$D$2:$D$2001,"BOOKED")>0,1,IF(AND(COUNTIFS(LOG!$C$2:$C$2001,C93,LOG!$L$2:$L$2001,L93,LOG!$D$2:$D$2001,"SENT_LINK")>0,COUNTIFS(LOG!$C$2:$C$2001,C93,LOG!$D$2:$D$2001,"SELF_BOOKED",LOG!$G$2:$G$2001,">"&G93)>0),1,0)))
A94: 46309.425 | B94: Ram | C94: 9000001580 | D94: CALL_BACK | F94: busy | G94: =IF(A94="","",IF(A94>=1,A94,IF(MAX($G$2:G93)=0,INT(SETTINGS!$B$4)+A94,INT(MAX($G$2:G93))+A94+IF(A94<MOD(MAX($G$2:G93),1),1,0)))) -> 46309.425 | H94: =IF(D94="","",IF(IFERROR(VLOOKUP(D94,LISTS!$A$2:$E$10,3,FALSE),0)=0,0,IF(IFERROR(COUNTIFS($C$2:C93,C94,$H$2:H93,1,$G$2:G93,">="&(G94-15/1440)),0)>0,0,1))) -> 1 | I94: =IF(H94=1,C94&"|"&COUNTIFS($C$2:C94,C94,$H$2:H94,1),"") -> 9000001580|1 | J94: =IF(D94="","",IF(A94="","Missing time",IF(AND(D94="NO_SLOTS",E94=""),"Write the request ID in column E",IF(C94="","Missing phone",IF(COUNTIF(DESK!$F$2:$F$601,C94)=0,"Phone not found: copy it from your list",IF(E94="","OK",IF(COUNTIFS(DESK!$F$2:$F$601,C94,DESK!$AW$2:$AW$601,E94)=0,"Request ID is not one of theirs: copy it from column D",IF(COUNTIFS(DESK!$F$2:$F$601,C94,DESK!$AW$2:$AW$601,E94,DESK!$L$2:$L$601,1)=0,"That ID is a removed duplicate: use the ID on your list","OK")))))))) -> OK | K94: =IF(E94="","",IFERROR(INDEX(DESK!$B$2:$B$601,MATCH(E94,DESK!$AW$2:$AW$601,0)),"")) | L94: =IF(OR(D94="",C94=""),"",COUNTIFS($C$2:C94,C94,$H$2:H94,1)) -> 1 | M94: =IF(H94<>1,"",IF(COUNTIFS(LOG!$C$2:$C$2001,C94,LOG!$L$2:$L$2001,L94,LOG!$D$2:$D$2001,"BOOKED")>0,1,IF(AND(COUNTIFS(LOG!$C$2:$C$2001,C94,LOG!$L$2:$L$2001,L94,LOG!$D$2:$D$2001,"SENT_LINK")>0,COUNTIFS(LOG!$C$2:$C$2001,C94,LOG!$D$2:$D$2001,"SELF_BOOKED",LOG!$G$2:$G$2001,">"&G94)>0),1,0))) -> 0
A95: 46309.43 | B95: Ram | C95: 9000003530 | D95: CALL_BACK | F95: busy | G95: =IF(A95="","",IF(A95>=1,A95,IF(MAX($G$2:G94)=0,INT(SETTINGS!$B$4)+A95,INT(MAX($G$2:G94))+A95+IF(A95<MOD(MAX($G$2:G94),1),1,0)))) -> 46309.43 | H95: =IF(D95="","",IF(IFERROR(VLOOKUP(D95,LISTS!$A$2:$E$10,3,FALSE),0)=0,0,IF(IFERROR(COUNTIFS($C$2:C94,C95,$H$2:H94,1,$G$2:G94,">="&(G95-15/1440)),0)>0,0,1))) -> 1 | I95: =IF(H95=1,C95&"|"&COUNTIFS($C$2:C95,C95,$H$2:H95,1),"") -> 9000003530|1 | J95: =IF(D95="","",IF(A95="","Missing time",IF(AND(D95="NO_SLOTS",E95=""),"Write the request ID in column E",IF(C95="","Missing phone",IF(COUNTIF(DESK!$F$2:$F$601,C95)=0,"Phone not found: copy it from your list",IF(E95="","OK",IF(COUNTIFS(DESK!$F$2:$F$601,C95,DESK!$AW$2:$AW$601,E95)=0,"Request ID is not one of theirs: copy it from column D",IF(COUNTIFS(DESK!$F$2:$F$601,C95,DESK!$AW$2:$AW$601,E95,DESK!$L$2:$L$601,1)=0,"That ID is a removed duplicate: use the ID on your list","OK")))))))) -> OK | K95: =IF(E95="","",IFERROR(INDEX(DESK!$B$2:$B$601,MATCH(E95,DESK!$AW$2:$AW$601,0)),"")) | L95: =IF(OR(D95="",C95=""),"",COUNTIFS($C$2:C95,C95,$H$2:H95,1)) -> 1 | M95: =IF(H95<>1,"",IF(COUNTIFS(LOG!$C$2:$C$2001,C95,LOG!$L$2:$L$2001,L95,LOG!$D$2:$D$2001,"BOOKED")>0,1,IF(AND(COUNTIFS(LOG!$C$2:$C$2001,C95,LOG!$L$2:$L$2001,L95,LOG!$D$2:$D$2001,"SENT_LINK")>0,COUNTIFS(LOG!$C$2:$C$2001,C95,LOG!$D$2:$D$2001,"SELF_BOOKED",LOG!$G$2:$G$2001,">"&G95)>0),1,0))) -> 0
A96: 46309.434 | B96: Ram | C96: 9000003699 | D96: NO_ANSWER | G96: =IF(A96="","",IF(A96>=1,A96,IF(MAX($G$2:G95)=0,INT(SETTINGS!$B$4)+A96,INT(MAX($G$2:G95))+A96+IF(A96<MOD(MAX($G$2:G95),1),1,0)))) -> 46309.434 | H96: =IF(D96="","",IF(IFERROR(VLOOKUP(D96,LISTS!$A$2:$E$10,3,FALSE),0)=0,0,IF(IFERROR(COUNTIFS($C$2:C95,C96,$H$2:H95,1,$G$2:G95,">="&(G96-15/1440)),0)>0,0,1))) -> 1 | I96: =IF(H96=1,C96&"|"&COUNTIFS($C$2:C96,C96,$H$2:H96,1),"") -> 9000003699|1 | J96: =IF(D96="","",IF(A96="","Missing time",IF(AND(D96="NO_SLOTS",E96=""),"Write the request ID in column E",IF(C96="","Missing phone",IF(COUNTIF(DESK!$F$2:$F$601,C96)=0,"Phone not found: copy it from your list",IF(E96="","OK",IF(COUNTIFS(DESK!$F$2:$F$601,C96,DESK!$AW$2:$AW$601,E96)=0,"Request ID is not one of theirs: copy it from column D",IF(COUNTIFS(DESK!$F$2:$F$601,C96,DESK!$AW$2:$AW$601,E96,DESK!$L$2:$L$601,1)=0,"That ID is a removed duplicate: use the ID on your list","OK")))))))) -> OK | K96: =IF(E96="","",IFERROR(INDEX(DESK!$B$2:$B$601,MATCH(E96,DESK!$AW$2:$AW$601,0)),"")) | L96: =IF(OR(D96="",C96=""),"",COUNTIFS($C$2:C96,C96,$H$2:H96,1)) -> 1 | M96: =IF(H96<>1,"",IF(COUNTIFS(LOG!$C$2:$C$2001,C96,LOG!$L$2:$L$2001,L96,LOG!$D$2:$D$2001,"BOOKED")>0,1,IF(AND(COUNTIFS(LOG!$C$2:$C$2001,C96,LOG!$L$2:$L$2001,L96,LOG!$D$2:$D$2001,"SENT_LINK")>0,COUNTIFS(LOG!$C$2:$C$2001,C96,LOG!$D$2:$D$2001,"SELF_BOOKED",LOG!$G$2:$G$2001,">"&G96)>0),1,0))) -> 0
A97: 46309.437 | B97: Ram | C97: 9000002295 | D97: NO_ANSWER | G97: =IF(A97="","",IF(A97>=1,A97,IF(MAX($G$2:G96)=0,INT(SETTINGS!$B$4)+A97,INT(MAX($G$2:G96))+A97+IF(A97<MOD(MAX($G$2:G96),1),1,0)))) -> 46309.437 | H97: =IF(D97="","",IF(IFERROR(VLOOKUP(D97,LISTS!$A$2:$E$10,3,FALSE),0)=0,0,IF(IFERROR(COUNTIFS($C$2:C96,C97,$H$2:H96,1,$G$2:G96,">="&(G97-15/1440)),0)>0,0,1))) -> 1 | I97: =IF(H97=1,C97&"|"&COUNTIFS($C$2:C97,C97,$H$2:H97,1),"") -> 9000002295|1 | J97: =IF(D97="","",IF(A97="","Missing time",IF(AND(D97="NO_SLOTS",E97=""),"Write the request ID in column E",IF(C97="","Missing phone",IF(COUNTIF(DESK!$F$2:$F$601,C97)=0,"Phone not found: copy it from your list",IF(E97="","OK",IF(COUNTIFS(DESK!$F$2:$F$601,C97,DESK!$AW$2:$AW$601,E97)=0,"Request ID is not one of theirs: copy it from column D",IF(COUNTIFS(DESK!$F$2:$F$601,C97,DESK!$AW$2:$AW$601,E97,DESK!$L$2:$L$601,1)=0,"That ID is a removed duplicate: use the ID on your list","OK")))))))) -> OK | K97: =IF(E97="","",IFERROR(INDEX(DESK!$B$2:$B$601,MATCH(E97,DESK!$AW$2:$AW$601,0)),"")) | L97: =IF(OR(D97="",C97=""),"",COUNTIFS($C$2:C97,C97,$H$2:H97,1)) -> 1 | M97: =IF(H97<>1,"",IF(COUNTIFS(LOG!$C$2:$C$2001,C97,LOG!$L$2:$L$2001,L97,LOG!$D$2:$D$2001,"BOOKED")>0,1,IF(AND(COUNTIFS(LOG!$C$2:$C$2001,C97,LOG!$L$2:$L$2001,L97,LOG!$D$2:$D$2001,"SENT_LINK")>0,COUNTIFS(LOG!$C$2:$C$2001,C97,LOG!$D$2:$D$2001,"SELF_BOOKED",LOG!$G$2:$G$2001,">"&G97)>0),1,0))) -> 0
A98: 46309.42 | B98: Lead | C98: 9000005389 | D98: SELF_BOOKED | E98: R387 | F98: calendly confirmation | G98: =IF(A98="","",IF(A98>=1,A98,IF(MAX($G$2:G97)=0,INT(SETTINGS!$B$4)+A98,INT(MAX($G$2:G97))+A98+IF(A98<MOD(MAX($G$2:G97),1),1,0)))) -> 46309.42 | H98: =IF(D98="","",IF(IFERROR(VLOOKUP(D98,LISTS!$A$2:$E$10,3,FALSE),0)=0,0,IF(IFERROR(COUNTIFS($C$2:C97,C98,$H$2:H97,1,$G$2:G97,">="&(G98-15/1440)),0)>0,0,1))) -> 0 | I98: =IF(H98=1,C98&"|"&COUNTIFS($C$2:C98,C98,$H$2:H98,1),"") | J98: =IF(D98="","",IF(A98="","Missing time",IF(AND(D98="NO_SLOTS",E98=""),"Write the request ID in column E",IF(C98="","Missing phone",IF(COUNTIF(DESK!$F$2:$F$601,C98)=0,"Phone not found: copy it from your list",IF(E98="","OK",IF(COUNTIFS(DESK!$F$2:$F$601,C98,DESK!$AW$2:$AW$601,E98)=0,"Request ID is not one of theirs: copy it from column D",IF(COUNTIFS(DESK!$F$2:$F$601,C98,DESK!$AW$2:$AW$601,E98,DESK!$L$2:$L$601,1)=0,"That ID is a removed duplicate: use the ID on your list","OK")))))))) -> OK | K98: =IF(E98="","",IFERROR(INDEX(DESK!$B$2:$B$601,MATCH(E98,DESK!$AW$2:$AW$601,0)),"")) -> Partner 025 | L98: =IF(OR(D98="",C98=""),"",COUNTIFS($C$2:C98,C98,$H$2:H98,1)) -> 0 | M98: =IF(H98<>1,"",IF(COUNTIFS(LOG!$C$2:$C$2001,C98,LOG!$L$2:$L$2001,L98,LOG!$D$2:$D$2001,"BOOKED")>0,1,IF(AND(COUNTIFS(LOG!$C$2:$C$2001,C98,LOG!$L$2:$L$2001,L98,LOG!$D$2:$D$2001,"SENT_LINK")>0,COUNTIFS(LOG!$C$2:$C$2001,C98,LOG!$D$2:$D$2001,"SELF_BOOKED",LOG!$G$2:$G$2001,">"&G98)>0),1,0)))
A99: 46309.421 | B99: Lead | C99: 9000004856 | D99: SELF_BOOKED | E99: R171 | F99: calendly confirmation | G99: =IF(A99="","",IF(A99>=1,A99,IF(MAX($G$2:G98)=0,INT(SETTINGS!$B$4)+A99,INT(MAX($G$2:G98))+A99+IF(A99<MOD(MAX($G$2:G98),1),1,0)))) -> 46309.421 | H99: =IF(D99="","",IF(IFERROR(VLOOKUP(D99,LISTS!$A$2:$E$10,3,FALSE),0)=0,0,IF(IFERROR(COUNTIFS($C$2:C98,C99,$H$2:H98,1,$G$2:G98,">="&(G99-15/1440)),0)>0,0,1))) -> 0 | I99: =IF(H99=1,C99&"|"&COUNTIFS($C$2:C99,C99,$H$2:H99,1),"") | J99: =IF(D99="","",IF(A99="","Missing time",IF(AND(D99="NO_SLOTS",E99=""),"Write the request ID in column E",IF(C99="","Missing phone",IF(COUNTIF(DESK!$F$2:$F$601,C99)=0,"Phone not found: copy it from your list",IF(E99="","OK",IF(COUNTIFS(DESK!$F$2:$F$601,C99,DESK!$AW$2:$AW$601,E99)=0,"Request ID is not one of theirs: copy it from column D",IF(COUNTIFS(DESK!$F$2:$F$601,C99,DESK!$AW$2:$AW$601,E99,DESK!$L$2:$L$601,1)=0,"That ID is a removed duplicate: use the ID on your list","OK")))))))) -> OK | K99: =IF(E99="","",IFERROR(INDEX(DESK!$B$2:$B$601,MATCH(E99,DESK!$AW$2:$AW$601,0)),"")) -> Partner 000 | L99: =IF(OR(D99="",C99=""),"",COUNTIFS($C$2:C99,C99,$H$2:H99,1)) -> 0 | M99: =IF(H99<>1,"",IF(COUNTIFS(LOG!$C$2:$C$2001,C99,LOG!$L$2:$L$2001,L99,LOG!$D$2:$D$2001,"BOOKED")>0,1,IF(AND(COUNTIFS(LOG!$C$2:$C$2001,C99,LOG!$L$2:$L$2001,L99,LOG!$D$2:$D$2001,"SENT_LINK")>0,COUNTIFS(LOG!$C$2:$C$2001,C99,LOG!$D$2:$D$2001,"SELF_BOOKED",LOG!$G$2:$G$2001,">"&G99)>0),1,0)))
A100: 46309.424 | B100: Lead | C100: 9000004414 | D100: SELF_BOOKED | E100: R015 | F100: calendly confirmation | G100: =IF(A100="","",IF(A100>=1,A100,IF(MAX($G$2:G99)=0,INT(SETTINGS!$B$4)+A100,INT(MAX($G$2:G99))+A100+IF(A100<MOD(MAX($G$2:G99),1),1,0)))) -> 46309.424 | H100: =IF(D100="","",IF(IFERROR(VLOOKUP(D100,LISTS!$A$2:$E$10,3,FALSE),0)=0,0,IF(IFERROR(COUNTIFS($C$2:C99,C100,$H$2:H99,1,$G$2:G99,">="&(G100-15/1440)),0)>0,0,1))) -> 0 | I100: =IF(H100=1,C100&"|"&COUNTIFS($C$2:C100,C100,$H$2:H100,1),"") | J100: =IF(D100="","",IF(A100="","Missing time",IF(AND(D100="NO_SLOTS",E100=""),"Write the request ID in column E",IF(C100="","Missing phone",IF(COUNTIF(DESK!$F$2:$F$601,C100)=0,"Phone not found: copy it from your list",IF(E100="","OK",IF(COUNTIFS(DESK!$F$2:$F$601,C100,DESK!$AW$2:$AW$601,E100)=0,"Request ID is not one of theirs: copy it from column D",IF(COUNTIFS(DESK!$F$2:$F$601,C100,DESK!$AW$2:$AW$601,E100,DESK!$L$2:$L$601,1)=0,"That ID is a removed duplicate: use the ID on your list","OK")))))))) -> OK | K100: =IF(E100="","",IFERROR(INDEX(DESK!$B$2:$B$601,MATCH(E100,DESK!$AW$2:$AW$601,0)),"")) -> Partner 003 | L100: =IF(OR(D100="",C100=""),"",COUNTIFS($C$2:C100,C100,$H$2:H100,1)) -> 0 | M100: =IF(H100<>1,"",IF(COUNTIFS(LOG!$C$2:$C$2001,C100,LOG!$L$2:$L$2001,L100,LOG!$D$2:$D$2001,"BOOKED")>0,1,IF(AND(COUNTIFS(LOG!$C$2:$C$2001,C100,LOG!$L$2:$L$2001,L100,LOG!$D$2:$D$2001,"SENT_LINK")>0,COUNTIFS(LOG!$C$2:$C$2001,C100,LOG!$D$2:$D$2001,"SELF_BOOKED",LOG!$G$2:$G$2001,">"&G100)>0),1,0)))
A101: 46309.425 | B101: Lead | C101: 9000004037 | D101: SELF_BOOKED | E101: R249 | F101: calendly confirmation | G101: =IF(A101="","",IF(A101>=1,A101,IF(MAX($G$2:G100)=0,INT(SETTINGS!$B$4)+A101,INT(MAX($G$2:G100))+A101+IF(A101<MOD(MAX($G$2:G100),1),1,0)))) -> 46309.425 | H101: =IF(D101="","",IF(IFERROR(VLOOKUP(D101,LISTS!$A$2:$E$10,3,FALSE),0)=0,0,IF(IFERROR(COUNTIFS($C$2:C100,C101,$H$2:H100,1,$G$2:G100,">="&(G101-15/1440)),0)>0,0,1))) -> 0 | I101: =IF(H101=1,C101&"|"&COUNTIFS($C$2:C101,C101,$H$2:H101,1),"") | J101: =IF(D101="","",IF(A101="","Missing time",IF(AND(D101="NO_SLOTS",E101=""),"Write the request ID in column E",IF(C101="","Missing phone",IF(COUNTIF(DESK!$F$2:$F$601,C101)=0,"Phone not found: copy it from your list",IF(E101="","OK",IF(COUNTIFS(DESK!$F$2:$F$601,C101,DESK!$AW$2:$AW$601,E101)=0,"Request ID is not one of theirs: copy it from column D",IF(COUNTIFS(DESK!$F$2:$F$601,C101,DESK!$AW$2:$AW$601,E101,DESK!$L$2:$L$601,1)=0,"That ID is a removed duplicate: use the ID on your list","OK")))))))) -> OK | K101: =IF(E101="","",IFERROR(INDEX(DESK!$B$2:$B$601,MATCH(E101,DESK!$AW$2:$AW$601,0)),"")) -> Partner 019 | L101: =IF(OR(D101="",C101=""),"",COUNTIFS($C$2:C101,C101,$H$2:H101,1)) -> 0 | M101: =IF(H101<>1,"",IF(COUNTIFS(LOG!$C$2:$C$2001,C101,LOG!$L$2:$L$2001,L101,LOG!$D$2:$D$2001,"BOOKED")>0,1,IF(AND(COUNTIFS(LOG!$C$2:$C$2001,C101,LOG!$L$2:$L$2001,L101,LOG!$D$2:$D$2001,"SENT_LINK")>0,COUNTIFS(LOG!$C$2:$C$2001,C101,LOG!$D$2:$D$2001,"SELF_BOOKED",LOG!$G$2:$G$2001,">"&G101)>0),1,0)))
A102: 46309.435 | B102: Lead | C102: 9000002581 | D102: SELF_BOOKED | E102: R132 | F102: calendly confirmation | G102: =IF(A102="","",IF(A102>=1,A102,IF(MAX($G$2:G101)=0,INT(SETTINGS!$B$4)+A102,INT(MAX($G$2:G101))+A102+IF(A102<MOD(MAX($G$2:G101),1),1,0)))) -> 46309.435 | H102: =IF(D102="","",IF(IFERROR(VLOOKUP(D102,LISTS!$A$2:$E$10,3,FALSE),0)=0,0,IF(IFERROR(COUNTIFS($C$2:C101,C102,$H$2:H101,1,$G$2:G101,">="&(G102-15/1440)),0)>0,0,1))) -> 0 | I102: =IF(H102=1,C102&"|"&COUNTIFS($C$2:C102,C102,$H$2:H102,1),"") | J102: =IF(D102="","",IF(A102="","Missing time",IF(AND(D102="NO_SLOTS",E102=""),"Write the request ID in column E",IF(C102="","Missing phone",IF(COUNTIF(DESK!$F$2:$F$601,C102)=0,"Phone not found: copy it from your list",IF(E102="","OK",IF(COUNTIFS(DESK!$F$2:$F$601,C102,DESK!$AW$2:$AW$601,E102)=0,"Request ID is not one of theirs: copy it from column D",IF(COUNTIFS(DESK!$F$2:$F$601,C102,DESK!$AW$2:$AW$601,E102,DESK!$L$2:$L$601,1)=0,"That ID is a removed duplicate: use the ID on your list","OK")))))))) -> OK | K102: =IF(E102="","",IFERROR(INDEX(DESK!$B$2:$B$601,MATCH(E102,DESK!$AW$2:$AW$601,0)),"")) -> Partner 000 | L102: =IF(OR(D102="",C102=""),"",COUNTIFS($C$2:C102,C102,$H$2:H102,1)) -> 0 | M102: =IF(H102<>1,"",IF(COUNTIFS(LOG!$C$2:$C$2001,C102,LOG!$L$2:$L$2001,L102,LOG!$D$2:$D$2001,"BOOKED")>0,1,IF(AND(COUNTIFS(LOG!$C$2:$C$2001,C102,LOG!$L$2:$L$2001,L102,LOG!$D$2:$D$2001,"SENT_LINK")>0,COUNTIFS(LOG!$C$2:$C$2001,C102,LOG!$D$2:$D$2001,"SELF_BOOKED",LOG!$G$2:$G$2001,">"&G102)>0),1,0)))
A103: 46309.435 | B103: Lead | C103: 9000003036 | D103: SELF_BOOKED | E103: R480 | F103: calendly confirmation | G103: =IF(A103="","",IF(A103>=1,A103,IF(MAX($G$2:G102)=0,INT(SETTINGS!$B$4)+A103,INT(MAX($G$2:G102))+A103+IF(A103<MOD(MAX($G$2:G102),1),1,0)))) -> 46309.435 | H103: =IF(D103="","",IF(IFERROR(VLOOKUP(D103,LISTS!$A$2:$E$10,3,FALSE),0)=0,0,IF(IFERROR(COUNTIFS($C$2:C102,C103,$H$2:H102,1,$G$2:G102,">="&(G103-15/1440)),0)>0,0,1))) -> 0 | I103: =IF(H103=1,C103&"|"&COUNTIFS($C$2:C103,C103,$H$2:H103,1),"") | J103: =IF(D103="","",IF(A103="","Missing time",IF(AND(D103="NO_SLOTS",E103=""),"Write the request ID in column E",IF(C103="","Missing phone",IF(COUNTIF(DESK!$F$2:$F$601,C103)=0,"Phone not found: copy it from your list",IF(E103="","OK",IF(COUNTIFS(DESK!$F$2:$F$601,C103,DESK!$AW$2:$AW$601,E103)=0,"Request ID is not one of theirs: copy it from column D",IF(COUNTIFS(DESK!$F$2:$F$601,C103,DESK!$AW$2:$AW$601,E103,DESK!$L$2:$L$601,1)=0,"That ID is a removed duplicate: use the ID on your list","OK")))))))) -> OK | K103: =IF(E103="","",IFERROR(INDEX(DESK!$B$2:$B$601,MATCH(E103,DESK!$AW$2:$AW$601,0)),"")) -> Partner 017 | L103: =IF(OR(D103="",C103=""),"",COUNTIFS($C$2:C103,C103,$H$2:H103,1)) -> 0 | M103: =IF(H103<>1,"",IF(COUNTIFS(LOG!$C$2:$C$2001,C103,LOG!$L$2:$L$2001,L103,LOG!$D$2:$D$2001,"BOOKED")>0,1,IF(AND(COUNTIFS(LOG!$C$2:$C$2001,C103,LOG!$L$2:$L$2001,L103,LOG!$D$2:$D$2001,"SENT_LINK")>0,COUNTIFS(LOG!$C$2:$C$2001,C103,LOG!$D$2:$D$2001,"SELF_BOOKED",LOG!$G$2:$G$2001,">"&G103)>0),1,0)))
A104: 46309.441 | B104: Ram | C104: 9000003348 | D104: BOOKED | G104: =IF(A104="","",IF(A104>=1,A104,IF(MAX($G$2:G103)=0,INT(SETTINGS!$B$4)+A104,INT(MAX($G$2:G103))+A104+IF(A104<MOD(MAX($G$2:G103),1),1,0)))) -> 46309.441 | H104: =IF(D104="","",IF(IFERROR(VLOOKUP(D104,LISTS!$A$2:$E$10,3,FALSE),0)=0,0,IF(IFERROR(COUNTIFS($C$2:C103,C104,$H$2:H103,1,$G$2:G103,">="&(G104-15/1440)),0)>0,0,1))) -> 1 | I104: =IF(H104=1,C104&"|"&COUNTIFS($C$2:C104,C104,$H$2:H104,1),"") -> 9000003348|1 | J104: =IF(D104="","",IF(A104="","Missing time",IF(AND(D104="NO_SLOTS",E104=""),"Write the request ID in column E",IF(C104="","Missing phone",IF(COUNTIF(DESK!$F$2:$F$601,C104)=0,"Phone not found: copy it from your list",IF(E104="","OK",IF(COUNTIFS(DESK!$F$2:$F$601,C104,DESK!$AW$2:$AW$601,E104)=0,"Request ID is not one of theirs: copy it from column D",IF(COUNTIFS(DESK!$F$2:$F$601,C104,DESK!$AW$2:$AW$601,E104,DESK!$L$2:$L$601,1)=0,"That ID is a removed duplicate: use the ID on your list","OK")))))))) -> OK | K104: =IF(E104="","",IFERROR(INDEX(DESK!$B$2:$B$601,MATCH(E104,DESK!$AW$2:$AW$601,0)),"")) | L104: =IF(OR(D104="",C104=""),"",COUNTIFS($C$2:C104,C104,$H$2:H104,1)) -> 1 | M104: =IF(H104<>1,"",IF(COUNTIFS(LOG!$C$2:$C$2001,C104,LOG!$L$2:$L$2001,L104,LOG!$D$2:$D$2001,"BOOKED")>0,1,IF(AND(COUNTIFS(LOG!$C$2:$C$2001,C104,LOG!$L$2:$L$2001,L104,LOG!$D$2:$D$2001,"SENT_LINK")>0,COUNTIFS(LOG!$C$2:$C$2001,C104,LOG!$D$2:$D$2001,"SELF_BOOKED",LOG!$G$2:$G$2001,">"&G104)>0),1,0))) -> 1
A105: 46309.444 | B105: Ram | C105: 9000002165 | D105: NO_ANSWER | G105: =IF(A105="","",IF(A105>=1,A105,IF(MAX($G$2:G104)=0,INT(SETTINGS!$B$4)+A105,INT(MAX($G$2:G104))+A105+IF(A105<MOD(MAX($G$2:G104),1),1,0)))) -> 46309.444 | H105: =IF(D105="","",IF(IFERROR(VLOOKUP(D105,LISTS!$A$2:$E$10,3,FALSE),0)=0,0,IF(IFERROR(COUNTIFS($C$2:C104,C105,$H$2:H104,1,$G$2:G104,">="&(G105-15/1440)),0)>0,0,1))) -> 1 | I105: =IF(H105=1,C105&"|"&COUNTIFS($C$2:C105,C105,$H$2:H105,1),"") -> 9000002165|1 | J105: =IF(D105="","",IF(A105="","Missing time",IF(AND(D105="NO_SLOTS",E105=""),"Write the request ID in column E",IF(C105="","Missing phone",IF(COUNTIF(DESK!$F$2:$F$601,C105)=0,"Phone not found: copy it from your list",IF(E105="","OK",IF(COUNTIFS(DESK!$F$2:$F$601,C105,DESK!$AW$2:$AW$601,E105)=0,"Request ID is not one of theirs: copy it from column D",IF(COUNTIFS(DESK!$F$2:$F$601,C105,DESK!$AW$2:$AW$601,E105,DESK!$L$2:$L$601,1)=0,"That ID is a removed duplicate: use the ID on your list","OK")))))))) -> OK | K105: =IF(E105="","",IFERROR(INDEX(DESK!$B$2:$B$601,MATCH(E105,DESK!$AW$2:$AW$601,0)),"")) | L105: =IF(OR(D105="",C105=""),"",COUNTIFS($C$2:C105,C105,$H$2:H105,1)) -> 1 | M105: =IF(H105<>1,"",IF(COUNTIFS(LOG!$C$2:$C$2001,C105,LOG!$L$2:$L$2001,L105,LOG!$D$2:$D$2001,"BOOKED")>0,1,IF(AND(COUNTIFS(LOG!$C$2:$C$2001,C105,LOG!$L$2:$L$2001,L105,LOG!$D$2:$D$2001,"SENT_LINK")>0,COUNTIFS(LOG!$C$2:$C$2001,C105,LOG!$D$2:$D$2001,"SELF_BOOKED",LOG!$G$2:$G$2001,">"&G105)>0),1,0))) -> 0
A106: 46309.448 | B106: Ram | C106: 9000000852 | D106: SENT_LINK | F106: sent booking link | G106: =IF(A106="","",IF(A106>=1,A106,IF(MAX($G$2:G105)=0,INT(SETTINGS!$B$4)+A106,INT(MAX($G$2:G105))+A106+IF(A106<MOD(MAX($G$2:G105),1),1,0)))) -> 46309.448 | H106: =IF(D106="","",IF(IFERROR(VLOOKUP(D106,LISTS!$A$2:$E$10,3,FALSE),0)=0,0,IF(IFERROR(COUNTIFS($C$2:C105,C106,$H$2:H105,1,$G$2:G105,">="&(G106-15/1440)),0)>0,0,1))) -> 1 | I106: =IF(H106=1,C106&"|"&COUNTIFS($C$2:C106,C106,$H$2:H106,1),"") -> 9000000852|1 | J106: =IF(D106="","",IF(A106="","Missing time",IF(AND(D106="NO_SLOTS",E106=""),"Write the request ID in column E",IF(C106="","Missing phone",IF(COUNTIF(DESK!$F$2:$F$601,C106)=0,"Phone not found: copy it from your list",IF(E106="","OK",IF(COUNTIFS(DESK!$F$2:$F$601,C106,DESK!$AW$2:$AW$601,E106)=0,"Request ID is not one of theirs: copy it from column D",IF(COUNTIFS(DESK!$F$2:$F$601,C106,DESK!$AW$2:$AW$601,E106,DESK!$L$2:$L$601,1)=0,"That ID is a removed duplicate: use the ID on your list","OK")))))))) -> OK | K106: =IF(E106="","",IFERROR(INDEX(DESK!$B$2:$B$601,MATCH(E106,DESK!$AW$2:$AW$601,0)),"")) | L106: =IF(OR(D106="",C106=""),"",COUNTIFS($C$2:C106,C106,$H$2:H106,1)) -> 1 | M106: =IF(H106<>1,"",IF(COUNTIFS(LOG!$C$2:$C$2001,C106,LOG!$L$2:$L$2001,L106,LOG!$D$2:$D$2001,"BOOKED")>0,1,IF(AND(COUNTIFS(LOG!$C$2:$C$2001,C106,LOG!$L$2:$L$2001,L106,LOG!$D$2:$D$2001,"SENT_LINK")>0,COUNTIFS(LOG!$C$2:$C$2001,C106,LOG!$D$2:$D$2001,"SELF_BOOKED",LOG!$G$2:$G$2001,">"&G106)>0),1,0))) -> 1
A107: 46309.448 | B107: Ram | C107: 9000000852 | D107: BOOKED | E107: R284 | G107: =IF(A107="","",IF(A107>=1,A107,IF(MAX($G$2:G106)=0,INT(SETTINGS!$B$4)+A107,INT(MAX($G$2:G106))+A107+IF(A107<MOD(MAX($G$2:G106),1),1,0)))) -> 46309.448 | H107: =IF(D107="","",IF(IFERROR(VLOOKUP(D107,LISTS!$A$2:$E$10,3,FALSE),0)=0,0,IF(IFERROR(COUNTIFS($C$2:C106,C107,$H$2:H106,1,$G$2:G106,">="&(G107-15/1440)),0)>0,0,1))) -> 0 | I107: =IF(H107=1,C107&"|"&COUNTIFS($C$2:C107,C107,$H$2:H107,1),"") | J107: =IF(D107="","",IF(A107="","Missing time",IF(AND(D107="NO_SLOTS",E107=""),"Write the request ID in column E",IF(C107="","Missing phone",IF(COUNTIF(DESK!$F$2:$F$601,C107)=0,"Phone not found: copy it from your list",IF(E107="","OK",IF(COUNTIFS(DESK!$F$2:$F$601,C107,DESK!$AW$2:$AW$601,E107)=0,"Request ID is not one of theirs: copy it from column D",IF(COUNTIFS(DESK!$F$2:$F$601,C107,DESK!$AW$2:$AW$601,E107,DESK!$L$2:$L$601,1)=0,"That ID is a removed duplicate: use the ID on your list","OK")))))))) -> OK | K107: =IF(E107="","",IFERROR(INDEX(DESK!$B$2:$B$601,MATCH(E107,DESK!$AW$2:$AW$601,0)),"")) -> Partner 042 | L107: =IF(OR(D107="",C107=""),"",COUNTIFS($C$2:C107,C107,$H$2:H107,1)) -> 1 | M107: =IF(H107<>1,"",IF(COUNTIFS(LOG!$C$2:$C$2001,C107,LOG!$L$2:$L$2001,L107,LOG!$D$2:$D$2001,"BOOKED")>0,1,IF(AND(COUNTIFS(LOG!$C$2:$C$2001,C107,LOG!$L$2:$L$2001,L107,LOG!$D$2:$D$2001,"SENT_LINK")>0,COUNTIFS(LOG!$C$2:$C$2001,C107,LOG!$D$2:$D$2001,"SELF_BOOKED",LOG!$G$2:$G$2001,">"&G107)>0),1,0)))
A108: 46309.452 | B108: Ram | C108: 9000004791 | D108: SENT_LINK | F108: sent booking link | G108: =IF(A108="","",IF(A108>=1,A108,IF(MAX($G$2:G107)=0,INT(SETTINGS!$B$4)+A108,INT(MAX($G$2:G107))+A108+IF(A108<MOD(MAX($G$2:G107),1),1,0)))) -> 46309.452 | H108: =IF(D108="","",IF(IFERROR(VLOOKUP(D108,LISTS!$A$2:$E$10,3,FALSE),0)=0,0,IF(IFERROR(COUNTIFS($C$2:C107,C108,$H$2:H107,1,$G$2:G107,">="&(G108-15/1440)),0)>0,0,1))) -> 1 | I108: =IF(H108=1,C108&"|"&COUNTIFS($C$2:C108,C108,$H$2:H108,1),"") -> 9000004791|1 | J108: =IF(D108="","",IF(A108="","Missing time",IF(AND(D108="NO_SLOTS",E108=""),"Write the request ID in column E",IF(C108="","Missing phone",IF(COUNTIF(DESK!$F$2:$F$601,C108)=0,"Phone not found: copy it from your list",IF(E108="","OK",IF(COUNTIFS(DESK!$F$2:$F$601,C108,DESK!$AW$2:$AW$601,E108)=0,"Request ID is not one of theirs: copy it from column D",IF(COUNTIFS(DESK!$F$2:$F$601,C108,DESK!$AW$2:$AW$601,E108,DESK!$L$2:$L$601,1)=0,"That ID is a removed duplicate: use the ID on your list","OK")))))))) -> OK | K108: =IF(E108="","",IFERROR(INDEX(DESK!$B$2:$B$601,MATCH(E108,DESK!$AW$2:$AW$601,0)),"")) | L108: =IF(OR(D108="",C108=""),"",COUNTIFS($C$2:C108,C108,$H$2:H108,1)) -> 1 | M108: =IF(H108<>1,"",IF(COUNTIFS(LOG!$C$2:$C$2001,C108,LOG!$L$2:$L$2001,L108,LOG!$D$2:$D$2001,"BOOKED")>0,1,IF(AND(COUNTIFS(LOG!$C$2:$C$2001,C108,LOG!$L$2:$L$2001,L108,LOG!$D$2:$D$2001,"SENT_LINK")>0,COUNTIFS(LOG!$C$2:$C$2001,C108,LOG!$D$2:$D$2001,"SELF_BOOKED",LOG!$G$2:$G$2001,">"&G108)>0),1,0))) -> 1
A109: 46309.452 | B109: Ram | C109: 9000004791 | D109: BOOKED | E109: R426 | G109: =IF(A109="","",IF(A109>=1,A109,IF(MAX($G$2:G108)=0,INT(SETTINGS!$B$4)+A109,INT(MAX($G$2:G108))+A109+IF(A109<MOD(MAX($G$2:G108),1),1,0)))) -> 46309.452 | H109: =IF(D109="","",IF(IFERROR(VLOOKUP(D109,LISTS!$A$2:$E$10,3,FALSE),0)=0,0,IF(IFERROR(COUNTIFS($C$2:C108,C109,$H$2:H108,1,$G$2:G108,">="&(G109-15/1440)),0)>0,0,1))) -> 0 | I109: =IF(H109=1,C109&"|"&COUNTIFS($C$2:C109,C109,$H$2:H109,1),"") | J109: =IF(D109="","",IF(A109="","Missing time",IF(AND(D109="NO_SLOTS",E109=""),"Write the request ID in column E",IF(C109="","Missing phone",IF(COUNTIF(DESK!$F$2:$F$601,C109)=0,"Phone not found: copy it from your list",IF(E109="","OK",IF(COUNTIFS(DESK!$F$2:$F$601,C109,DESK!$AW$2:$AW$601,E109)=0,"Request ID is not one of theirs: copy it from column D",IF(COUNTIFS(DESK!$F$2:$F$601,C109,DESK!$AW$2:$AW$601,E109,DESK!$L$2:$L$601,1)=0,"That ID is a removed duplicate: use the ID on your list","OK")))))))) -> OK | K109: =IF(E109="","",IFERROR(INDEX(DESK!$B$2:$B$601,MATCH(E109,DESK!$AW$2:$AW$601,0)),"")) -> Partner 023 | L109: =IF(OR(D109="",C109=""),"",COUNTIFS($C$2:C109,C109,$H$2:H109,1)) -> 1 | M109: =IF(H109<>1,"",IF(COUNTIFS(LOG!$C$2:$C$2001,C109,LOG!$L$2:$L$2001,L109,LOG!$D$2:$D$2001,"BOOKED")>0,1,IF(AND(COUNTIFS(LOG!$C$2:$C$2001,C109,LOG!$L$2:$L$2001,L109,LOG!$D$2:$D$2001,"SENT_LINK")>0,COUNTIFS(LOG!$C$2:$C$2001,C109,LOG!$D$2:$D$2001,"SELF_BOOKED",LOG!$G$2:$G$2001,">"&G109)>0),1,0)))
A110: 46309.455 | B110: Ram | C110: 9000000969 | D110: NO_ANSWER | G110: =IF(A110="","",IF(A110>=1,A110,IF(MAX($G$2:G109)=0,INT(SETTINGS!$B$4)+A110,INT(MAX($G$2:G109))+A110+IF(A110<MOD(MAX($G$2:G109),1),1,0)))) -> 46309.455 | H110: =IF(D110="","",IF(IFERROR(VLOOKUP(D110,LISTS!$A$2:$E$10,3,FALSE),0)=0,0,IF(IFERROR(COUNTIFS($C$2:C109,C110,$H$2:H109,1,$G$2:G109,">="&(G110-15/1440)),0)>0,0,1))) -> 1 | I110: =IF(H110=1,C110&"|"&COUNTIFS($C$2:C110,C110,$H$2:H110,1),"") -> 9000000969|1 | J110: =IF(D110="","",IF(A110="","Missing time",IF(AND(D110="NO_SLOTS",E110=""),"Write the request ID in column E",IF(C110="","Missing phone",IF(COUNTIF(DESK!$F$2:$F$601,C110)=0,"Phone not found: copy it from your list",IF(E110="","OK",IF(COUNTIFS(DESK!$F$2:$F$601,C110,DESK!$AW$2:$AW$601,E110)=0,"Request ID is not one of theirs: copy it from column D",IF(COUNTIFS(DESK!$F$2:$F$601,C110,DESK!$AW$2:$AW$601,E110,DESK!$L$2:$L$601,1)=0,"That ID is a removed duplicate: use the ID on your list","OK")))))))) -> OK | K110: =IF(E110="","",IFERROR(INDEX(DESK!$B$2:$B$601,MATCH(E110,DESK!$AW$2:$AW$601,0)),"")) | L110: =IF(OR(D110="",C110=""),"",COUNTIFS($C$2:C110,C110,$H$2:H110,1)) -> 1 | M110: =IF(H110<>1,"",IF(COUNTIFS(LOG!$C$2:$C$2001,C110,LOG!$L$2:$L$2001,L110,LOG!$D$2:$D$2001,"BOOKED")>0,1,IF(AND(COUNTIFS(LOG!$C$2:$C$2001,C110,LOG!$L$2:$L$2001,L110,LOG!$D$2:$D$2001,"SENT_LINK")>0,COUNTIFS(LOG!$C$2:$C$2001,C110,LOG!$D$2:$D$2001,"SELF_BOOKED",LOG!$G$2:$G$2001,">"&G110)>0),1,0))) -> 0
A111: 46309.439 | B111: Lead | C111: 9000002165 | D111: SELF_BOOKED | E111: R352 | F111: calendly confirmation | G111: =IF(A111="","",IF(A111>=1,A111,IF(MAX($G$2:G110)=0,INT(SETTINGS!$B$4)+A111,INT(MAX($G$2:G110))+A111+IF(A111<MOD(MAX($G$2:G110),1),1,0)))) -> 46309.439 | H111: =IF(D111="","",IF(IFERROR(VLOOKUP(D111,LISTS!$A$2:$E$10,3,FALSE),0)=0,0,IF(IFERROR(COUNTIFS($C$2:C110,C111,$H$2:H110,1,$G$2:G110,">="&(G111-15/1440)),0)>0,0,1))) -> 0 | I111: =IF(H111=1,C111&"|"&COUNTIFS($C$2:C111,C111,$H$2:H111,1),"") | J111: =IF(D111="","",IF(A111="","Missing time",IF(AND(D111="NO_SLOTS",E111=""),"Write the request ID in column E",IF(C111="","Missing phone",IF(COUNTIF(DESK!$F$2:$F$601,C111)=0,"Phone not found: copy it from your list",IF(E111="","OK",IF(COUNTIFS(DESK!$F$2:$F$601,C111,DESK!$AW$2:$AW$601,E111)=0,"Request ID is not one of theirs: copy it from column D",IF(COUNTIFS(DESK!$F$2:$F$601,C111,DESK!$AW$2:$AW$601,E111,DESK!$L$2:$L$601,1)=0,"That ID is a removed duplicate: use the ID on your list","OK")))))))) -> OK | K111: =IF(E111="","",IFERROR(INDEX(DESK!$B$2:$B$601,MATCH(E111,DESK!$AW$2:$AW$601,0)),"")) -> Partner 003 | L111: =IF(OR(D111="",C111=""),"",COUNTIFS($C$2:C111,C111,$H$2:H111,1)) -> 1 | M111: =IF(H111<>1,"",IF(COUNTIFS(LOG!$C$2:$C$2001,C111,LOG!$L$2:$L$2001,L111,LOG!$D$2:$D$2001,"BOOKED")>0,1,IF(AND(COUNTIFS(LOG!$C$2:$C$2001,C111,LOG!$L$2:$L$2001,L111,LOG!$D$2:$D$2001,"SENT_LINK")>0,COUNTIFS(LOG!$C$2:$C$2001,C111,LOG!$D$2:$D$2001,"SELF_BOOKED",LOG!$G$2:$G$2001,">"&G111)>0),1,0)))
A112: 46309.442 | B112: Lead | C112: 9000004791 | D112: SELF_BOOKED | E112: R512 | F112: calendly confirmation | G112: =IF(A112="","",IF(A112>=1,A112,IF(MAX($G$2:G111)=0,INT(SETTINGS!$B$4)+A112,INT(MAX($G$2:G111))+A112+IF(A112<MOD(MAX($G$2:G111),1),1,0)))) -> 46309.442 | H112: =IF(D112="","",IF(IFERROR(VLOOKUP(D112,LISTS!$A$2:$E$10,3,FALSE),0)=0,0,IF(IFERROR(COUNTIFS($C$2:C111,C112,$H$2:H111,1,$G$2:G111,">="&(G112-15/1440)),0)>0,0,1))) -> 0 | I112: =IF(H112=1,C112&"|"&COUNTIFS($C$2:C112,C112,$H$2:H112,1),"") | J112: =IF(D112="","",IF(A112="","Missing time",IF(AND(D112="NO_SLOTS",E112=""),"Write the request ID in column E",IF(C112="","Missing phone",IF(COUNTIF(DESK!$F$2:$F$601,C112)=0,"Phone not found: copy it from your list",IF(E112="","OK",IF(COUNTIFS(DESK!$F$2:$F$601,C112,DESK!$AW$2:$AW$601,E112)=0,"Request ID is not one of theirs: copy it from column D",IF(COUNTIFS(DESK!$F$2:$F$601,C112,DESK!$AW$2:$AW$601,E112,DESK!$L$2:$L$601,1)=0,"That ID is a removed duplicate: use the ID on your list","OK")))))))) -> OK | K112: =IF(E112="","",IFERROR(INDEX(DESK!$B$2:$B$601,MATCH(E112,DESK!$AW$2:$AW$601,0)),"")) -> Partner 000 | L112: =IF(OR(D112="",C112=""),"",COUNTIFS($C$2:C112,C112,$H$2:H112,1)) -> 1 | M112: =IF(H112<>1,"",IF(COUNTIFS(LOG!$C$2:$C$2001,C112,LOG!$L$2:$L$2001,L112,LOG!$D$2:$D$2001,"BOOKED")>0,1,IF(AND(COUNTIFS(LOG!$C$2:$C$2001,C112,LOG!$L$2:$L$2001,L112,LOG!$D$2:$D$2001,"SENT_LINK")>0,COUNTIFS(LOG!$C$2:$C$2001,C112,LOG!$D$2:$D$2001,"SELF_BOOKED",LOG!$G$2:$G$2001,">"&G112)>0),1,0)))
A113: 46309.443 | B113: Lead | C113: 9000002152 | D113: SELF_BOOKED | E113: R011 | F113: calendly confirmation | G113: =IF(A113="","",IF(A113>=1,A113,IF(MAX($G$2:G112)=0,INT(SETTINGS!$B$4)+A113,INT(MAX($G$2:G112))+A113+IF(A113<MOD(MAX($G$2:G112),1),1,0)))) -> 46309.443 | H113: =IF(D113="","",IF(IFERROR(VLOOKUP(D113,LISTS!$A$2:$E$10,3,FALSE),0)=0,0,IF(IFERROR(COUNTIFS($C$2:C112,C113,$H$2:H112,1,$G$2:G112,">="&(G113-15/1440)),0)>0,0,1))) -> 0 | I113: =IF(H113=1,C113&"|"&COUNTIFS($C$2:C113,C113,$H$2:H113,1),"") | J113: =IF(D113="","",IF(A113="","Missing time",IF(AND(D113="NO_SLOTS",E113=""),"Write the request ID in column E",IF(C113="","Missing phone",IF(COUNTIF(DESK!$F$2:$F$601,C113)=0,"Phone not found: copy it from your list",IF(E113="","OK",IF(COUNTIFS(DESK!$F$2:$F$601,C113,DESK!$AW$2:$AW$601,E113)=0,"Request ID is not one of theirs: copy it from column D",IF(COUNTIFS(DESK!$F$2:$F$601,C113,DESK!$AW$2:$AW$601,E113,DESK!$L$2:$L$601,1)=0,"That ID is a removed duplicate: use the ID on your list","OK")))))))) -> OK | K113: =IF(E113="","",IFERROR(INDEX(DESK!$B$2:$B$601,MATCH(E113,DESK!$AW$2:$AW$601,0)),"")) -> Partner 040 | L113: =IF(OR(D113="",C113=""),"",COUNTIFS($C$2:C113,C113,$H$2:H113,1)) -> 0 | M113: =IF(H113<>1,"",IF(COUNTIFS(LOG!$C$2:$C$2001,C113,LOG!$L$2:$L$2001,L113,LOG!$D$2:$D$2001,"BOOKED")>0,1,IF(AND(COUNTIFS(LOG!$C$2:$C$2001,C113,LOG!$L$2:$L$2001,L113,LOG!$D$2:$D$2001,"SENT_LINK")>0,COUNTIFS(LOG!$C$2:$C$2001,C113,LOG!$D$2:$D$2001,"SELF_BOOKED",LOG!$G$2:$G$2001,">"&G113)>0),1,0)))
A114: 46309.452 | B114: Lead | C114: 9000001736 | D114: SELF_BOOKED | E114: R384 | F114: calendly confirmation | G114: =IF(A114="","",IF(A114>=1,A114,IF(MAX($G$2:G113)=0,INT(SETTINGS!$B$4)+A114,INT(MAX($G$2:G113))+A114+IF(A114<MOD(MAX($G$2:G113),1),1,0)))) -> 46309.452 | H114: =IF(D114="","",IF(IFERROR(VLOOKUP(D114,LISTS!$A$2:$E$10,3,FALSE),0)=0,0,IF(IFERROR(COUNTIFS($C$2:C113,C114,$H$2:H113,1,$G$2:G113,">="&(G114-15/1440)),0)>0,0,1))) -> 0 | I114: =IF(H114=1,C114&"|"&COUNTIFS($C$2:C114,C114,$H$2:H114,1),"") | J114: =IF(D114="","",IF(A114="","Missing time",IF(AND(D114="NO_SLOTS",E114=""),"Write the request ID in column E",IF(C114="","Missing phone",IF(COUNTIF(DESK!$F$2:$F$601,C114)=0,"Phone not found: copy it from your list",IF(E114="","OK",IF(COUNTIFS(DESK!$F$2:$F$601,C114,DESK!$AW$2:$AW$601,E114)=0,"Request ID is not one of theirs: copy it from column D",IF(COUNTIFS(DESK!$F$2:$F$601,C114,DESK!$AW$2:$AW$601,E114,DESK!$L$2:$L$601,1)=0,"That ID is a removed duplicate: use the ID on your list","OK")))))))) -> OK | K114: =IF(E114="","",IFERROR(INDEX(DESK!$B$2:$B$601,MATCH(E114,DESK!$AW$2:$AW$601,0)),"")) -> Partner 016 | L114: =IF(OR(D114="",C114=""),"",COUNTIFS($C$2:C114,C114,$H$2:H114,1)) -> 0 | M114: =IF(H114<>1,"",IF(COUNTIFS(LOG!$C$2:$C$2001,C114,LOG!$L$2:$L$2001,L114,LOG!$D$2:$D$2001,"BOOKED")>0,1,IF(AND(COUNTIFS(LOG!$C$2:$C$2001,C114,LOG!$L$2:$L$2001,L114,LOG!$D$2:$D$2001,"SENT_LINK")>0,COUNTIFS(LOG!$C$2:$C$2001,C114,LOG!$D$2:$D$2001,"SELF_BOOKED",LOG!$G$2:$G$2001,">"&G114)>0),1,0)))
A115: 46309.463 | B115: Ram | C115: 9000002958 | D115: NO_ANSWER | G115: =IF(A115="","",IF(A115>=1,A115,IF(MAX($G$2:G114)=0,INT(SETTINGS!$B$4)+A115,INT(MAX($G$2:G114))+A115+IF(A115<MOD(MAX($G$2:G114),1),1,0)))) -> 46309.463 | H115: =IF(D115="","",IF(IFERROR(VLOOKUP(D115,LISTS!$A$2:$E$10,3,FALSE),0)=0,0,IF(IFERROR(COUNTIFS($C$2:C114,C115,$H$2:H114,1,$G$2:G114,">="&(G115-15/1440)),0)>0,0,1))) -> 1 | I115: =IF(H115=1,C115&"|"&COUNTIFS($C$2:C115,C115,$H$2:H115,1),"") -> 9000002958|1 | J115: =IF(D115="","",IF(A115="","Missing time",IF(AND(D115="NO_SLOTS",E115=""),"Write the request ID in column E",IF(C115="","Missing phone",IF(COUNTIF(DESK!$F$2:$F$601,C115)=0,"Phone not found: copy it from your list",IF(E115="","OK",IF(COUNTIFS(DESK!$F$2:$F$601,C115,DESK!$AW$2:$AW$601,E115)=0,"Request ID is not one of theirs: copy it from column D",IF(COUNTIFS(DESK!$F$2:$F$601,C115,DESK!$AW$2:$AW$601,E115,DESK!$L$2:$L$601,1)=0,"That ID is a removed duplicate: use the ID on your list","OK")))))))) -> OK | K115: =IF(E115="","",IFERROR(INDEX(DESK!$B$2:$B$601,MATCH(E115,DESK!$AW$2:$AW$601,0)),"")) | L115: =IF(OR(D115="",C115=""),"",COUNTIFS($C$2:C115,C115,$H$2:H115,1)) -> 1 | M115: =IF(H115<>1,"",IF(COUNTIFS(LOG!$C$2:$C$2001,C115,LOG!$L$2:$L$2001,L115,LOG!$D$2:$D$2001,"BOOKED")>0,1,IF(AND(COUNTIFS(LOG!$C$2:$C$2001,C115,LOG!$L$2:$L$2001,L115,LOG!$D$2:$D$2001,"SENT_LINK")>0,COUNTIFS(LOG!$C$2:$C$2001,C115,LOG!$D$2:$D$2001,"SELF_BOOKED",LOG!$G$2:$G$2001,">"&G115)>0),1,0))) -> 0
A116: 46309.468 | B116: Ram | C116: 9000001177 | D116: CALL_BACK | F116: busy | G116: =IF(A116="","",IF(A116>=1,A116,IF(MAX($G$2:G115)=0,INT(SETTINGS!$B$4)+A116,INT(MAX($G$2:G115))+A116+IF(A116<MOD(MAX($G$2:G115),1),1,0)))) -> 46309.468 | H116: =IF(D116="","",IF(IFERROR(VLOOKUP(D116,LISTS!$A$2:$E$10,3,FALSE),0)=0,0,IF(IFERROR(COUNTIFS($C$2:C115,C116,$H$2:H115,1,$G$2:G115,">="&(G116-15/1440)),0)>0,0,1))) -> 1 | I116: =IF(H116=1,C116&"|"&COUNTIFS($C$2:C116,C116,$H$2:H116,1),"") -> 9000001177|1 | J116: =IF(D116="","",IF(A116="","Missing time",IF(AND(D116="NO_SLOTS",E116=""),"Write the request ID in column E",IF(C116="","Missing phone",IF(COUNTIF(DESK!$F$2:$F$601,C116)=0,"Phone not found: copy it from your list",IF(E116="","OK",IF(COUNTIFS(DESK!$F$2:$F$601,C116,DESK!$AW$2:$AW$601,E116)=0,"Request ID is not one of theirs: copy it from column D",IF(COUNTIFS(DESK!$F$2:$F$601,C116,DESK!$AW$2:$AW$601,E116,DESK!$L$2:$L$601,1)=0,"That ID is a removed duplicate: use the ID on your list","OK")))))))) -> OK | K116: =IF(E116="","",IFERROR(INDEX(DESK!$B$2:$B$601,MATCH(E116,DESK!$AW$2:$AW$601,0)),"")) | L116: =IF(OR(D116="",C116=""),"",COUNTIFS($C$2:C116,C116,$H$2:H116,1)) -> 1 | M116: =IF(H116<>1,"",IF(COUNTIFS(LOG!$C$2:$C$2001,C116,LOG!$L$2:$L$2001,L116,LOG!$D$2:$D$2001,"BOOKED")>0,1,IF(AND(COUNTIFS(LOG!$C$2:$C$2001,C116,LOG!$L$2:$L$2001,L116,LOG!$D$2:$D$2001,"SENT_LINK")>0,COUNTIFS(LOG!$C$2:$C$2001,C116,LOG!$D$2:$D$2001,"SELF_BOOKED",LOG!$G$2:$G$2001,">"&G116)>0),1,0))) -> 0
A117: 46309.471 | B117: Ram | C117: 9000001008 | D117: SENT_LINK | F117: sent booking link | G117: =IF(A117="","",IF(A117>=1,A117,IF(MAX($G$2:G116)=0,INT(SETTINGS!$B$4)+A117,INT(MAX($G$2:G116))+A117+IF(A117<MOD(MAX($G$2:G116),1),1,0)))) -> 46309.471 | H117: =IF(D117="","",IF(IFERROR(VLOOKUP(D117,LISTS!$A$2:$E$10,3,FALSE),0)=0,0,IF(IFERROR(COUNTIFS($C$2:C116,C117,$H$2:H116,1,$G$2:G116,">="&(G117-15/1440)),0)>0,0,1))) -> 1 | I117: =IF(H117=1,C117&"|"&COUNTIFS($C$2:C117,C117,$H$2:H117,1),"") -> 9000001008|1 | J117: =IF(D117="","",IF(A117="","Missing time",IF(AND(D117="NO_SLOTS",E117=""),"Write the request ID in column E",IF(C117="","Missing phone",IF(COUNTIF(DESK!$F$2:$F$601,C117)=0,"Phone not found: copy it from your list",IF(E117="","OK",IF(COUNTIFS(DESK!$F$2:$F$601,C117,DESK!$AW$2:$AW$601,E117)=0,"Request ID is not one of theirs: copy it from column D",IF(COUNTIFS(DESK!$F$2:$F$601,C117,DESK!$AW$2:$AW$601,E117,DESK!$L$2:$L$601,1)=0,"That ID is a removed duplicate: use the ID on your list","OK")))))))) -> OK | K117: =IF(E117="","",IFERROR(INDEX(DESK!$B$2:$B$601,MATCH(E117,DESK!$AW$2:$AW$601,0)),"")) | L117: =IF(OR(D117="",C117=""),"",COUNTIFS($C$2:C117,C117,$H$2:H117,1)) -> 1 | M117: =IF(H117<>1,"",IF(COUNTIFS(LOG!$C$2:$C$2001,C117,LOG!$L$2:$L$2001,L117,LOG!$D$2:$D$2001,"BOOKED")>0,1,IF(AND(COUNTIFS(LOG!$C$2:$C$2001,C117,LOG!$L$2:$L$2001,L117,LOG!$D$2:$D$2001,"SENT_LINK")>0,COUNTIFS(LOG!$C$2:$C$2001,C117,LOG!$D$2:$D$2001,"SELF_BOOKED",LOG!$G$2:$G$2001,">"&G117)>0),1,0))) -> 1
A118: 46309.472 | B118: Ram | C118: 9000001008 | D118: BOOKED | E118: R090 | G118: =IF(A118="","",IF(A118>=1,A118,IF(MAX($G$2:G117)=0,INT(SETTINGS!$B$4)+A118,INT(MAX($G$2:G117))+A118+IF(A118<MOD(MAX($G$2:G117),1),1,0)))) -> 46309.472 | H118: =IF(D118="","",IF(IFERROR(VLOOKUP(D118,LISTS!$A$2:$E$10,3,FALSE),0)=0,0,IF(IFERROR(COUNTIFS($C$2:C117,C118,$H$2:H117,1,$G$2:G117,">="&(G118-15/1440)),0)>0,0,1))) -> 0 | I118: =IF(H118=1,C118&"|"&COUNTIFS($C$2:C118,C118,$H$2:H118,1),"") | J118: =IF(D118="","",IF(A118="","Missing time",IF(AND(D118="NO_SLOTS",E118=""),"Write the request ID in column E",IF(C118="","Missing phone",IF(COUNTIF(DESK!$F$2:$F$601,C118)=0,"Phone not found: copy it from your list",IF(E118="","OK",IF(COUNTIFS(DESK!$F$2:$F$601,C118,DESK!$AW$2:$AW$601,E118)=0,"Request ID is not one of theirs: copy it from column D",IF(COUNTIFS(DESK!$F$2:$F$601,C118,DESK!$AW$2:$AW$601,E118,DESK!$L$2:$L$601,1)=0,"That ID is a removed duplicate: use the ID on your list","OK")))))))) -> OK | K118: =IF(E118="","",IFERROR(INDEX(DESK!$B$2:$B$601,MATCH(E118,DESK!$AW$2:$AW$601,0)),"")) -> Partner 004 | L118: =IF(OR(D118="",C118=""),"",COUNTIFS($C$2:C118,C118,$H$2:H118,1)) -> 1 | M118: =IF(H118<>1,"",IF(COUNTIFS(LOG!$C$2:$C$2001,C118,LOG!$L$2:$L$2001,L118,LOG!$D$2:$D$2001,"BOOKED")>0,1,IF(AND(COUNTIFS(LOG!$C$2:$C$2001,C118,LOG!$L$2:$L$2001,L118,LOG!$D$2:$D$2001,"SENT_LINK")>0,COUNTIFS(LOG!$C$2:$C$2001,C118,LOG!$D$2:$D$2001,"SELF_BOOKED",LOG!$G$2:$G$2001,">"&G118)>0),1,0)))
A119: 46309.475 | B119: Ram | C119: 9000004271 | D119: CALL_BACK | F119: busy | G119: =IF(A119="","",IF(A119>=1,A119,IF(MAX($G$2:G118)=0,INT(SETTINGS!$B$4)+A119,INT(MAX($G$2:G118))+A119+IF(A119<MOD(MAX($G$2:G118),1),1,0)))) -> 46309.475 | H119: =IF(D119="","",IF(IFERROR(VLOOKUP(D119,LISTS!$A$2:$E$10,3,FALSE),0)=0,0,IF(IFERROR(COUNTIFS($C$2:C118,C119,$H$2:H118,1,$G$2:G118,">="&(G119-15/1440)),0)>0,0,1))) -> 1 | I119: =IF(H119=1,C119&"|"&COUNTIFS($C$2:C119,C119,$H$2:H119,1),"") -> 9000004271|1 | J119: =IF(D119="","",IF(A119="","Missing time",IF(AND(D119="NO_SLOTS",E119=""),"Write the request ID in column E",IF(C119="","Missing phone",IF(COUNTIF(DESK!$F$2:$F$601,C119)=0,"Phone not found: copy it from your list",IF(E119="","OK",IF(COUNTIFS(DESK!$F$2:$F$601,C119,DESK!$AW$2:$AW$601,E119)=0,"Request ID is not one of theirs: copy it from column D",IF(COUNTIFS(DESK!$F$2:$F$601,C119,DESK!$AW$2:$AW$601,E119,DESK!$L$2:$L$601,1)=0,"That ID is a removed duplicate: use the ID on your list","OK")))))))) -> OK | K119: =IF(E119="","",IFERROR(INDEX(DESK!$B$2:$B$601,MATCH(E119,DESK!$AW$2:$AW$601,0)),"")) | L119: =IF(OR(D119="",C119=""),"",COUNTIFS($C$2:C119,C119,$H$2:H119,1)) -> 1 | M119: =IF(H119<>1,"",IF(COUNTIFS(LOG!$C$2:$C$2001,C119,LOG!$L$2:$L$2001,L119,LOG!$D$2:$D$2001,"BOOKED")>0,1,IF(AND(COUNTIFS(LOG!$C$2:$C$2001,C119,LOG!$L$2:$L$2001,L119,LOG!$D$2:$D$2001,"SENT_LINK")>0,COUNTIFS(LOG!$C$2:$C$2001,C119,LOG!$D$2:$D$2001,"SELF_BOOKED",LOG!$G$2:$G$2001,">"&G119)>0),1,0))) -> 0
A120: 46309.46 | B120: Lead | C120: 9000003491 | D120: SELF_BOOKED | E120: R460 | F120: calendly confirmation | G120: =IF(A120="","",IF(A120>=1,A120,IF(MAX($G$2:G119)=0,INT(SETTINGS!$B$4)+A120,INT(MAX($G$2:G119))+A120+IF(A120<MOD(MAX($G$2:G119),1),1,0)))) -> 46309.46 | H120: =IF(D120="","",IF(IFERROR(VLOOKUP(D120,LISTS!$A$2:$E$10,3,FALSE),0)=0,0,IF(IFERROR(COUNTIFS($C$2:C119,C120,$H$2:H119,1,$G$2:G119,">="&(G120-15/1440)),0)>0,0,1))) -> 0 | I120: =IF(H120=1,C120&"|"&COUNTIFS($C$2:C120,C120,$H$2:H120,1),"") | J120: =IF(D120="","",IF(A120="","Missing time",IF(AND(D120="NO_SLOTS",E120=""),"Write the request ID in column E",IF(C120="","Missing phone",IF(COUNTIF(DESK!$F$2:$F$601,C120)=0,"Phone not found: copy it from your list",IF(E120="","OK",IF(COUNTIFS(DESK!$F$2:$F$601,C120,DESK!$AW$2:$AW$601,E120)=0,"Request ID is not one of theirs: copy it from column D",IF(COUNTIFS(DESK!$F$2:$F$601,C120,DESK!$AW$2:$AW$601,E120,DESK!$L$2:$L$601,1)=0,"That ID is a removed duplicate: use the ID on your list","OK")))))))) -> OK | K120: =IF(E120="","",IFERROR(INDEX(DESK!$B$2:$B$601,MATCH(E120,DESK!$AW$2:$AW$601,0)),"")) -> Partner 005 | L120: =IF(OR(D120="",C120=""),"",COUNTIFS($C$2:C120,C120,$H$2:H120,1)) -> 0 | M120: =IF(H120<>1,"",IF(COUNTIFS(LOG!$C$2:$C$2001,C120,LOG!$L$2:$L$2001,L120,LOG!$D$2:$D$2001,"BOOKED")>0,1,IF(AND(COUNTIFS(LOG!$C$2:$C$2001,C120,LOG!$L$2:$L$2001,L120,LOG!$D$2:$D$2001,"SENT_LINK")>0,COUNTIFS(LOG!$C$2:$C$2001,C120,LOG!$D$2:$D$2001,"SELF_BOOKED",LOG!$G$2:$G$2001,">"&G120)>0),1,0)))
A121: 46309.46 | B121: Lead | C121: 9000000852 | D121: SELF_BOOKED | E121: R501 | F121: calendly confirmation | G121: =IF(A121="","",IF(A121>=1,A121,IF(MAX($G$2:G120)=0,INT(SETTINGS!$B$4)+A121,INT(MAX($G$2:G120))+A121+IF(A121<MOD(MAX($G$2:G120),1),1,0)))) -> 46309.46 | H121: =IF(D121="","",IF(IFERROR(VLOOKUP(D121,LISTS!$A$2:$E$10,3,FALSE),0)=0,0,IF(IFERROR(COUNTIFS($C$2:C120,C121,$H$2:H120,1,$G$2:G120,">="&(G121-15/1440)),0)>0,0,1))) -> 0 | I121: =IF(H121=1,C121&"|"&COUNTIFS($C$2:C121,C121,$H$2:H121,1),"") | J121: =IF(D121="","",IF(A121="","Missing time",IF(AND(D121="NO_SLOTS",E121=""),"Write the request ID in column E",IF(C121="","Missing phone",IF(COUNTIF(DESK!$F$2:$F$601,C121)=0,"Phone not found: copy it from your list",IF(E121="","OK",IF(COUNTIFS(DESK!$F$2:$F$601,C121,DESK!$AW$2:$AW$601,E121)=0,"Request ID is not one of theirs: copy it from column D",IF(COUNTIFS(DESK!$F$2:$F$601,C121,DESK!$AW$2:$AW$601,E121,DESK!$L$2:$L$601,1)=0,"That ID is a removed duplicate: use the ID on your list","OK")))))))) -> OK | K121: =IF(E121="","",IFERROR(INDEX(DESK!$B$2:$B$601,MATCH(E121,DESK!$AW$2:$AW$601,0)),"")) -> Partner 001 | L121: =IF(OR(D121="",C121=""),"",COUNTIFS($C$2:C121,C121,$H$2:H121,1)) -> 1 | M121: =IF(H121<>1,"",IF(COUNTIFS(LOG!$C$2:$C$2001,C121,LOG!$L$2:$L$2001,L121,LOG!$D$2:$D$2001,"BOOKED")>0,1,IF(AND(COUNTIFS(LOG!$C$2:$C$2001,C121,LOG!$L$2:$L$2001,L121,LOG!$D$2:$D$2001,"SENT_LINK")>0,COUNTIFS(LOG!$C$2:$C$2001,C121,LOG!$D$2:$D$2001,"SELF_BOOKED",LOG!$G$2:$G$2001,">"&G121)>0),1,0)))
A122: 46309.461 | B122: Lead | C122: 9000000683 | D122: SELF_BOOKED | E122: R024 | F122: calendly confirmation | G122: =IF(A122="","",IF(A122>=1,A122,IF(MAX($G$2:G121)=0,INT(SETTINGS!$B$4)+A122,INT(MAX($G$2:G121))+A122+IF(A122<MOD(MAX($G$2:G121),1),1,0)))) -> 46309.461 | H122: =IF(D122="","",IF(IFERROR(VLOOKUP(D122,LISTS!$A$2:$E$10,3,FALSE),0)=0,0,IF(IFERROR(COUNTIFS($C$2:C121,C122,$H$2:H121,1,$G$2:G121,">="&(G122-15/1440)),0)>0,0,1))) -> 0 | I122: =IF(H122=1,C122&"|"&COUNTIFS($C$2:C122,C122,$H$2:H122,1),"") | J122: =IF(D122="","",IF(A122="","Missing time",IF(AND(D122="NO_SLOTS",E122=""),"Write the request ID in column E",IF(C122="","Missing phone",IF(COUNTIF(DESK!$F$2:$F$601,C122)=0,"Phone not found: copy it from your list",IF(E122="","OK",IF(COUNTIFS(DESK!$F$2:$F$601,C122,DESK!$AW$2:$AW$601,E122)=0,"Request ID is not one of theirs: copy it from column D",IF(COUNTIFS(DESK!$F$2:$F$601,C122,DESK!$AW$2:$AW$601,E122,DESK!$L$2:$L$601,1)=0,"That ID is a removed duplicate: use the ID on your list","OK")))))))) -> OK | K122: =IF(E122="","",IFERROR(INDEX(DESK!$B$2:$B$601,MATCH(E122,DESK!$AW$2:$AW$601,0)),"")) -> Partner 074 | L122: =IF(OR(D122="",C122=""),"",COUNTIFS($C$2:C122,C122,$H$2:H122,1)) -> 0 | M122: =IF(H122<>1,"",IF(COUNTIFS(LOG!$C$2:$C$2001,C122,LOG!$L$2:$L$2001,L122,LOG!$D$2:$D$2001,"BOOKED")>0,1,IF(AND(COUNTIFS(LOG!$C$2:$C$2001,C122,LOG!$L$2:$L$2001,L122,LOG!$D$2:$D$2001,"SENT_LINK")>0,COUNTIFS(LOG!$C$2:$C$2001,C122,LOG!$D$2:$D$2001,"SELF_BOOKED",LOG!$G$2:$G$2001,">"&G122)>0),1,0)))
A123: 46309.462 | B123: Lead | C123: 9000001697 | D123: SELF_BOOKED | E123: R327 | F123: calendly confirmation | G123: =IF(A123="","",IF(A123>=1,A123,IF(MAX($G$2:G122)=0,INT(SETTINGS!$B$4)+A123,INT(MAX($G$2:G122))+A123+IF(A123<MOD(MAX($G$2:G122),1),1,0)))) -> 46309.462 | H123: =IF(D123="","",IF(IFERROR(VLOOKUP(D123,LISTS!$A$2:$E$10,3,FALSE),0)=0,0,IF(IFERROR(COUNTIFS($C$2:C122,C123,$H$2:H122,1,$G$2:G122,">="&(G123-15/1440)),0)>0,0,1))) -> 0 | I123: =IF(H123=1,C123&"|"&COUNTIFS($C$2:C123,C123,$H$2:H123,1),"") | J123: =IF(D123="","",IF(A123="","Missing time",IF(AND(D123="NO_SLOTS",E123=""),"Write the request ID in column E",IF(C123="","Missing phone",IF(COUNTIF(DESK!$F$2:$F$601,C123)=0,"Phone not found: copy it from your list",IF(E123="","OK",IF(COUNTIFS(DESK!$F$2:$F$601,C123,DESK!$AW$2:$AW$601,E123)=0,"Request ID is not one of theirs: copy it from column D",IF(COUNTIFS(DESK!$F$2:$F$601,C123,DESK!$AW$2:$AW$601,E123,DESK!$L$2:$L$601,1)=0,"That ID is a removed duplicate: use the ID on your list","OK")))))))) -> OK | K123: =IF(E123="","",IFERROR(INDEX(DESK!$B$2:$B$601,MATCH(E123,DESK!$AW$2:$AW$601,0)),"")) -> Partner 000 | L123: =IF(OR(D123="",C123=""),"",COUNTIFS($C$2:C123,C123,$H$2:H123,1)) -> 0 | M123: =IF(H123<>1,"",IF(COUNTIFS(LOG!$C$2:$C$2001,C123,LOG!$L$2:$L$2001,L123,LOG!$D$2:$D$2001,"BOOKED")>0,1,IF(AND(COUNTIFS(LOG!$C$2:$C$2001,C123,LOG!$L$2:$L$2001,L123,LOG!$D$2:$D$2001,"SENT_LINK")>0,COUNTIFS(LOG!$C$2:$C$2001,C123,LOG!$D$2:$D$2001,"SELF_BOOKED",LOG!$G$2:$G$2001,">"&G123)>0),1,0)))
A124: 46309.463 | B124: Lead | C124: 9000001164 | D124: SELF_BOOKED | E124: R381 | F124: calendly confirmation | G124: =IF(A124="","",IF(A124>=1,A124,IF(MAX($G$2:G123)=0,INT(SETTINGS!$B$4)+A124,INT(MAX($G$2:G123))+A124+IF(A124<MOD(MAX($G$2:G123),1),1,0)))) -> 46309.463 | H124: =IF(D124="","",IF(IFERROR(VLOOKUP(D124,LISTS!$A$2:$E$10,3,FALSE),0)=0,0,IF(IFERROR(COUNTIFS($C$2:C123,C124,$H$2:H123,1,$G$2:G123,">="&(G124-15/1440)),0)>0,0,1))) -> 0 | I124: =IF(H124=1,C124&"|"&COUNTIFS($C$2:C124,C124,$H$2:H124,1),"") | J124: =IF(D124="","",IF(A124="","Missing time",IF(AND(D124="NO_SLOTS",E124=""),"Write the request ID in column E",IF(C124="","Missing phone",IF(COUNTIF(DESK!$F$2:$F$601,C124)=0,"Phone not found: copy it from your list",IF(E124="","OK",IF(COUNTIFS(DESK!$F$2:$F$601,C124,DESK!$AW$2:$AW$601,E124)=0,"Request ID is not one of theirs: copy it from column D",IF(COUNTIFS(DESK!$F$2:$F$601,C124,DESK!$AW$2:$AW$601,E124,DESK!$L$2:$L$601,1)=0,"That ID is a removed duplicate: use the ID on your list","OK")))))))) -> OK | K124: =IF(E124="","",IFERROR(INDEX(DESK!$B$2:$B$601,MATCH(E124,DESK!$AW$2:$AW$601,0)),"")) -> Partner 001 | L124: =IF(OR(D124="",C124=""),"",COUNTIFS($C$2:C124,C124,$H$2:H124,1)) -> 0 | M124: =IF(H124<>1,"",IF(COUNTIFS(LOG!$C$2:$C$2001,C124,LOG!$L$2:$L$2001,L124,LOG!$D$2:$D$2001,"BOOKED")>0,1,IF(AND(COUNTIFS(LOG!$C$2:$C$2001,C124,LOG!$L$2:$L$2001,L124,LOG!$D$2:$D$2001,"SENT_LINK")>0,COUNTIFS(LOG!$C$2:$C$2001,C124,LOG!$D$2:$D$2001,"SELF_BOOKED",LOG!$G$2:$G$2001,">"&G124)>0),1,0)))
A125: 46309.465 | B125: Lead | C125: 9000001008 | D125: SELF_BOOKED | E125: R014 | F125: calendly confirmation | G125: =IF(A125="","",IF(A125>=1,A125,IF(MAX($G$2:G124)=0,INT(SETTINGS!$B$4)+A125,INT(MAX($G$2:G124))+A125+IF(A125<MOD(MAX($G$2:G124),1),1,0)))) -> 46309.465 | H125: =IF(D125="","",IF(IFERROR(VLOOKUP(D125,LISTS!$A$2:$E$10,3,FALSE),0)=0,0,IF(IFERROR(COUNTIFS($C$2:C124,C125,$H$2:H124,1,$G$2:G124,">="&(G125-15/1440)),0)>0,0,1))) -> 0 | I125: =IF(H125=1,C125&"|"&COUNTIFS($C$2:C125,C125,$H$2:H125,1),"") | J125: =IF(D125="","",IF(A125="","Missing time",IF(AND(D125="NO_SLOTS",E125=""),"Write the request ID in column E",IF(C125="","Missing phone",IF(COUNTIF(DESK!$F$2:$F$601,C125)=0,"Phone not found: copy it from your list",IF(E125="","OK",IF(COUNTIFS(DESK!$F$2:$F$601,C125,DESK!$AW$2:$AW$601,E125)=0,"Request ID is not one of theirs: copy it from column D",IF(COUNTIFS(DESK!$F$2:$F$601,C125,DESK!$AW$2:$AW$601,E125,DESK!$L$2:$L$601,1)=0,"That ID is a removed duplicate: use the ID on your list","OK")))))))) -> OK | K125: =IF(E125="","",IFERROR(INDEX(DESK!$B$2:$B$601,MATCH(E125,DESK!$AW$2:$AW$601,0)),"")) -> Partner 092 | L125: =IF(OR(D125="",C125=""),"",COUNTIFS($C$2:C125,C125,$H$2:H125,1)) -> 1 | M125: =IF(H125<>1,"",IF(COUNTIFS(LOG!$C$2:$C$2001,C125,LOG!$L$2:$L$2001,L125,LOG!$D$2:$D$2001,"BOOKED")>0,1,IF(AND(COUNTIFS(LOG!$C$2:$C$2001,C125,LOG!$L$2:$L$2001,L125,LOG!$D$2:$D$2001,"SENT_LINK")>0,COUNTIFS(LOG!$C$2:$C$2001,C125,LOG!$D$2:$D$2001,"SELF_BOOKED",LOG!$G$2:$G$2001,">"&G125)>0),1,0)))
A126: 46309.468 | B126: Lead | C126: 9000004115 | D126: SELF_BOOKED | E126: R035 | F126: calendly confirmation | G126: =IF(A126="","",IF(A126>=1,A126,IF(MAX($G$2:G125)=0,INT(SETTINGS!$B$4)+A126,INT(MAX($G$2:G125))+A126+IF(A126<MOD(MAX($G$2:G125),1),1,0)))) -> 46309.468 | H126: =IF(D126="","",IF(IFERROR(VLOOKUP(D126,LISTS!$A$2:$E$10,3,FALSE),0)=0,0,IF(IFERROR(COUNTIFS($C$2:C125,C126,$H$2:H125,1,$G$2:G125,">="&(G126-15/1440)),0)>0,0,1))) -> 0 | I126: =IF(H126=1,C126&"|"&COUNTIFS($C$2:C126,C126,$H$2:H126,1),"") | J126: =IF(D126="","",IF(A126="","Missing time",IF(AND(D126="NO_SLOTS",E126=""),"Write the request ID in column E",IF(C126="","Missing phone",IF(COUNTIF(DESK!$F$2:$F$601,C126)=0,"Phone not found: copy it from your list",IF(E126="","OK",IF(COUNTIFS(DESK!$F$2:$F$601,C126,DESK!$AW$2:$AW$601,E126)=0,"Request ID is not one of theirs: copy it from column D",IF(COUNTIFS(DESK!$F$2:$F$601,C126,DESK!$AW$2:$AW$601,E126,DESK!$L$2:$L$601,1)=0,"That ID is a removed duplicate: use the ID on your list","OK")))))))) -> OK | K126: =IF(E126="","",IFERROR(INDEX(DESK!$B$2:$B$601,MATCH(E126,DESK!$AW$2:$AW$601,0)),"")) -> Partner 000 | L126: =IF(OR(D126="",C126=""),"",COUNTIFS($C$2:C126,C126,$H$2:H126,1)) -> 0 | M126: =IF(H126<>1,"",IF(COUNTIFS(LOG!$C$2:$C$2001,C126,LOG!$L$2:$L$2001,L126,LOG!$D$2:$D$2001,"BOOKED")>0,1,IF(AND(COUNTIFS(LOG!$C$2:$C$2001,C126,LOG!$L$2:$L$2001,L126,LOG!$D$2:$D$2001,"SENT_LINK")>0,COUNTIFS(LOG!$C$2:$C$2001,C126,LOG!$D$2:$D$2001,"SELF_BOOKED",LOG!$G$2:$G$2001,">"&G126)>0),1,0)))
A127: 46309.483 | B127: Ram | C127: 9000000462 | D127: SENT_LINK | F127: sent booking link | G127: =IF(A127="","",IF(A127>=1,A127,IF(MAX($G$2:G126)=0,INT(SETTINGS!$B$4)+A127,INT(MAX($G$2:G126))+A127+IF(A127<MOD(MAX($G$2:G126),1),1,0)))) -> 46309.483 | H127: =IF(D127="","",IF(IFERROR(VLOOKUP(D127,LISTS!$A$2:$E$10,3,FALSE),0)=0,0,IF(IFERROR(COUNTIFS($C$2:C126,C127,$H$2:H126,1,$G$2:G126,">="&(G127-15/1440)),0)>0,0,1))) -> 1 | I127: =IF(H127=1,C127&"|"&COUNTIFS($C$2:C127,C127,$H$2:H127,1),"") -> 9000000462|1 | J127: =IF(D127="","",IF(A127="","Missing time",IF(AND(D127="NO_SLOTS",E127=""),"Write the request ID in column E",IF(C127="","Missing phone",IF(COUNTIF(DESK!$F$2:$F$601,C127)=0,"Phone not found: copy it from your list",IF(E127="","OK",IF(COUNTIFS(DESK!$F$2:$F$601,C127,DESK!$AW$2:$AW$601,E127)=0,"Request ID is not one of theirs: copy it from column D",IF(COUNTIFS(DESK!$F$2:$F$601,C127,DESK!$AW$2:$AW$601,E127,DESK!$L$2:$L$601,1)=0,"That ID is a removed duplicate: use the ID on your list","OK")))))))) -> OK | K127: =IF(E127="","",IFERROR(INDEX(DESK!$B$2:$B$601,MATCH(E127,DESK!$AW$2:$AW$601,0)),"")) | L127: =IF(OR(D127="",C127=""),"",COUNTIFS($C$2:C127,C127,$H$2:H127,1)) -> 1 | M127: =IF(H127<>1,"",IF(COUNTIFS(LOG!$C$2:$C$2001,C127,LOG!$L$2:$L$2001,L127,LOG!$D$2:$D$2001,"BOOKED")>0,1,IF(AND(COUNTIFS(LOG!$C$2:$C$2001,C127,LOG!$L$2:$L$2001,L127,LOG!$D$2:$D$2001,"SENT_LINK")>0,COUNTIFS(LOG!$C$2:$C$2001,C127,LOG!$D$2:$D$2001,"SELF_BOOKED",LOG!$G$2:$G$2001,">"&G127)>0),1,0))) -> 1
A128: 46309.487 | B128: Ram | C128: 9000004427 | D128: NO_ANSWER | G128: =IF(A128="","",IF(A128>=1,A128,IF(MAX($G$2:G127)=0,INT(SETTINGS!$B$4)+A128,INT(MAX($G$2:G127))+A128+IF(A128<MOD(MAX($G$2:G127),1),1,0)))) -> 46309.487 | H128: =IF(D128="","",IF(IFERROR(VLOOKUP(D128,LISTS!$A$2:$E$10,3,FALSE),0)=0,0,IF(IFERROR(COUNTIFS($C$2:C127,C128,$H$2:H127,1,$G$2:G127,">="&(G128-15/1440)),0)>0,0,1))) -> 1 | I128: =IF(H128=1,C128&"|"&COUNTIFS($C$2:C128,C128,$H$2:H128,1),"") -> 9000004427|1 | J128: =IF(D128="","",IF(A128="","Missing time",IF(AND(D128="NO_SLOTS",E128=""),"Write the request ID in column E",IF(C128="","Missing phone",IF(COUNTIF(DESK!$F$2:$F$601,C128)=0,"Phone not found: copy it from your list",IF(E128="","OK",IF(COUNTIFS(DESK!$F$2:$F$601,C128,DESK!$AW$2:$AW$601,E128)=0,"Request ID is not one of theirs: copy it from column D",IF(COUNTIFS(DESK!$F$2:$F$601,C128,DESK!$AW$2:$AW$601,E128,DESK!$L$2:$L$601,1)=0,"That ID is a removed duplicate: use the ID on your list","OK")))))))) -> OK | K128: =IF(E128="","",IFERROR(INDEX(DESK!$B$2:$B$601,MATCH(E128,DESK!$AW$2:$AW$601,0)),"")) | L128: =IF(OR(D128="",C128=""),"",COUNTIFS($C$2:C128,C128,$H$2:H128,1)) -> 1 | M128: =IF(H128<>1,"",IF(COUNTIFS(LOG!$C$2:$C$2001,C128,LOG!$L$2:$L$2001,L128,LOG!$D$2:$D$2001,"BOOKED")>0,1,IF(AND(COUNTIFS(LOG!$C$2:$C$2001,C128,LOG!$L$2:$L$2001,L128,LOG!$D$2:$D$2001,"SENT_LINK")>0,COUNTIFS(LOG!$C$2:$C$2001,C128,LOG!$D$2:$D$2001,"SELF_BOOKED",LOG!$G$2:$G$2001,">"&G128)>0),1,0))) -> 0
A129: 46309.492 | B129: Ram | C129: 9000003543 | D129: STOP | F129: asked to stop | G129: =IF(A129="","",IF(A129>=1,A129,IF(MAX($G$2:G128)=0,INT(SETTINGS!$B$4)+A129,INT(MAX($G$2:G128))+A129+IF(A129<MOD(MAX($G$2:G128),1),1,0)))) -> 46309.492 | H129: =IF(D129="","",IF(IFERROR(VLOOKUP(D129,LISTS!$A$2:$E$10,3,FALSE),0)=0,0,IF(IFERROR(COUNTIFS($C$2:C128,C129,$H$2:H128,1,$G$2:G128,">="&(G129-15/1440)),0)>0,0,1))) -> 1 | I129: =IF(H129=1,C129&"|"&COUNTIFS($C$2:C129,C129,$H$2:H129,1),"") -> 9000003543|1 | J129: =IF(D129="","",IF(A129="","Missing time",IF(AND(D129="NO_SLOTS",E129=""),"Write the request ID in column E",IF(C129="","Missing phone",IF(COUNTIF(DESK!$F$2:$F$601,C129)=0,"Phone not found: copy it from your list",IF(E129="","OK",IF(COUNTIFS(DESK!$F$2:$F$601,C129,DESK!$AW$2:$AW$601,E129)=0,"Request ID is not one of theirs: copy it from column D",IF(COUNTIFS(DESK!$F$2:$F$601,C129,DESK!$AW$2:$AW$601,E129,DESK!$L$2:$L$601,1)=0,"That ID is a removed duplicate: use the ID on your list","OK")))))))) -> OK | K129: =IF(E129="","",IFERROR(INDEX(DESK!$B$2:$B$601,MATCH(E129,DESK!$AW$2:$AW$601,0)),"")) | L129: =IF(OR(D129="",C129=""),"",COUNTIFS($C$2:C129,C129,$H$2:H129,1)) -> 1 | M129: =IF(H129<>1,"",IF(COUNTIFS(LOG!$C$2:$C$2001,C129,LOG!$L$2:$L$2001,L129,LOG!$D$2:$D$2001,"BOOKED")>0,1,IF(AND(COUNTIFS(LOG!$C$2:$C$2001,C129,LOG!$L$2:$L$2001,L129,LOG!$D$2:$D$2001,"SENT_LINK")>0,COUNTIFS(LOG!$C$2:$C$2001,C129,LOG!$D$2:$D$2001,"SELF_BOOKED",LOG!$G$2:$G$2001,">"&G129)>0),1,0))) -> 0
A130: 46309.496 | B130: Ram | C130: 9000003803 | D130: CALL_BACK | F130: busy | G130: =IF(A130="","",IF(A130>=1,A130,IF(MAX($G$2:G129)=0,INT(SETTINGS!$B$4)+A130,INT(MAX($G$2:G129))+A130+IF(A130<MOD(MAX($G$2:G129),1),1,0)))) -> 46309.496 | H130: =IF(D130="","",IF(IFERROR(VLOOKUP(D130,LISTS!$A$2:$E$10,3,FALSE),0)=0,0,IF(IFERROR(COUNTIFS($C$2:C129,C130,$H$2:H129,1,$G$2:G129,">="&(G130-15/1440)),0)>0,0,1))) -> 1 | I130: =IF(H130=1,C130&"|"&COUNTIFS($C$2:C130,C130,$H$2:H130,1),"") -> 9000003803|1 | J130: =IF(D130="","",IF(A130="","Missing time",IF(AND(D130="NO_SLOTS",E130=""),"Write the request ID in column E",IF(C130="","Missing phone",IF(COUNTIF(DESK!$F$2:$F$601,C130)=0,"Phone not found: copy it from your list",IF(E130="","OK",IF(COUNTIFS(DESK!$F$2:$F$601,C130,DESK!$AW$2:$AW$601,E130)=0,"Request ID is not one of theirs: copy it from column D",IF(COUNTIFS(DESK!$F$2:$F$601,C130,DESK!$AW$2:$AW$601,E130,DESK!$L$2:$L$601,1)=0,"That ID is a removed duplicate: use the ID on your list","OK")))))))) -> OK | K130: =IF(E130="","",IFERROR(INDEX(DESK!$B$2:$B$601,MATCH(E130,DESK!$AW$2:$AW$601,0)),"")) | L130: =IF(OR(D130="",C130=""),"",COUNTIFS($C$2:C130,C130,$H$2:H130,1)) -> 1 | M130: =IF(H130<>1,"",IF(COUNTIFS(LOG!$C$2:$C$2001,C130,LOG!$L$2:$L$2001,L130,LOG!$D$2:$D$2001,"BOOKED")>0,1,IF(AND(COUNTIFS(LOG!$C$2:$C$2001,C130,LOG!$L$2:$L$2001,L130,LOG!$D$2:$D$2001,"SENT_LINK")>0,COUNTIFS(LOG!$C$2:$C$2001,C130,LOG!$D$2:$D$2001,"SELF_BOOKED",LOG!$G$2:$G$2001,">"&G130)>0),1,0))) -> 0
A131: 46309.491 | B131: Lead | C131: 9000002802 | D131: SELF_BOOKED | E131: R047 | F131: calendly confirmation | G131: =IF(A131="","",IF(A131>=1,A131,IF(MAX($G$2:G130)=0,INT(SETTINGS!$B$4)+A131,INT(MAX($G$2:G130))+A131+IF(A131<MOD(MAX($G$2:G130),1),1,0)))) -> 46309.491 | H131: =IF(D131="","",IF(IFERROR(VLOOKUP(D131,LISTS!$A$2:$E$10,3,FALSE),0)=0,0,IF(IFERROR(COUNTIFS($C$2:C130,C131,$H$2:H130,1,$G$2:G130,">="&(G131-15/1440)),0)>0,0,1))) -> 0 | I131: =IF(H131=1,C131&"|"&COUNTIFS($C$2:C131,C131,$H$2:H131,1),"") | J131: =IF(D131="","",IF(A131="","Missing time",IF(AND(D131="NO_SLOTS",E131=""),"Write the request ID in column E",IF(C131="","Missing phone",IF(COUNTIF(DESK!$F$2:$F$601,C131)=0,"Phone not found: copy it from your list",IF(E131="","OK",IF(COUNTIFS(DESK!$F$2:$F$601,C131,DESK!$AW$2:$AW$601,E131)=0,"Request ID is not one of theirs: copy it from column D",IF(COUNTIFS(DESK!$F$2:$F$601,C131,DESK!$AW$2:$AW$601,E131,DESK!$L$2:$L$601,1)=0,"That ID is a removed duplicate: use the ID on your list","OK")))))))) -> OK | K131: =IF(E131="","",IFERROR(INDEX(DESK!$B$2:$B$601,MATCH(E131,DESK!$AW$2:$AW$601,0)),"")) -> Partner 002 | L131: =IF(OR(D131="",C131=""),"",COUNTIFS($C$2:C131,C131,$H$2:H131,1)) -> 0 | M131: =IF(H131<>1,"",IF(COUNTIFS(LOG!$C$2:$C$2001,C131,LOG!$L$2:$L$2001,L131,LOG!$D$2:$D$2001,"BOOKED")>0,1,IF(AND(COUNTIFS(LOG!$C$2:$C$2001,C131,LOG!$L$2:$L$2001,L131,LOG!$D$2:$D$2001,"SENT_LINK")>0,COUNTIFS(LOG!$C$2:$C$2001,C131,LOG!$D$2:$D$2001,"SELF_BOOKED",LOG!$G$2:$G$2001,">"&G131)>0),1,0)))
A132: 46309.492 | B132: Lead | C132: 9000002906 | D132: SELF_BOOKED | E132: R412 | F132: calendly confirmation | G132: =IF(A132="","",IF(A132>=1,A132,IF(MAX($G$2:G131)=0,INT(SETTINGS!$B$4)+A132,INT(MAX($G$2:G131))+A132+IF(A132<MOD(MAX($G$2:G131),1),1,0)))) -> 46309.492 | H132: =IF(D132="","",IF(IFERROR(VLOOKUP(D132,LISTS!$A$2:$E$10,3,FALSE),0)=0,0,IF(IFERROR(COUNTIFS($C$2:C131,C132,$H$2:H131,1,$G$2:G131,">="&(G132-15/1440)),0)>0,0,1))) -> 0 | I132: =IF(H132=1,C132&"|"&COUNTIFS($C$2:C132,C132,$H$2:H132,1),"") | J132: =IF(D132="","",IF(A132="","Missing time",IF(AND(D132="NO_SLOTS",E132=""),"Write the request ID in column E",IF(C132="","Missing phone",IF(COUNTIF(DESK!$F$2:$F$601,C132)=0,"Phone not found: copy it from your list",IF(E132="","OK",IF(COUNTIFS(DESK!$F$2:$F$601,C132,DESK!$AW$2:$AW$601,E132)=0,"Request ID is not one of theirs: copy it from column D",IF(COUNTIFS(DESK!$F$2:$F$601,C132,DESK!$AW$2:$AW$601,E132,DESK!$L$2:$L$601,1)=0,"That ID is a removed duplicate: use the ID on your list","OK")))))))) -> OK | K132: =IF(E132="","",IFERROR(INDEX(DESK!$B$2:$B$601,MATCH(E132,DESK!$AW$2:$AW$601,0)),"")) -> Partner 006 | L132: =IF(OR(D132="",C132=""),"",COUNTIFS($C$2:C132,C132,$H$2:H132,1)) -> 0 | M132: =IF(H132<>1,"",IF(COUNTIFS(LOG!$C$2:$C$2001,C132,LOG!$L$2:$L$2001,L132,LOG!$D$2:$D$2001,"BOOKED")>0,1,IF(AND(COUNTIFS(LOG!$C$2:$C$2001,C132,LOG!$L$2:$L$2001,L132,LOG!$D$2:$D$2001,"SENT_LINK")>0,COUNTIFS(LOG!$C$2:$C$2001,C132,LOG!$D$2:$D$2001,"SELF_BOOKED",LOG!$G$2:$G$2001,">"&G132)>0),1,0)))
A133: 46309.494 | B133: Lead | C133: 9000001541 | D133: SELF_BOOKED | E133: R169 | F133: calendly confirmation | G133: =IF(A133="","",IF(A133>=1,A133,IF(MAX($G$2:G132)=0,INT(SETTINGS!$B$4)+A133,INT(MAX($G$2:G132))+A133+IF(A133<MOD(MAX($G$2:G132),1),1,0)))) -> 46309.494 | H133: =IF(D133="","",IF(IFERROR(VLOOKUP(D133,LISTS!$A$2:$E$10,3,FALSE),0)=0,0,IF(IFERROR(COUNTIFS($C$2:C132,C133,$H$2:H132,1,$G$2:G132,">="&(G133-15/1440)),0)>0,0,1))) -> 0 | I133: =IF(H133=1,C133&"|"&COUNTIFS($C$2:C133,C133,$H$2:H133,1),"") | J133: =IF(D133="","",IF(A133="","Missing time",IF(AND(D133="NO_SLOTS",E133=""),"Write the request ID in column E",IF(C133="","Missing phone",IF(COUNTIF(DESK!$F$2:$F$601,C133)=0,"Phone not found: copy it from your list",IF(E133="","OK",IF(COUNTIFS(DESK!$F$2:$F$601,C133,DESK!$AW$2:$AW$601,E133)=0,"Request ID is not one of theirs: copy it from column D",IF(COUNTIFS(DESK!$F$2:$F$601,C133,DESK!$AW$2:$AW$601,E133,DESK!$L$2:$L$601,1)=0,"That ID is a removed duplicate: use the ID on your list","OK")))))))) -> OK | K133: =IF(E133="","",IFERROR(INDEX(DESK!$B$2:$B$601,MATCH(E133,DESK!$AW$2:$AW$601,0)),"")) -> Partner 001 | L133: =IF(OR(D133="",C133=""),"",COUNTIFS($C$2:C133,C133,$H$2:H133,1)) -> 0 | M133: =IF(H133<>1,"",IF(COUNTIFS(LOG!$C$2:$C$2001,C133,LOG!$L$2:$L$2001,L133,LOG!$D$2:$D$2001,"BOOKED")>0,1,IF(AND(COUNTIFS(LOG!$C$2:$C$2001,C133,LOG!$L$2:$L$2001,L133,LOG!$D$2:$D$2001,"SENT_LINK")>0,COUNTIFS(LOG!$C$2:$C$2001,C133,LOG!$D$2:$D$2001,"SELF_BOOKED",LOG!$G$2:$G$2001,">"&G133)>0),1,0)))
A134: 46309.497 | B134: Lead | C134: 9000005077 | D134: SELF_BOOKED | E134: R198 | F134: calendly confirmation | G134: =IF(A134="","",IF(A134>=1,A134,IF(MAX($G$2:G133)=0,INT(SETTINGS!$B$4)+A134,INT(MAX($G$2:G133))+A134+IF(A134<MOD(MAX($G$2:G133),1),1,0)))) -> 46309.497 | H134: =IF(D134="","",IF(IFERROR(VLOOKUP(D134,LISTS!$A$2:$E$10,3,FALSE),0)=0,0,IF(IFERROR(COUNTIFS($C$2:C133,C134,$H$2:H133,1,$G$2:G133,">="&(G134-15/1440)),0)>0,0,1))) -> 0 | I134: =IF(H134=1,C134&"|"&COUNTIFS($C$2:C134,C134,$H$2:H134,1),"") | J134: =IF(D134="","",IF(A134="","Missing time",IF(AND(D134="NO_SLOTS",E134=""),"Write the request ID in column E",IF(C134="","Missing phone",IF(COUNTIF(DESK!$F$2:$F$601,C134)=0,"Phone not found: copy it from your list",IF(E134="","OK",IF(COUNTIFS(DESK!$F$2:$F$601,C134,DESK!$AW$2:$AW$601,E134)=0,"Request ID is not one of theirs: copy it from column D",IF(COUNTIFS(DESK!$F$2:$F$601,C134,DESK!$AW$2:$AW$601,E134,DESK!$L$2:$L$601,1)=0,"That ID is a removed duplicate: use the ID on your list","OK")))))))) -> OK | K134: =IF(E134="","",IFERROR(INDEX(DESK!$B$2:$B$601,MATCH(E134,DESK!$AW$2:$AW$601,0)),"")) -> Partner 039 | L134: =IF(OR(D134="",C134=""),"",COUNTIFS($C$2:C134,C134,$H$2:H134,1)) -> 0 | M134: =IF(H134<>1,"",IF(COUNTIFS(LOG!$C$2:$C$2001,C134,LOG!$L$2:$L$2001,L134,LOG!$D$2:$D$2001,"BOOKED")>0,1,IF(AND(COUNTIFS(LOG!$C$2:$C$2001,C134,LOG!$L$2:$L$2001,L134,LOG!$D$2:$D$2001,"SENT_LINK")>0,COUNTIFS(LOG!$C$2:$C$2001,C134,LOG!$D$2:$D$2001,"SELF_BOOKED",LOG!$G$2:$G$2001,">"&G134)>0),1,0)))
A135: 46309.503 | B135: Shyam | C135: 9000002711 | D135: NO_ANSWER | G135: =IF(A135="","",IF(A135>=1,A135,IF(MAX($G$2:G134)=0,INT(SETTINGS!$B$4)+A135,INT(MAX($G$2:G134))+A135+IF(A135<MOD(MAX($G$2:G134),1),1,0)))) -> 46309.503 | H135: =IF(D135="","",IF(IFERROR(VLOOKUP(D135,LISTS!$A$2:$E$10,3,FALSE),0)=0,0,IF(IFERROR(COUNTIFS($C$2:C134,C135,$H$2:H134,1,$G$2:G134,">="&(G135-15/1440)),0)>0,0,1))) -> 1 | I135: =IF(H135=1,C135&"|"&COUNTIFS($C$2:C135,C135,$H$2:H135,1),"") -> 9000002711|1 | J135: =IF(D135="","",IF(A135="","Missing time",IF(AND(D135="NO_SLOTS",E135=""),"Write the request ID in column E",IF(C135="","Missing phone",IF(COUNTIF(DESK!$F$2:$F$601,C135)=0,"Phone not found: copy it from your list",IF(E135="","OK",IF(COUNTIFS(DESK!$F$2:$F$601,C135,DESK!$AW$2:$AW$601,E135)=0,"Request ID is not one of theirs: copy it from column D",IF(COUNTIFS(DESK!$F$2:$F$601,C135,DESK!$AW$2:$AW$601,E135,DESK!$L$2:$L$601,1)=0,"That ID is a removed duplicate: use the ID on your list","OK")))))))) -> OK | K135: =IF(E135="","",IFERROR(INDEX(DESK!$B$2:$B$601,MATCH(E135,DESK!$AW$2:$AW$601,0)),"")) | L135: =IF(OR(D135="",C135=""),"",COUNTIFS($C$2:C135,C135,$H$2:H135,1)) -> 1 | M135: =IF(H135<>1,"",IF(COUNTIFS(LOG!$C$2:$C$2001,C135,LOG!$L$2:$L$2001,L135,LOG!$D$2:$D$2001,"BOOKED")>0,1,IF(AND(COUNTIFS(LOG!$C$2:$C$2001,C135,LOG!$L$2:$L$2001,L135,LOG!$D$2:$D$2001,"SENT_LINK")>0,COUNTIFS(LOG!$C$2:$C$2001,C135,LOG!$D$2:$D$2001,"SELF_BOOKED",LOG!$G$2:$G$2001,">"&G135)>0),1,0))) -> 0
A136: 46309.504 | B136: Ram | C136: 9000004076 | D136: NO_ANSWER | G136: =IF(A136="","",IF(A136>=1,A136,IF(MAX($G$2:G135)=0,INT(SETTINGS!$B$4)+A136,INT(MAX($G$2:G135))+A136+IF(A136<MOD(MAX($G$2:G135),1),1,0)))) -> 46309.504 | H136: =IF(D136="","",IF(IFERROR(VLOOKUP(D136,LISTS!$A$2:$E$10,3,FALSE),0)=0,0,IF(IFERROR(COUNTIFS($C$2:C135,C136,$H$2:H135,1,$G$2:G135,">="&(G136-15/1440)),0)>0,0,1))) -> 1 | I136: =IF(H136=1,C136&"|"&COUNTIFS($C$2:C136,C136,$H$2:H136,1),"") -> 9000004076|1 | J136: =IF(D136="","",IF(A136="","Missing time",IF(AND(D136="NO_SLOTS",E136=""),"Write the request ID in column E",IF(C136="","Missing phone",IF(COUNTIF(DESK!$F$2:$F$601,C136)=0,"Phone not found: copy it from your list",IF(E136="","OK",IF(COUNTIFS(DESK!$F$2:$F$601,C136,DESK!$AW$2:$AW$601,E136)=0,"Request ID is not one of theirs: copy it from column D",IF(COUNTIFS(DESK!$F$2:$F$601,C136,DESK!$AW$2:$AW$601,E136,DESK!$L$2:$L$601,1)=0,"That ID is a removed duplicate: use the ID on your list","OK")))))))) -> OK | K136: =IF(E136="","",IFERROR(INDEX(DESK!$B$2:$B$601,MATCH(E136,DESK!$AW$2:$AW$601,0)),"")) | L136: =IF(OR(D136="",C136=""),"",COUNTIFS($C$2:C136,C136,$H$2:H136,1)) -> 1 | M136: =IF(H136<>1,"",IF(COUNTIFS(LOG!$C$2:$C$2001,C136,LOG!$L$2:$L$2001,L136,LOG!$D$2:$D$2001,"BOOKED")>0,1,IF(AND(COUNTIFS(LOG!$C$2:$C$2001,C136,LOG!$L$2:$L$2001,L136,LOG!$D$2:$D$2001,"SENT_LINK")>0,COUNTIFS(LOG!$C$2:$C$2001,C136,LOG!$D$2:$D$2001,"SELF_BOOKED",LOG!$G$2:$G$2001,">"&G136)>0),1,0))) -> 0
A137: 46309.507 | B137: Ram | C137: 9000004310 | D137: NO_ANSWER | G137: =IF(A137="","",IF(A137>=1,A137,IF(MAX($G$2:G136)=0,INT(SETTINGS!$B$4)+A137,INT(MAX($G$2:G136))+A137+IF(A137<MOD(MAX($G$2:G136),1),1,0)))) -> 46309.507 | H137: =IF(D137="","",IF(IFERROR(VLOOKUP(D137,LISTS!$A$2:$E$10,3,FALSE),0)=0,0,IF(IFERROR(COUNTIFS($C$2:C136,C137,$H$2:H136,1,$G$2:G136,">="&(G137-15/1440)),0)>0,0,1))) -> 1 | I137: =IF(H137=1,C137&"|"&COUNTIFS($C$2:C137,C137,$H$2:H137,1),"") -> 9000004310|1 | J137: =IF(D137="","",IF(A137="","Missing time",IF(AND(D137="NO_SLOTS",E137=""),"Write the request ID in column E",IF(C137="","Missing phone",IF(COUNTIF(DESK!$F$2:$F$601,C137)=0,"Phone not found: copy it from your list",IF(E137="","OK",IF(COUNTIFS(DESK!$F$2:$F$601,C137,DESK!$AW$2:$AW$601,E137)=0,"Request ID is not one of theirs: copy it from column D",IF(COUNTIFS(DESK!$F$2:$F$601,C137,DESK!$AW$2:$AW$601,E137,DESK!$L$2:$L$601,1)=0,"That ID is a removed duplicate: use the ID on your list","OK")))))))) -> OK | K137: =IF(E137="","",IFERROR(INDEX(DESK!$B$2:$B$601,MATCH(E137,DESK!$AW$2:$AW$601,0)),"")) | L137: =IF(OR(D137="",C137=""),"",COUNTIFS($C$2:C137,C137,$H$2:H137,1)) -> 1 | M137: =IF(H137<>1,"",IF(COUNTIFS(LOG!$C$2:$C$2001,C137,LOG!$L$2:$L$2001,L137,LOG!$D$2:$D$2001,"BOOKED")>0,1,IF(AND(COUNTIFS(LOG!$C$2:$C$2001,C137,LOG!$L$2:$L$2001,L137,LOG!$D$2:$D$2001,"SENT_LINK")>0,COUNTIFS(LOG!$C$2:$C$2001,C137,LOG!$D$2:$D$2001,"SELF_BOOKED",LOG!$G$2:$G$2001,">"&G137)>0),1,0))) -> 0
A138: 46309.507 | B138: Shyam | C138: 9000004089 | D138: NO_ANSWER | G138: =IF(A138="","",IF(A138>=1,A138,IF(MAX($G$2:G137)=0,INT(SETTINGS!$B$4)+A138,INT(MAX($G$2:G137))+A138+IF(A138<MOD(MAX($G$2:G137),1),1,0)))) -> 46309.507 | H138: =IF(D138="","",IF(IFERROR(VLOOKUP(D138,LISTS!$A$2:$E$10,3,FALSE),0)=0,0,IF(IFERROR(COUNTIFS($C$2:C137,C138,$H$2:H137,1,$G$2:G137,">="&(G138-15/1440)),0)>0,0,1))) -> 1 | I138: =IF(H138=1,C138&"|"&COUNTIFS($C$2:C138,C138,$H$2:H138,1),"") -> 9000004089|1 | J138: =IF(D138="","",IF(A138="","Missing time",IF(AND(D138="NO_SLOTS",E138=""),"Write the request ID in column E",IF(C138="","Missing phone",IF(COUNTIF(DESK!$F$2:$F$601,C138)=0,"Phone not found: copy it from your list",IF(E138="","OK",IF(COUNTIFS(DESK!$F$2:$F$601,C138,DESK!$AW$2:$AW$601,E138)=0,"Request ID is not one of theirs: copy it from column D",IF(COUNTIFS(DESK!$F$2:$F$601,C138,DESK!$AW$2:$AW$601,E138,DESK!$L$2:$L$601,1)=0,"That ID is a removed duplicate: use the ID on your list","OK")))))))) -> OK | K138: =IF(E138="","",IFERROR(INDEX(DESK!$B$2:$B$601,MATCH(E138,DESK!$AW$2:$AW$601,0)),"")) | L138: =IF(OR(D138="",C138=""),"",COUNTIFS($C$2:C138,C138,$H$2:H138,1)) -> 1 | M138: =IF(H138<>1,"",IF(COUNTIFS(LOG!$C$2:$C$2001,C138,LOG!$L$2:$L$2001,L138,LOG!$D$2:$D$2001,"BOOKED")>0,1,IF(AND(COUNTIFS(LOG!$C$2:$C$2001,C138,LOG!$L$2:$L$2001,L138,LOG!$D$2:$D$2001,"SENT_LINK")>0,COUNTIFS(LOG!$C$2:$C$2001,C138,LOG!$D$2:$D$2001,"SELF_BOOKED",LOG!$G$2:$G$2001,">"&G138)>0),1,0))) -> 0
A139: 46309.51 | B139: Ram | C139: 9000001268 | D139: NO_ANSWER | G139: =IF(A139="","",IF(A139>=1,A139,IF(MAX($G$2:G138)=0,INT(SETTINGS!$B$4)+A139,INT(MAX($G$2:G138))+A139+IF(A139<MOD(MAX($G$2:G138),1),1,0)))) -> 46309.51 | H139: =IF(D139="","",IF(IFERROR(VLOOKUP(D139,LISTS!$A$2:$E$10,3,FALSE),0)=0,0,IF(IFERROR(COUNTIFS($C$2:C138,C139,$H$2:H138,1,$G$2:G138,">="&(G139-15/1440)),0)>0,0,1))) -> 1 | I139: =IF(H139=1,C139&"|"&COUNTIFS($C$2:C139,C139,$H$2:H139,1),"") -> 9000001268|1 | J139: =IF(D139="","",IF(A139="","Missing time",IF(AND(D139="NO_SLOTS",E139=""),"Write the request ID in column E",IF(C139="","Missing phone",IF(COUNTIF(DESK!$F$2:$F$601,C139)=0,"Phone not found: copy it from your list",IF(E139="","OK",IF(COUNTIFS(DESK!$F$2:$F$601,C139,DESK!$AW$2:$AW$601,E139)=0,"Request ID is not one of theirs: copy it from column D",IF(COUNTIFS(DESK!$F$2:$F$601,C139,DESK!$AW$2:$AW$601,E139,DESK!$L$2:$L$601,1)=0,"That ID is a removed duplicate: use the ID on your list","OK")))))))) -> OK | K139: =IF(E139="","",IFERROR(INDEX(DESK!$B$2:$B$601,MATCH(E139,DESK!$AW$2:$AW$601,0)),"")) | L139: =IF(OR(D139="",C139=""),"",COUNTIFS($C$2:C139,C139,$H$2:H139,1)) -> 1 | M139: =IF(H139<>1,"",IF(COUNTIFS(LOG!$C$2:$C$2001,C139,LOG!$L$2:$L$2001,L139,LOG!$D$2:$D$2001,"BOOKED")>0,1,IF(AND(COUNTIFS(LOG!$C$2:$C$2001,C139,LOG!$L$2:$L$2001,L139,LOG!$D$2:$D$2001,"SENT_LINK")>0,COUNTIFS(LOG!$C$2:$C$2001,C139,LOG!$D$2:$D$2001,"SELF_BOOKED",LOG!$G$2:$G$2001,">"&G139)>0),1,0))) -> 0
A140: 46309.513 | B140: Shyam | C140: 9000003361 | D140: BOOKED | G140: =IF(A140="","",IF(A140>=1,A140,IF(MAX($G$2:G139)=0,INT(SETTINGS!$B$4)+A140,INT(MAX($G$2:G139))+A140+IF(A140<MOD(MAX($G$2:G139),1),1,0)))) -> 46309.513 | H140: =IF(D140="","",IF(IFERROR(VLOOKUP(D140,LISTS!$A$2:$E$10,3,FALSE),0)=0,0,IF(IFERROR(COUNTIFS($C$2:C139,C140,$H$2:H139,1,$G$2:G139,">="&(G140-15/1440)),0)>0,0,1))) -> 1 | I140: =IF(H140=1,C140&"|"&COUNTIFS($C$2:C140,C140,$H$2:H140,1),"") -> 9000003361|1 | J140: =IF(D140="","",IF(A140="","Missing time",IF(AND(D140="NO_SLOTS",E140=""),"Write the request ID in column E",IF(C140="","Missing phone",IF(COUNTIF(DESK!$F$2:$F$601,C140)=0,"Phone not found: copy it from your list",IF(E140="","OK",IF(COUNTIFS(DESK!$F$2:$F$601,C140,DESK!$AW$2:$AW$601,E140)=0,"Request ID is not one of theirs: copy it from column D",IF(COUNTIFS(DESK!$F$2:$F$601,C140,DESK!$AW$2:$AW$601,E140,DESK!$L$2:$L$601,1)=0,"That ID is a removed duplicate: use the ID on your list","OK")))))))) -> OK | K140: =IF(E140="","",IFERROR(INDEX(DESK!$B$2:$B$601,MATCH(E140,DESK!$AW$2:$AW$601,0)),"")) | L140: =IF(OR(D140="",C140=""),"",COUNTIFS($C$2:C140,C140,$H$2:H140,1)) -> 1 | M140: =IF(H140<>1,"",IF(COUNTIFS(LOG!$C$2:$C$2001,C140,LOG!$L$2:$L$2001,L140,LOG!$D$2:$D$2001,"BOOKED")>0,1,IF(AND(COUNTIFS(LOG!$C$2:$C$2001,C140,LOG!$L$2:$L$2001,L140,LOG!$D$2:$D$2001,"SENT_LINK")>0,COUNTIFS(LOG!$C$2:$C$2001,C140,LOG!$D$2:$D$2001,"SELF_BOOKED",LOG!$G$2:$G$2001,">"&G140)>0),1,0))) -> 1
A141: 46309.514 | B141: Ram | C141: 9000005038 | D141: NO_ANSWER | G141: =IF(A141="","",IF(A141>=1,A141,IF(MAX($G$2:G140)=0,INT(SETTINGS!$B$4)+A141,INT(MAX($G$2:G140))+A141+IF(A141<MOD(MAX($G$2:G140),1),1,0)))) -> 46309.514 | H141: =IF(D141="","",IF(IFERROR(VLOOKUP(D141,LISTS!$A$2:$E$10,3,FALSE),0)=0,0,IF(IFERROR(COUNTIFS($C$2:C140,C141,$H$2:H140,1,$G$2:G140,">="&(G141-15/1440)),0)>0,0,1))) -> 1 | I141: =IF(H141=1,C141&"|"&COUNTIFS($C$2:C141,C141,$H$2:H141,1),"") -> 9000005038|1 | J141: =IF(D141="","",IF(A141="","Missing time",IF(AND(D141="NO_SLOTS",E141=""),"Write the request ID in column E",IF(C141="","Missing phone",IF(COUNTIF(DESK!$F$2:$F$601,C141)=0,"Phone not found: copy it from your list",IF(E141="","OK",IF(COUNTIFS(DESK!$F$2:$F$601,C141,DESK!$AW$2:$AW$601,E141)=0,"Request ID is not one of theirs: copy it from column D",IF(COUNTIFS(DESK!$F$2:$F$601,C141,DESK!$AW$2:$AW$601,E141,DESK!$L$2:$L$601,1)=0,"That ID is a removed duplicate: use the ID on your list","OK")))))))) -> OK | K141: =IF(E141="","",IFERROR(INDEX(DESK!$B$2:$B$601,MATCH(E141,DESK!$AW$2:$AW$601,0)),"")) | L141: =IF(OR(D141="",C141=""),"",COUNTIFS($C$2:C141,C141,$H$2:H141,1)) -> 1 | M141: =IF(H141<>1,"",IF(COUNTIFS(LOG!$C$2:$C$2001,C141,LOG!$L$2:$L$2001,L141,LOG!$D$2:$D$2001,"BOOKED")>0,1,IF(AND(COUNTIFS(LOG!$C$2:$C$2001,C141,LOG!$L$2:$L$2001,L141,LOG!$D$2:$D$2001,"SENT_LINK")>0,COUNTIFS(LOG!$C$2:$C$2001,C141,LOG!$D$2:$D$2001,"SELF_BOOKED",LOG!$G$2:$G$2001,">"&G141)>0),1,0))) -> 0
A142: 46309.519 | B142: Ram | C142: 9000002724 | D142: BOOKED | G142: =IF(A142="","",IF(A142>=1,A142,IF(MAX($G$2:G141)=0,INT(SETTINGS!$B$4)+A142,INT(MAX($G$2:G141))+A142+IF(A142<MOD(MAX($G$2:G141),1),1,0)))) -> 46309.519 | H142: =IF(D142="","",IF(IFERROR(VLOOKUP(D142,LISTS!$A$2:$E$10,3,FALSE),0)=0,0,IF(IFERROR(COUNTIFS($C$2:C141,C142,$H$2:H141,1,$G$2:G141,">="&(G142-15/1440)),0)>0,0,1))) -> 1 | I142: =IF(H142=1,C142&"|"&COUNTIFS($C$2:C142,C142,$H$2:H142,1),"") -> 9000002724|1 | J142: =IF(D142="","",IF(A142="","Missing time",IF(AND(D142="NO_SLOTS",E142=""),"Write the request ID in column E",IF(C142="","Missing phone",IF(COUNTIF(DESK!$F$2:$F$601,C142)=0,"Phone not found: copy it from your list",IF(E142="","OK",IF(COUNTIFS(DESK!$F$2:$F$601,C142,DESK!$AW$2:$AW$601,E142)=0,"Request ID is not one of theirs: copy it from column D",IF(COUNTIFS(DESK!$F$2:$F$601,C142,DESK!$AW$2:$AW$601,E142,DESK!$L$2:$L$601,1)=0,"That ID is a removed duplicate: use the ID on your list","OK")))))))) -> OK | K142: =IF(E142="","",IFERROR(INDEX(DESK!$B$2:$B$601,MATCH(E142,DESK!$AW$2:$AW$601,0)),"")) | L142: =IF(OR(D142="",C142=""),"",COUNTIFS($C$2:C142,C142,$H$2:H142,1)) -> 1 | M142: =IF(H142<>1,"",IF(COUNTIFS(LOG!$C$2:$C$2001,C142,LOG!$L$2:$L$2001,L142,LOG!$D$2:$D$2001,"BOOKED")>0,1,IF(AND(COUNTIFS(LOG!$C$2:$C$2001,C142,LOG!$L$2:$L$2001,L142,LOG!$D$2:$D$2001,"SENT_LINK")>0,COUNTIFS(LOG!$C$2:$C$2001,C142,LOG!$D$2:$D$2001,"SELF_BOOKED",LOG!$G$2:$G$2001,">"&G142)>0),1,0))) -> 1
A143: 46309.519 | B143: Shyam | C143: 9000003153 | D143: NO_ANSWER | G143: =IF(A143="","",IF(A143>=1,A143,IF(MAX($G$2:G142)=0,INT(SETTINGS!$B$4)+A143,INT(MAX($G$2:G142))+A143+IF(A143<MOD(MAX($G$2:G142),1),1,0)))) -> 46309.519 | H143: =IF(D143="","",IF(IFERROR(VLOOKUP(D143,LISTS!$A$2:$E$10,3,FALSE),0)=0,0,IF(IFERROR(COUNTIFS($C$2:C142,C143,$H$2:H142,1,$G$2:G142,">="&(G143-15/1440)),0)>0,0,1))) -> 1 | I143: =IF(H143=1,C143&"|"&COUNTIFS($C$2:C143,C143,$H$2:H143,1),"") -> 9000003153|1 | J143: =IF(D143="","",IF(A143="","Missing time",IF(AND(D143="NO_SLOTS",E143=""),"Write the request ID in column E",IF(C143="","Missing phone",IF(COUNTIF(DESK!$F$2:$F$601,C143)=0,"Phone not found: copy it from your list",IF(E143="","OK",IF(COUNTIFS(DESK!$F$2:$F$601,C143,DESK!$AW$2:$AW$601,E143)=0,"Request ID is not one of theirs: copy it from column D",IF(COUNTIFS(DESK!$F$2:$F$601,C143,DESK!$AW$2:$AW$601,E143,DESK!$L$2:$L$601,1)=0,"That ID is a removed duplicate: use the ID on your list","OK")))))))) -> OK | K143: =IF(E143="","",IFERROR(INDEX(DESK!$B$2:$B$601,MATCH(E143,DESK!$AW$2:$AW$601,0)),"")) | L143: =IF(OR(D143="",C143=""),"",COUNTIFS($C$2:C143,C143,$H$2:H143,1)) -> 1 | M143: =IF(H143<>1,"",IF(COUNTIFS(LOG!$C$2:$C$2001,C143,LOG!$L$2:$L$2001,L143,LOG!$D$2:$D$2001,"BOOKED")>0,1,IF(AND(COUNTIFS(LOG!$C$2:$C$2001,C143,LOG!$L$2:$L$2001,L143,LOG!$D$2:$D$2001,"SENT_LINK")>0,COUNTIFS(LOG!$C$2:$C$2001,C143,LOG!$D$2:$D$2001,"SELF_BOOKED",LOG!$G$2:$G$2001,">"&G143)>0),1,0))) -> 0
A144: 46309.518 | B144: Lead | C144: 9000001112 | D144: SELF_BOOKED | E144: R374 | F144: calendly confirmation | G144: =IF(A144="","",IF(A144>=1,A144,IF(MAX($G$2:G143)=0,INT(SETTINGS!$B$4)+A144,INT(MAX($G$2:G143))+A144+IF(A144<MOD(MAX($G$2:G143),1),1,0)))) -> 46309.518 | H144: =IF(D144="","",IF(IFERROR(VLOOKUP(D144,LISTS!$A$2:$E$10,3,FALSE),0)=0,0,IF(IFERROR(COUNTIFS($C$2:C143,C144,$H$2:H143,1,$G$2:G143,">="&(G144-15/1440)),0)>0,0,1))) -> 0 | I144: =IF(H144=1,C144&"|"&COUNTIFS($C$2:C144,C144,$H$2:H144,1),"") | J144: =IF(D144="","",IF(A144="","Missing time",IF(AND(D144="NO_SLOTS",E144=""),"Write the request ID in column E",IF(C144="","Missing phone",IF(COUNTIF(DESK!$F$2:$F$601,C144)=0,"Phone not found: copy it from your list",IF(E144="","OK",IF(COUNTIFS(DESK!$F$2:$F$601,C144,DESK!$AW$2:$AW$601,E144)=0,"Request ID is not one of theirs: copy it from column D",IF(COUNTIFS(DESK!$F$2:$F$601,C144,DESK!$AW$2:$AW$601,E144,DESK!$L$2:$L$601,1)=0,"That ID is a removed duplicate: use the ID on your list","OK")))))))) -> OK | K144: =IF(E144="","",IFERROR(INDEX(DESK!$B$2:$B$601,MATCH(E144,DESK!$AW$2:$AW$601,0)),"")) -> Partner 002 | L144: =IF(OR(D144="",C144=""),"",COUNTIFS($C$2:C144,C144,$H$2:H144,1)) -> 0 | M144: =IF(H144<>1,"",IF(COUNTIFS(LOG!$C$2:$C$2001,C144,LOG!$L$2:$L$2001,L144,LOG!$D$2:$D$2001,"BOOKED")>0,1,IF(AND(COUNTIFS(LOG!$C$2:$C$2001,C144,LOG!$L$2:$L$2001,L144,LOG!$D$2:$D$2001,"SENT_LINK")>0,COUNTIFS(LOG!$C$2:$C$2001,C144,LOG!$D$2:$D$2001,"SELF_BOOKED",LOG!$G$2:$G$2001,">"&G144)>0),1,0)))
A145: 46309.525 | B145: Shyam | C145: 9000003699 | D145: NO_ANSWER | G145: =IF(A145="","",IF(A145>=1,A145,IF(MAX($G$2:G144)=0,INT(SETTINGS!$B$4)+A145,INT(MAX($G$2:G144))+A145+IF(A145<MOD(MAX($G$2:G144),1),1,0)))) -> 46309.525 | H145: =IF(D145="","",IF(IFERROR(VLOOKUP(D145,LISTS!$A$2:$E$10,3,FALSE),0)=0,0,IF(IFERROR(COUNTIFS($C$2:C144,C145,$H$2:H144,1,$G$2:G144,">="&(G145-15/1440)),0)>0,0,1))) -> 1 | I145: =IF(H145=1,C145&"|"&COUNTIFS($C$2:C145,C145,$H$2:H145,1),"") -> 9000003699|2 | J145: =IF(D145="","",IF(A145="","Missing time",IF(AND(D145="NO_SLOTS",E145=""),"Write the request ID in column E",IF(C145="","Missing phone",IF(COUNTIF(DESK!$F$2:$F$601,C145)=0,"Phone not found: copy it from your list",IF(E145="","OK",IF(COUNTIFS(DESK!$F$2:$F$601,C145,DESK!$AW$2:$AW$601,E145)=0,"Request ID is not one of theirs: copy it from column D",IF(COUNTIFS(DESK!$F$2:$F$601,C145,DESK!$AW$2:$AW$601,E145,DESK!$L$2:$L$601,1)=0,"That ID is a removed duplicate: use the ID on your list","OK")))))))) -> OK | K145: =IF(E145="","",IFERROR(INDEX(DESK!$B$2:$B$601,MATCH(E145,DESK!$AW$2:$AW$601,0)),"")) | L145: =IF(OR(D145="",C145=""),"",COUNTIFS($C$2:C145,C145,$H$2:H145,1)) -> 2 | M145: =IF(H145<>1,"",IF(COUNTIFS(LOG!$C$2:$C$2001,C145,LOG!$L$2:$L$2001,L145,LOG!$D$2:$D$2001,"BOOKED")>0,1,IF(AND(COUNTIFS(LOG!$C$2:$C$2001,C145,LOG!$L$2:$L$2001,L145,LOG!$D$2:$D$2001,"SENT_LINK")>0,COUNTIFS(LOG!$C$2:$C$2001,C145,LOG!$D$2:$D$2001,"SELF_BOOKED",LOG!$G$2:$G$2001,">"&G145)>0),1,0))) -> 0
A146: 46309.525 | B146: Ram | C146: 9000001580 | D146: NO_ANSWER | G146: =IF(A146="","",IF(A146>=1,A146,IF(MAX($G$2:G145)=0,INT(SETTINGS!$B$4)+A146,INT(MAX($G$2:G145))+A146+IF(A146<MOD(MAX($G$2:G145),1),1,0)))) -> 46309.525 | H146: =IF(D146="","",IF(IFERROR(VLOOKUP(D146,LISTS!$A$2:$E$10,3,FALSE),0)=0,0,IF(IFERROR(COUNTIFS($C$2:C145,C146,$H$2:H145,1,$G$2:G145,">="&(G146-15/1440)),0)>0,0,1))) -> 1 | I146: =IF(H146=1,C146&"|"&COUNTIFS($C$2:C146,C146,$H$2:H146,1),"") -> 9000001580|2 | J146: =IF(D146="","",IF(A146="","Missing time",IF(AND(D146="NO_SLOTS",E146=""),"Write the request ID in column E",IF(C146="","Missing phone",IF(COUNTIF(DESK!$F$2:$F$601,C146)=0,"Phone not found: copy it from your list",IF(E146="","OK",IF(COUNTIFS(DESK!$F$2:$F$601,C146,DESK!$AW$2:$AW$601,E146)=0,"Request ID is not one of theirs: copy it from column D",IF(COUNTIFS(DESK!$F$2:$F$601,C146,DESK!$AW$2:$AW$601,E146,DESK!$L$2:$L$601,1)=0,"That ID is a removed duplicate: use the ID on your list","OK")))))))) -> OK | K146: =IF(E146="","",IFERROR(INDEX(DESK!$B$2:$B$601,MATCH(E146,DESK!$AW$2:$AW$601,0)),"")) | L146: =IF(OR(D146="",C146=""),"",COUNTIFS($C$2:C146,C146,$H$2:H146,1)) -> 2 | M146: =IF(H146<>1,"",IF(COUNTIFS(LOG!$C$2:$C$2001,C146,LOG!$L$2:$L$2001,L146,LOG!$D$2:$D$2001,"BOOKED")>0,1,IF(AND(COUNTIFS(LOG!$C$2:$C$2001,C146,LOG!$L$2:$L$2001,L146,LOG!$D$2:$D$2001,"SENT_LINK")>0,COUNTIFS(LOG!$C$2:$C$2001,C146,LOG!$D$2:$D$2001,"SELF_BOOKED",LOG!$G$2:$G$2001,">"&G146)>0),1,0))) -> 0
A147: 46309.529 | B147: Ram | C147: 9000003530 | D147: BOOKED | E147: R067 | G147: =IF(A147="","",IF(A147>=1,A147,IF(MAX($G$2:G146)=0,INT(SETTINGS!$B$4)+A147,INT(MAX($G$2:G146))+A147+IF(A147<MOD(MAX($G$2:G146),1),1,0)))) -> 46309.529 | H147: =IF(D147="","",IF(IFERROR(VLOOKUP(D147,LISTS!$A$2:$E$10,3,FALSE),0)=0,0,IF(IFERROR(COUNTIFS($C$2:C146,C147,$H$2:H146,1,$G$2:G146,">="&(G147-15/1440)),0)>0,0,1))) -> 1 | I147: =IF(H147=1,C147&"|"&COUNTIFS($C$2:C147,C147,$H$2:H147,1),"") -> 9000003530|2 | J147: =IF(D147="","",IF(A147="","Missing time",IF(AND(D147="NO_SLOTS",E147=""),"Write the request ID in column E",IF(C147="","Missing phone",IF(COUNTIF(DESK!$F$2:$F$601,C147)=0,"Phone not found: copy it from your list",IF(E147="","OK",IF(COUNTIFS(DESK!$F$2:$F$601,C147,DESK!$AW$2:$AW$601,E147)=0,"Request ID is not one of theirs: copy it from column D",IF(COUNTIFS(DESK!$F$2:$F$601,C147,DESK!$AW$2:$AW$601,E147,DESK!$L$2:$L$601,1)=0,"That ID is a removed duplicate: use the ID on your list","OK")))))))) -> OK | K147: =IF(E147="","",IFERROR(INDEX(DESK!$B$2:$B$601,MATCH(E147,DESK!$AW$2:$AW$601,0)),"")) -> Partner 040 | L147: =IF(OR(D147="",C147=""),"",COUNTIFS($C$2:C147,C147,$H$2:H147,1)) -> 2 | M147: =IF(H147<>1,"",IF(COUNTIFS(LOG!$C$2:$C$2001,C147,LOG!$L$2:$L$2001,L147,LOG!$D$2:$D$2001,"BOOKED")>0,1,IF(AND(COUNTIFS(LOG!$C$2:$C$2001,C147,LOG!$L$2:$L$2001,L147,LOG!$D$2:$D$2001,"SENT_LINK")>0,COUNTIFS(LOG!$C$2:$C$2001,C147,LOG!$D$2:$D$2001,"SELF_BOOKED",LOG!$G$2:$G$2001,">"&G147)>0),1,0))) -> 1
A148: 46309.529 | B148: Ram | C148: 9000003530 | D148: NOT_INTERESTED | E148: R251 | F148: declined this one | G148: =IF(A148="","",IF(A148>=1,A148,IF(MAX($G$2:G147)=0,INT(SETTINGS!$B$4)+A148,INT(MAX($G$2:G147))+A148+IF(A148<MOD(MAX($G$2:G147),1),1,0)))) -> 46309.529 | H148: =IF(D148="","",IF(IFERROR(VLOOKUP(D148,LISTS!$A$2:$E$10,3,FALSE),0)=0,0,IF(IFERROR(COUNTIFS($C$2:C147,C148,$H$2:H147,1,$G$2:G147,">="&(G148-15/1440)),0)>0,0,1))) -> 0 | I148: =IF(H148=1,C148&"|"&COUNTIFS($C$2:C148,C148,$H$2:H148,1),"") | J148: =IF(D148="","",IF(A148="","Missing time",IF(AND(D148="NO_SLOTS",E148=""),"Write the request ID in column E",IF(C148="","Missing phone",IF(COUNTIF(DESK!$F$2:$F$601,C148)=0,"Phone not found: copy it from your list",IF(E148="","OK",IF(COUNTIFS(DESK!$F$2:$F$601,C148,DESK!$AW$2:$AW$601,E148)=0,"Request ID is not one of theirs: copy it from column D",IF(COUNTIFS(DESK!$F$2:$F$601,C148,DESK!$AW$2:$AW$601,E148,DESK!$L$2:$L$601,1)=0,"That ID is a removed duplicate: use the ID on your list","OK")))))))) -> OK | K148: =IF(E148="","",IFERROR(INDEX(DESK!$B$2:$B$601,MATCH(E148,DESK!$AW$2:$AW$601,0)),"")) -> Partner 005 | L148: =IF(OR(D148="",C148=""),"",COUNTIFS($C$2:C148,C148,$H$2:H148,1)) -> 2 | M148: =IF(H148<>1,"",IF(COUNTIFS(LOG!$C$2:$C$2001,C148,LOG!$L$2:$L$2001,L148,LOG!$D$2:$D$2001,"BOOKED")>0,1,IF(AND(COUNTIFS(LOG!$C$2:$C$2001,C148,LOG!$L$2:$L$2001,L148,LOG!$D$2:$D$2001,"SENT_LINK")>0,COUNTIFS(LOG!$C$2:$C$2001,C148,LOG!$D$2:$D$2001,"SELF_BOOKED",LOG!$G$2:$G$2001,">"&G148)>0),1,0)))
A149: 46309.529 | B149: Shyam | C149: 9000002295 | D149: NO_ANSWER | G149: =IF(A149="","",IF(A149>=1,A149,IF(MAX($G$2:G148)=0,INT(SETTINGS!$B$4)+A149,INT(MAX($G$2:G148))+A149+IF(A149<MOD(MAX($G$2:G148),1),1,0)))) -> 46309.529 | H149: =IF(D149="","",IF(IFERROR(VLOOKUP(D149,LISTS!$A$2:$E$10,3,FALSE),0)=0,0,IF(IFERROR(COUNTIFS($C$2:C148,C149,$H$2:H148,1,$G$2:G148,">="&(G149-15/1440)),0)>0,0,1))) -> 1 | I149: =IF(H149=1,C149&"|"&COUNTIFS($C$2:C149,C149,$H$2:H149,1),"") -> 9000002295|2 | J149: =IF(D149="","",IF(A149="","Missing time",IF(AND(D149="NO_SLOTS",E149=""),"Write the request ID in column E",IF(C149="","Missing phone",IF(COUNTIF(DESK!$F$2:$F$601,C149)=0,"Phone not found: copy it from your list",IF(E149="","OK",IF(COUNTIFS(DESK!$F$2:$F$601,C149,DESK!$AW$2:$AW$601,E149)=0,"Request ID is not one of theirs: copy it from column D",IF(COUNTIFS(DESK!$F$2:$F$601,C149,DESK!$AW$2:$AW$601,E149,DESK!$L$2:$L$601,1)=0,"That ID is a removed duplicate: use the ID on your list","OK")))))))) -> OK | K149: =IF(E149="","",IFERROR(INDEX(DESK!$B$2:$B$601,MATCH(E149,DESK!$AW$2:$AW$601,0)),"")) | L149: =IF(OR(D149="",C149=""),"",COUNTIFS($C$2:C149,C149,$H$2:H149,1)) -> 2 | M149: =IF(H149<>1,"",IF(COUNTIFS(LOG!$C$2:$C$2001,C149,LOG!$L$2:$L$2001,L149,LOG!$D$2:$D$2001,"BOOKED")>0,1,IF(AND(COUNTIFS(LOG!$C$2:$C$2001,C149,LOG!$L$2:$L$2001,L149,LOG!$D$2:$D$2001,"SENT_LINK")>0,COUNTIFS(LOG!$C$2:$C$2001,C149,LOG!$D$2:$D$2001,"SELF_BOOKED",LOG!$G$2:$G$2001,">"&G149)>0),1,0))) -> 0
A150: 46309.533 | B150: Shyam | C150: 9000004583 | D150: BOOKED | G150: =IF(A150="","",IF(A150>=1,A150,IF(MAX($G$2:G149)=0,INT(SETTINGS!$B$4)+A150,INT(MAX($G$2:G149))+A150+IF(A150<MOD(MAX($G$2:G149),1),1,0)))) -> 46309.533 | H150: =IF(D150="","",IF(IFERROR(VLOOKUP(D150,LISTS!$A$2:$E$10,3,FALSE),0)=0,0,IF(IFERROR(COUNTIFS($C$2:C149,C150,$H$2:H149,1,$G$2:G149,">="&(G150-15/1440)),0)>0,0,1))) -> 1 | I150: =IF(H150=1,C150&"|"&COUNTIFS($C$2:C150,C150,$H$2:H150,1),"") -> 9000004583|1 | J150: =IF(D150="","",IF(A150="","Missing time",IF(AND(D150="NO_SLOTS",E150=""),"Write the request ID in column E",IF(C150="","Missing phone",IF(COUNTIF(DESK!$F$2:$F$601,C150)=0,"Phone not found: copy it from your list",IF(E150="","OK",IF(COUNTIFS(DESK!$F$2:$F$601,C150,DESK!$AW$2:$AW$601,E150)=0,"Request ID is not one of theirs: copy it from column D",IF(COUNTIFS(DESK!$F$2:$F$601,C150,DESK!$AW$2:$AW$601,E150,DESK!$L$2:$L$601,1)=0,"That ID is a removed duplicate: use the ID on your list","OK")))))))) -> OK | K150: =IF(E150="","",IFERROR(INDEX(DESK!$B$2:$B$601,MATCH(E150,DESK!$AW$2:$AW$601,0)),"")) | L150: =IF(OR(D150="",C150=""),"",COUNTIFS($C$2:C150,C150,$H$2:H150,1)) -> 1 | M150: =IF(H150<>1,"",IF(COUNTIFS(LOG!$C$2:$C$2001,C150,LOG!$L$2:$L$2001,L150,LOG!$D$2:$D$2001,"BOOKED")>0,1,IF(AND(COUNTIFS(LOG!$C$2:$C$2001,C150,LOG!$L$2:$L$2001,L150,LOG!$D$2:$D$2001,"SENT_LINK")>0,COUNTIFS(LOG!$C$2:$C$2001,C150,LOG!$D$2:$D$2001,"SELF_BOOKED",LOG!$G$2:$G$2001,">"&G150)>0),1,0))) -> 1
A151: 46309.533 | B151: Ram | C151: 9000002386 | D151: NO_ANSWER | G151: =IF(A151="","",IF(A151>=1,A151,IF(MAX($G$2:G150)=0,INT(SETTINGS!$B$4)+A151,INT(MAX($G$2:G150))+A151+IF(A151<MOD(MAX($G$2:G150),1),1,0)))) -> 46309.533 | H151: =IF(D151="","",IF(IFERROR(VLOOKUP(D151,LISTS!$A$2:$E$10,3,FALSE),0)=0,0,IF(IFERROR(COUNTIFS($C$2:C150,C151,$H$2:H150,1,$G$2:G150,">="&(G151-15/1440)),0)>0,0,1))) -> 1 | I151: =IF(H151=1,C151&"|"&COUNTIFS($C$2:C151,C151,$H$2:H151,1),"") -> 9000002386|1 | J151: =IF(D151="","",IF(A151="","Missing time",IF(AND(D151="NO_SLOTS",E151=""),"Write the request ID in column E",IF(C151="","Missing phone",IF(COUNTIF(DESK!$F$2:$F$601,C151)=0,"Phone not found: copy it from your list",IF(E151="","OK",IF(COUNTIFS(DESK!$F$2:$F$601,C151,DESK!$AW$2:$AW$601,E151)=0,"Request ID is not one of theirs: copy it from column D",IF(COUNTIFS(DESK!$F$2:$F$601,C151,DESK!$AW$2:$AW$601,E151,DESK!$L$2:$L$601,1)=0,"That ID is a removed duplicate: use the ID on your list","OK")))))))) -> OK | K151: =IF(E151="","",IFERROR(INDEX(DESK!$B$2:$B$601,MATCH(E151,DESK!$AW$2:$AW$601,0)),"")) | L151: =IF(OR(D151="",C151=""),"",COUNTIFS($C$2:C151,C151,$H$2:H151,1)) -> 1 | M151: =IF(H151<>1,"",IF(COUNTIFS(LOG!$C$2:$C$2001,C151,LOG!$L$2:$L$2001,L151,LOG!$D$2:$D$2001,"BOOKED")>0,1,IF(AND(COUNTIFS(LOG!$C$2:$C$2001,C151,LOG!$L$2:$L$2001,L151,LOG!$D$2:$D$2001,"SENT_LINK")>0,COUNTIFS(LOG!$C$2:$C$2001,C151,LOG!$D$2:$D$2001,"SELF_BOOKED",LOG!$G$2:$G$2001,">"&G151)>0),1,0))) -> 0
